Workbook

Sheet README
A1: ROW Module – Consolidated Feature Union
A3: Primary focus | B3: The 'ROW Features' sheet is the deliverable: features for Right-of-Way (ROW) land acquisition, relocation, condemnation, payments, property management, utilities coordination, and the platform capabilities ROW needs (documents, workflow, GIS, reporting, security, integration). It is built only from the six ROW/real-estate requirement documents (NH DOT, Idaho, NMDOT, WSDOT, Austin, Osceola §6.1.7).
A4: City / County sheet | B4: 'City-County ROW Use' is a SEPARATE sheet. It holds requirements for managing USE of public right-of-way (permits, inspections, street/curb data) from city/county-level documents (Detroit, Calgary, Regina, Smart ROW matrix). These are city/county level requirements and are NOT part of the ROW module scope above; they are kept only for reference.
A5: Sheets | B5: ROW Features – the union for the ROW module. City-County ROW Use – separate, reference only. Traceability – every source item behind every feature (verbatim). Sources – the documents and how priority was read. Summary – formula counts. Open Questions – items I could not determine.
A6: Consolidated priority (formula) | B6: Computed from the per-source codes, using the HIGHEST rating any counted source gave: Must Have (M) > Should Have (S) > Could Have (C) > Stated – no priority (E) > Aurigo-only. It means 'at least one source requires it', not agreement – use '# sources', '# sources rating Must' and 'Consensus tier' for weight.
A7: Per-source codes | B7: M = Must/Required. S = Should/Desired/Medium/Preferred. C = Could/Optional/Low. E = stated as needed but no priority given (typical of RFIs). Blank = not mentioned. Exact rule per source is on the Sources sheet; the source's own label is kept in 'Source references'.
A8: Consensus tier | B8: Tier 1 = rated Must by 3+ sources; Tier 2 = Must in 2; Tier 3 = Must in 1; Tier 4 = Should only; Tier 5 = Could only; Tier 6 = stated, no priority. Useful because NH and Idaho rate almost everything as required.
A9: Aurigo coverage columns | B9: Judged ONLY from Aurigo documents in the project (ROW Pro SOW – Original and Pro versions, demo script, deck, library list). 'Covered (SOW)' = named in the SOW; 'Partial' = related but not the full ask; 'Platform / demo only' = in demo script/deck, not SOW; 'Not evidenced' = nothing found in those documents (not the same as 'product lacks it').
A10: 'Also asked by city/county docs' | B10: On ROW Features, this column notes where a city/county document also asks for a similar capability. Those mentions are NOT counted in priority or source counts.
A11: De-duplication caveat | B11: Feature count is my consolidation, not a count of source requirements. Similar asks were merged; report-tool minutiae in the Idaho RFP are summarised in a few features. NH rows with truncated text are not mapped (see Open Questions).
A12: No-guess policy | B12: Descriptions restate what sources say. Undefined terms are quoted, not interpreted; see Notes and Open Questions.
A13: Build roadmap columns | B13: 'ROW Features' columns Z-AC: Release (R01-R35), Release theme, Build sequence (unique 1-323), Depends on. See the 'Release Key' sheet for release themes, rules and assumptions.
A14: New requirements (ROW-233 to ROW-323) | B14: 91 process-step requirements added from New_Requirements.md (rows 236-326 of 'ROW Features'). They come from process sources (SOPs, DOT manual sections, lifecycle stages), not from the six RFP/RFI documents, so columns M-R are blank, priority is 'Stated – no priority', consensus tier is Tier 6, and Aurigo coverage is 'Not assessed (new)'. Evidence is in 'Source references' and on the Traceability sheet (rows marked source code NEW).

Sheet Release Key
A1: ROW BUILD ROADMAP – RELEASE KEY
A2: Release and Build sequence are on the 'ROW Features' sheet (columns Z-AC). They are judgment assignments, not formulas. Each release is a thin, usable slice; sequence is unique (1-323).
A4: Release | B4: Theme | C4: # features | D4: First seq | E4: Last seq | F4: Release in version 2 file | G4: Why it sits here (basis)
A5: R01 | B5: Platform foundation & UI standards | C5: =COUNTIF('ROW Features'!$Z$4:$Z$326,A5) -> 13 | D5: =_xlfn.MINIFS('ROW Features'!$AB$4:$AB$326,'ROW Features'!$Z$4:$Z$326,A5) -> 1 | E5: =_xlfn.MAXIFS('ROW Features'!$AB$4:$AB$326,'ROW Features'!$Z$4:$Z$326,A5) -> 13 | F5: R01 | G5: Everything else is built on hosting, environments, the shared data model, role/field security, audit and the UI standards (accessibility, browsers, usability) that every later form must follow.
A6: R02 | B6: Project & parcel core | C6: =COUNTIF('ROW Features'!$Z$4:$Z$326,A6) -> 11 | D6: =_xlfn.MINIFS('ROW Features'!$AB$4:$AB$326,'ROW Features'!$Z$4:$Z$326,A6) -> 14 | E6: =_xlfn.MAXIFS('ROW Features'!$AB$4:$AB$326,'ROW Features'!$Z$4:$Z$326,A6) -> 24 | F6: R02 | G6: First business slice: a ROW project and its parcels (System Design 3a: Project and Parcel Management comes first), plus the document repository, workflow engine and tasks every later module uses. Parent-tract and tax-parcel link (ROW-233) attaches to the parcel record.
A7: R03 | B7: Owners, stakeholders & parcel team | C7: =COUNTIF('ROW Features'!$Z$4:$Z$326,A7) -> 9 | D7: =_xlfn.MINIFS('ROW Features'!$AB$4:$AB$326,'ROW Features'!$Z$4:$Z$326,A7) -> 25 | E7: =_xlfn.MAXIFS('ROW Features'!$AB$4:$AB$326,'ROW Features'!$Z$4:$Z$326,A7) -> 33 | F7: R03 | G7: Owners, interests, contacts and team roles hang off the parcel (System Design: M1 -> M2). Demographics and tax data are captured here so payments and Title VI reporting have the data later.
A8: R04 | B8: Project funding, parcel depth, acquisition plan & map viewer | C8: =COUNTIF('ROW Features'!$Z$4:$Z$326,A8) -> 12 | D8: =_xlfn.MINIFS('ROW Features'!$AB$4:$AB$326,'ROW Features'!$Z$4:$Z$326,A8) -> 34 | E8: =_xlfn.MAXIFS('ROW Features'!$AB$4:$AB$326,'ROW Features'!$Z$4:$Z$326,A8) -> 45 | F8: R04 | G8: Deepens the parcel and project records (funding, estimates, budgets, acquisition plan, interests by type, grouping, split/combine, batch updates) and adds the map viewer that appraisal, utilities and inventory reuse.
A9: R05 | B9: Templates, correspondence & e-signature | C9: =COUNTIF('ROW Features'!$Z$4:$Z$326,A9) -> 4 | D9: =_xlfn.MINIFS('ROW Features'!$AB$4:$AB$326,'ROW Features'!$Z$4:$Z$326,A9) -> 46 | E9: =_xlfn.MAXIFS('ROW Features'!$AB$4:$AB$326,'ROW Features'!$Z$4:$Z$326,A9) -> 49 | F9: R05 | G9: Templates, mail merge and e-signature are needed by hearing notices and title reports (R07), notices to owners (R06), offers (R11) and relocation notices (R18), so they come first.
A10: R06 | B10: Acquisition rules, authorization, compliance & alerts | C10: =COUNTIF('ROW Features'!$Z$4:$Z$326,A10) -> 16 | D10: =_xlfn.MINIFS('ROW Features'!$AB$4:$AB$326,'ROW Features'!$Z$4:$Z$326,A10) -> 50 | E10: =_xlfn.MAXIFS('ROW Features'!$AB$4:$AB$326,'ROW Features'!$Z$4:$Z$326,A10) -> 65 | F10: R06 | G10: System Design: the Acquisition Process and Compliance Engine governs Acquisition and Negotiation. ROW authorization, site visit, Notice to Owner and the plan-review gate belong to the pre-acquisition steps in Diagram 1. Alerts are built here because deadline and next-action reminders depend on them.
A11: R07 | B11: Title & abstraction | C11: =COUNTIF('ROW Features'!$Z$4:$Z$326,A11) -> 15 | D11: =_xlfn.MINIFS('ROW Features'!$AB$4:$AB$326,'ROW Features'!$Z$4:$Z$326,A11) -> 66 | E11: =_xlfn.MAXIFS('ROW Features'!$AB$4:$AB$326,'ROW Features'!$Z$4:$Z$326,A11) -> 80 | F11: R07 | G11: Title and survey both feed appraisal (System Design: M3 and M4 -> M5). Title ordering is built before title research. Uses document versioning, role-based confidential access (R01) and mail merge (R05).
A12: R08 | B12: Survey, plans & appraisal package | C12: =COUNTIF('ROW Features'!$Z$4:$Z$326,A12) -> 9 | D12: =_xlfn.MINIFS('ROW Features'!$AB$4:$AB$326,'ROW Features'!$Z$4:$Z$326,A12) -> 81 | E12: =_xlfn.MAXIFS('ROW Features'!$AB$4:$AB$326,'ROW Features'!$Z$4:$Z$326,A12) -> 89 | F12: R08 | G12: Survey data and CAD files feed appraisal (System Design: M4 -> M5). GIS quality check, legal/sketch review and appraisal package assembly close out Diagram 2 and hand the parcel to appraisal.
A13: R09 | B13: Appraisal core | Utilities core (parallel track) | C13: =COUNTIF('ROW Features'!$Z$4:$Z$326,A13) -> 20 | D13: =_xlfn.MINIFS('ROW Features'!$AB$4:$AB$326,'ROW Features'!$Z$4:$Z$326,A13) -> 90 | E13: =_xlfn.MAXIFS('ROW Features'!$AB$4:$AB$326,'ROW Features'!$Z$4:$Z$326,A13) -> 109 | F13: R09 | G13: Appraisal intake needs the assembled package (R08). Utilities run in parallel with acquisition per your direction; the utilities core needs only project, parcel, tasks and documents.
A14: R10 | B14: Appraisal depth | Utilities agreements & reimbursement (parallel track) | C14: =COUNTIF('ROW Features'!$Z$4:$Z$326,A14) -> 20 | D14: =_xlfn.MINIFS('ROW Features'!$AB$4:$AB$326,'ROW Features'!$Z$4:$Z$326,A14) -> 110 | E14: =_xlfn.MAXIFS('ROW Features'!$AB$4:$AB$326,'ROW Features'!$Z$4:$Z$326,A14) -> 129 | F14: R10 | G14: Appraiser management, report writing, specialty reports and comparable-sales data build on the appraisal core and the R04 map viewer. On the utilities track: prior rights, cost authorization, relocation notices, estimate review, Buy America and milestones build on the utilities core and its agreements.
A15: R11 | B15: Pre-offer review, offers & negotiation | C15: =COUNTIF('ROW Features'!$Z$4:$Z$326,A15) -> 13 | D15: =_xlfn.MINIFS('ROW Features'!$AB$4:$AB$326,'ROW Features'!$Z$4:$Z$326,A15) -> 130 | E15: =_xlfn.MAXIFS('ROW Features'!$AB$4:$AB$326,'ROW Features'!$Z$4:$Z$326,A15) -> 142 | F15: R11 | G15: Offers start only after just compensation is approved (R09). Management review, funding check and approval thresholds come before the first offer. Impasse data created here feeds condemnation (R21).
A16: R12 | B16: Agreements, easements & alternative acquisition paths | C16: =COUNTIF('ROW Features'!$Z$4:$Z$326,A16) -> 9 | D16: =_xlfn.MINIFS('ROW Features'!$AB$4:$AB$326,'ROW Features'!$Z$4:$Z$326,A16) -> 143 | E16: =_xlfn.MAXIFS('ROW Features'!$AB$4:$AB$326,'ROW Features'!$Z$4:$Z$326,A16) -> 151 | F16: R12 | G16: Agreement approval, subordination letters, easements, key turnover and environmental site assessments follow the settlement (R11). Donation, developer-conveyance and early-acquisition paths reuse the configurable acquisition workflow (ROW-071).
... A39: R35 | B39: Rail & transit (NH-specific) | C39: =COUNTIF('ROW Features'!$Z$4:$Z$326,A39) -> 5 | D39: =_xlfn.MINIFS('ROW Features'!$AB$4:$AB$326,'ROW Features'!$Z$4:$Z$326,A39) -> 319 | E39: =_xlfn.MAXIFS('ROW Features'!$AB$4:$AB$326,'ROW Features'!$Z$4:$Z$326,A39) -> 323 | F39: R28 | G39: Per your direction, NH-specific rail items go last. NH has not defined several of its named systems (see Open Questions #5-6).
B40: Total | C40: =SUM(C5:C39) -> 323
A42: Rules applied
A43: 1. Dependency first: a feature is never built before something it needs. Every 'Depends on' ID has a lower build sequence than the feature itself.
A44: 2. Within the same dependency level, existing features are ordered by Consensus tier (sources rating Must, then number of sources). The 91 new features (ROW-233 to ROW-323) have no tier, so they follow existing features at the same level and are then ordered by ID.
A45: 3. Nothing is treated as already built: Aurigo coverage columns were NOT used for ordering (your direction: fresh start, existing items are to-do).
A46: 4. Thin slices: each release is a coherent set a user group can use. Process order follows the System Design arrows and the numbered process diagrams (project/parcel -> owners/title/survey -> appraisal -> acquisition -> payments -> relocation / condemnation -> clearance -> certification; property management after acquisition).
A47: 5. Parallel tracks (your direction): Utilities run alongside appraisal and payments (R09, R10, R14); web inspection and mobile/field access are delivered together (R27).
A48: 6. Last (your direction): external portals (R32), integrations (R33-R34) and NH-specific rail items (R35). Payments are tracked in-system first (R13); finance integration is R33.
A49: 7. Overlapping features are delivered in the same release, not merged or flagged: ROW-111 and ROW-211 (R33); ROW-058, ROW-107, ROW-108 and ROW-243 (R13); ROW-083 and ROW-292 (R26); ROW-140 and ROW-301 (R29); ROW-139 and ROW-296 (R28).
A50: 8. Not used for ordering (your direction): deadlines and security-certification gating. Certifications (ROW-217) sit in R30.
A52: Assumptions to confirm
A53: A. First customer go-live candidate = after R17 (standard acquisition from project through closing and parcel closure, with data migration and production readiness). Relocation, condemnation, clearance, certification and property management follow. You did not specify a go-live point; move it if needed.
A54: B. System Design shows title and survey feeding appraisal, so appraisal (R09) comes after R07-R08 even though that delays the first end-to-end slice.
... A59: G. Release numbers changed from version 2 because new features needed new slices. Column F shows the version 2 release for each current release.

Sheet ROW Features
A1: ROW MODULE FEATURES – built from ROW / real-estate documents only. City/county permitting & street-data requirements are on the separate 'City-County ROW Use' sheet.
A3: Feature ID | B3: Domain | C3: Category | D3: Sub-category | E3: Feature | F3: Description (plain English) | G3: Requirement type | H3: Consolidated priority | I3: # sources | J3: # sources rating Must | K3: Breadth | L3: Consensus tier | M3: NH | N3: ID | O3: NM | P3: WA | Q3: ATX | R3: OSC | S3: Source references (document – location [source's own priority label]) | T3: Regulation / standard cited | U3: Named systems / tools | V3: Aurigo ROW Pro coverage (provided docs only) | W3: Aurigo evidence | X3: Notes / open questions | Y3: Also asked by city/county docs (not counted) | Z3: Release | AA3: Release theme | AB3: Build sequence (1 = build first) | AC3: Depends on (feature IDs built earlier)
A4: ROW-001 | B4: Land Acquisition & Relocation | C4: Project & Parcel Setup | D4: Project record | E4: ROW project set-up with unique project ID | F4: Create a ROW project record with a unique project number and descriptive data (location, description, project/parcel information). The Aurigo demo script notes the number can be auto-generated or pulled from another system. | G4: Functional | H4: =IF(COUNTIF(M4:R4,"M")>0,"Must Have",IF(COUNTIF(M4:R4,"S")>0,"Should Have",IF(COUNTIF(M4:R4,"C")>0,"Could Have",IF(COUNTA(M4:R4)>0,"Stated – no priority","Aurigo-only (no RFP source)")))) -> Must Have | I4: =COUNTA(M4:R4) -> 2 | J4: =COUNTIF(M4:R4,"M") -> 1 | K4: =IF(I4=0,"Aurigo-only",IF(I4=1,"Single source",IF(I4=2,"Two sources",IF(I4<=4,"Common (3-4)","Broad (5+)")))) -> Two sources | L4: =IF(J4>=3,"Tier 1: Must in 3+ sources",IF(J4=2,"Tier 2: Must in 2 sources",IF(J4=1,"Tier 3: Must in 1 source",IF(COUNTIF(M4:R4,"S")>0,"Tier 4: Should only",IF(COUNTIF(M4:R4,"C")>0,"Tier 5: Could only",IF(I4>0,"Tier 6: stated, no priority","Aurigo-only")))))) -> Tier 3: Must in 1 source | N4: M | P4: E | S4: Idaho ITD RFP Event 85 – ROWMS: §9 Scope of Work ['must' requirement (§9)] WSDOT RFI (2023): Perf. Requirements – Baseline System Capabilities [RFI – performance requirement list (no priority given)] | V4: Covered (SOW) | W4: Pro SOW: 'Project/Land Entity', 'Project Location'; Demo: ROW Project Details form | Z4: R02 | AA4: Project & parcel core | AB4: 14 | AC4: ROW-084, ROW-212
A5: ROW-002 | B5: Land Acquisition & Relocation | C5: Project & Parcel Setup | D5: Project record | E5: Configurable multi-level Work Breakdown Structure (WBS) | F5: Break a project into configurable levels (example in the source: project, phase, task, activity, sub-activity, line item, category, parcel, sub-parcel, county, city). | G5: Functional | H5: =IF(COUNTIF(M5:R5,"M")>0,"Must Have",IF(COUNTIF(M5:R5,"S")>0,"Should Have",IF(COUNTIF(M5:R5,"C")>0,"Could Have",IF(COUNTA(M5:R5)>0,"Stated – no priority","Aurigo-only (no RFP source)")))) -> Must Have | I5: =COUNTA(M5:R5) -> 1 | J5: =COUNTIF(M5:R5,"M") -> 1 | K5: =IF(I5=0,"Aurigo-only",IF(I5=1,"Single source",IF(I5=2,"Two sources",IF(I5<=4,"Common (3-4)","Broad (5+)")))) -> Single source | L5: =IF(J5>=3,"Tier 1: Must in 3+ sources",IF(J5=2,"Tier 2: Must in 2 sources",IF(J5=1,"Tier 3: Must in 1 source",IF(COUNTIF(M5:R5,"S")>0,"Tier 4: Should only",IF(COUNTIF(M5:R5,"C")>0,"Tier 5: Could only",IF(I5>0,"Tier 6: stated, no priority","Aurigo-only")))))) -> Tier 3: Must in 1 source | N5: M | S5: Idaho ITD RFP Event 85 – ROWMS: §9 Scope of Work ['must' requirement (§9)] | V5: Not evidenced | W5: No matching item found in the provided Aurigo documents (SOW, demo script, deck, library list). | Z5: R02 | AA5: Project & parcel core | AB5: 17 | AC5: ROW-001
A6: ROW-003 | B6: Land Acquisition & Relocation | C6: Project & Parcel Setup | D6: Project record | E6: Project tracking by region / district | F6: Track projects by the agency's regions or districts and filter/report by region or district. | G6: Functional | H6: =IF(COUNTIF(M6:R6,"M")>0,"Must Have",IF(COUNTIF(M6:R6,"S")>0,"Should Have",IF(COUNTIF(M6:R6,"C")>0,"Could Have",IF(COUNTA(M6:R6)>0,"Stated – no priority","Aurigo-only (no RFP source)")))) -> Must Have | I6: =COUNTA(M6:R6) -> 3 | J6: =COUNTIF(M6:R6,"M") -> 2 | K6: =IF(I6=0,"Aurigo-only",IF(I6=1,"Single source",IF(I6=2,"Two sources",IF(I6<=4,"Common (3-4)","Broad (5+)")))) -> Common (3-4) | L6: =IF(J6>=3,"Tier 1: Must in 3+ sources",IF(J6=2,"Tier 2: Must in 2 sources",IF(J6=1,"Tier 3: Must in 1 source",IF(COUNTIF(M6:R6,"S")>0,"Tier 4: Should only",IF(COUNTIF(M6:R6,"C")>0,"Tier 5: Could only",IF(I6>0,"Tier 6: stated, no priority","Aurigo-only")))))) -> Tier 2: Must in 2 sources | M6: M | N6: M | P6: E | S6: NH DOT ROWMS & Rail Requirements: Tab 7 Administrative – row 19 [Required / High]; Tab 6 Property Mgmt – row 20 [Required / High] Idaho ITD RFP Event 85 – ROWMS: §9 Management Reporting - General ['must' requirement (§9)] WSDOT RFI (2023): Perf. Requirements – Baseline System Capabilities [RFI – performance requirement list (no priority given)] | V6: Not evidenced | W6: No matching item found in the provided Aurigo documents (SOW, demo script, deck, library list). | X6: Filtering by region/district appears in NH (Admin tab and Property Mgmt reporting) and Idaho (dashboard district filter). | Z6: R02 | AA6: Project & parcel core | AB6: 16 | AC6: ROW-001
A7: ROW-004 | B7: Land Acquisition & Relocation | C7: Project & Parcel Setup | D7: Project record | E7: Project funding & estimate capture | F7: Record funding source and amount, design estimate and current estimate, and construction dates (letting, plan turn-in, projected construction start/completion) on the ROW project. | G7: Functional | H7: =IF(COUNTIF(M7:R7,"M")>0,"Must Have",IF(COUNTIF(M7:R7,"S")>0,"Should Have",IF(COUNTIF(M7:R7,"C")>0,"Could Have",IF(COUNTA(M7:R7)>0,"Stated – no priority","Aurigo-only (no RFP source)")))) -> Aurigo-only (no RFP source) | I7: =COUNTA(M7:R7) -> 0 | J7: =COUNTIF(M7:R7,"M") -> 0 | K7: =IF(I7=0,"Aurigo-only",IF(I7=1,"Single source",IF(I7=2,"Two sources",IF(I7<=4,"Common (3-4)","Broad (5+)")))) -> Aurigo-only | L7: =IF(J7>=3,"Tier 1: Must in 3+ sources",IF(J7=2,"Tier 2: Must in 2 sources",IF(J7=1,"Tier 3: Must in 1 source",IF(COUNTIF(M7:R7,"S")>0,"Tier 4: Should only",IF(COUNTIF(M7:R7,"C")>0,"Tier 5: Could only",IF(I7>0,"Tier 6: stated, no priority","Aurigo-only")))))) -> Aurigo-only | V7: Platform / demo only | W7: Demo script: ROW Project Details form (Funding Information, Design/Current Estimate, Construction Details) | X7: Aurigo-only: seen in the demo script, not requested in any provided RFP/RFI as a stand-alone item. | Z7: R04 | AA7: Project funding, parcel depth, acquisition plan & map viewer | AB7: 34 | AC7: ROW-001
A8: ROW-005 | B8: Land Acquisition & Relocation | C8: Project & Parcel Setup | D8: Parcel record | E8: Parcel record and parcel-level case tracking | F8: Manage each parcel as its own record (parcel number, legal description, address, area, type of property, tenant, status) and track the acquisition case at parcel level through its milestones. NH adds that data entered once should cascade to relocation needs. | G8: Functional | H8: =IF(COUNTIF(M8:R8,"M")>0,"Must Have",IF(COUNTIF(M8:R8,"S")>0,"Should Have",IF(COUNTIF(M8:R8,"C")>0,"Could Have",IF(COUNTA(M8:R8)>0,"Stated – no priority","Aurigo-only (no RFP source)")))) -> Must Have | I8: =COUNTA(M8:R8) -> 4 | J8: =COUNTIF(M8:R8,"M") -> 3 | K8: =IF(I8=0,"Aurigo-only",IF(I8=1,"Single source",IF(I8=2,"Two sources",IF(I8<=4,"Common (3-4)","Broad (5+)")))) -> Common (3-4) | L8: =IF(J8>=3,"Tier 1: Must in 3+ sources",IF(J8=2,"Tier 2: Must in 2 sources",IF(J8=1,"Tier 3: Must in 1 source",IF(COUNTIF(M8:R8,"S")>0,"Tier 4: Should only",IF(COUNTIF(M8:R8,"C")>0,"Tier 5: Could only",IF(I8>0,"Tier 6: stated, no priority","Aurigo-only")))))) -> Tier 1: Must in 3+ sources | M8: M | N8: M | P8: E | Q8: M | S8: NH DOT ROWMS & Rail Requirements: Tab 2 ROW Agent – row 4 [Required / High]; Tab 6 Property Mgmt – row 3 [Required / High] Idaho ITD RFP Event 85 – ROWMS: §9 Project Information Requirements ['must' requirement (§9)] WSDOT RFI (2023): Perf. Requirements – Property Acquisition & Relocation Services [RFI – performance requirement list (no priority given)] Austin Transit Partnership RFQ (2025): Scope – IV. Data Requirements [RFQ – requirement listed in scope] | V8: Covered (SOW) | W8: Pro SOW: 'Parcel', 'Parcel Location', 'Design Details'; Demo: Parcel Details form (status auto-updates from child forms) | Z8: R02 | AA8: Project & parcel core | AB8: 15 | AC8: ROW-001
A9: ROW-006 | B9: Land Acquisition & Relocation | C9: Project & Parcel Setup | D9: Parcel record | E9: Parcel grouping under projects / corridors with roll-up | F9: Group parcels under projects or corridors and roll their data up for reporting. | G9: Functional | H9: =IF(COUNTIF(M9:R9,"M")>0,"Must Have",IF(COUNTIF(M9:R9,"S")>0,"Should Have",IF(COUNTIF(M9:R9,"C")>0,"Could Have",IF(COUNTA(M9:R9)>0,"Stated – no priority","Aurigo-only (no RFP source)")))) -> Must Have | I9: =COUNTA(M9:R9) -> 1 | J9: =COUNTIF(M9:R9,"M") -> 1 | K9: =IF(I9=0,"Aurigo-only",IF(I9=1,"Single source",IF(I9=2,"Two sources",IF(I9<=4,"Common (3-4)","Broad (5+)")))) -> Single source | L9: =IF(J9>=3,"Tier 1: Must in 3+ sources",IF(J9=2,"Tier 2: Must in 2 sources",IF(J9=1,"Tier 3: Must in 1 source",IF(COUNTIF(M9:R9,"S")>0,"Tier 4: Should only",IF(COUNTIF(M9:R9,"C")>0,"Tier 5: Could only",IF(I9>0,"Tier 6: stated, no priority","Aurigo-only")))))) -> Tier 3: Must in 1 source | M9: M | S9: NH DOT ROWMS & Rail Requirements: Tab 2 ROW Agent – row 6 [Required / High] | V9: Partial | W9: Demo: parcels sit under the ROW Project navigation tree; corridor grouping not evidenced | Z9: R04 | AA9: Project funding, parcel depth, acquisition plan & map viewer | AB9: 39 | AC9: ROW-005
A10: ROW-007 | B10: Land Acquisition & Relocation | C10: Project & Parcel Setup | D10: Parcel record | E10: Combine / split parcels and remnant (uneconomic remainder) creation | F10: Combine or split parcel records; flag a parcel or part of one as a potential uneconomic remnant/remainder and assign it a new parcel number and ID. NH also asks to transfer post-construction remnants and classify them (e.g., surplus). | G10: Functional | H10: =IF(COUNTIF(M10:R10,"M")>0,"Must Have",IF(COUNTIF(M10:R10,"S")>0,"Should Have",IF(COUNTIF(M10:R10,"C")>0,"Could Have",IF(COUNTA(M10:R10)>0,"Stated – no priority","Aurigo-only (no RFP source)")))) -> Must Have | I10: =COUNTA(M10:R10) -> 2 | J10: =COUNTIF(M10:R10,"M") -> 1 | K10: =IF(I10=0,"Aurigo-only",IF(I10=1,"Single source",IF(I10=2,"Two sources",IF(I10<=4,"Common (3-4)","Broad (5+)")))) -> Two sources | L10: =IF(J10>=3,"Tier 1: Must in 3+ sources",IF(J10=2,"Tier 2: Must in 2 sources",IF(J10=1,"Tier 3: Must in 1 source",IF(COUNTIF(M10:R10,"S")>0,"Tier 4: Should only",IF(COUNTIF(M10:R10,"C")>0,"Tier 5: Could only",IF(I10>0,"Tier 6: stated, no priority","Aurigo-only")))))) -> Tier 3: Must in 1 source | M10: S | N10: M | S10: NH DOT ROWMS & Rail Requirements: Tab 6 Property Mgmt – row 7 [Desired / Medium] Idaho ITD RFP Event 85 – ROWMS: §9 Appraisal Requirements ['must' requirement (§9)] | V10: Covered (SOW) | W10: Pro SOW: 'Combine/Split Parcels' (ROW-level core process) | Z10: R04 | AA10: Project funding, parcel depth, acquisition plan & map viewer | AB10: 38 | AC10: ROW-005
A11: ROW-008 | B11: Land Acquisition & Relocation | C11: Project & Parcel Setup | D11: Parcel record | E11: Batch updates for multi-parcel projects | F11: Update many parcels at once (multi-parcel projects or corridor-wide additions) and support batch data entry. | G11: Functional | H11: =IF(COUNTIF(M11:R11,"M")>0,"Must Have",IF(COUNTIF(M11:R11,"S")>0,"Should Have",IF(COUNTIF(M11:R11,"C")>0,"Could Have",IF(COUNTA(M11:R11)>0,"Stated – no priority","Aurigo-only (no RFP source)")))) -> Must Have | I11: =COUNTA(M11:R11) -> 1 | J11: =COUNTIF(M11:R11,"M") -> 1 | K11: =IF(I11=0,"Aurigo-only",IF(I11=1,"Single source",IF(I11=2,"Two sources",IF(I11<=4,"Common (3-4)","Broad (5+)")))) -> Single source | L11: =IF(J11>=3,"Tier 1: Must in 3+ sources",IF(J11=2,"Tier 2: Must in 2 sources",IF(J11=1,"Tier 3: Must in 1 source",IF(COUNTIF(M11:R11,"S")>0,"Tier 4: Should only",IF(COUNTIF(M11:R11,"C")>0,"Tier 5: Could only",IF(I11>0,"Tier 6: stated, no priority","Aurigo-only")))))) -> Tier 3: Must in 1 source | M11: M | S11: NH DOT ROWMS & Rail Requirements: Tab 6 Property Mgmt – row 6 [Required / High]; Tab 7 Administrative – row 29 [Required / High] | V11: Not evidenced | W11: No matching item found in the provided Aurigo documents (SOW, demo script, deck, library list). | Z11: R04 | AA11: Project funding, parcel depth, acquisition plan & map viewer | AB11: 40 | AC11: ROW-005
A12: ROW-009 | B12: Land Acquisition & Relocation | C12: Project & Parcel Setup | D12: Parcel record | E12: Parcel synopsis / summary view and print | F12: Display or print a one-page summary of a parcel (location, owners, contacts, leases, tenants, title information). | G12: Functional | H12: =IF(COUNTIF(M12:R12,"M")>0,"Must Have",IF(COUNTIF(M12:R12,"S")>0,"Should Have",IF(COUNTIF(M12:R12,"C")>0,"Could Have",IF(COUNTA(M12:R12)>0,"Stated – no priority","Aurigo-only (no RFP source)")))) -> Must Have | I12: =COUNTA(M12:R12) -> 1 | J12: =COUNTIF(M12:R12,"M") -> 1 | K12: =IF(I12=0,"Aurigo-only",IF(I12=1,"Single source",IF(I12=2,"Two sources",IF(I12<=4,"Common (3-4)","Broad (5+)")))) -> Single source | L12: =IF(J12>=3,"Tier 1: Must in 3+ sources",IF(J12=2,"Tier 2: Must in 2 sources",IF(J12=1,"Tier 3: Must in 1 source",IF(COUNTIF(M12:R12,"S")>0,"Tier 4: Should only",IF(COUNTIF(M12:R12,"C")>0,"Tier 5: Could only",IF(I12>0,"Tier 6: stated, no priority","Aurigo-only")))))) -> Tier 3: Must in 1 source | N12: M | S12: Idaho ITD RFP Event 85 – ROWMS: §9 Negotiation and Acquisition Requirements ['must' requirement (§9)] | V12: Partial | W12: Demo: Parcel form shows Grantee, Appraisal, Agreement and Easement summaries | Z12: R04 | AA12: Project funding, parcel depth, acquisition plan & map viewer | AB12: 41 | AC12: ROW-005, ROW-014
A13: ROW-010 | B13: Land Acquisition & Relocation | C13: Project & Parcel Setup | D13: Parcel record | E13: Parcel milestone tracking with dates | F13: Track acquisition milestones per parcel with scheduled/completed dates and status (e.g., title verification, offer delivery, negotiation, acceptance, closing). | G13: Functional | H13: =IF(COUNTIF(M13:R13,"M")>0,"Must Have",IF(COUNTIF(M13:R13,"S")>0,"Should Have",IF(COUNTIF(M13:R13,"C")>0,"Could Have",IF(COUNTA(M13:R13)>0,"Stated – no priority","Aurigo-only (no RFP source)")))) -> Must Have | I13: =COUNTA(M13:R13) -> 2 | J13: =COUNTIF(M13:R13,"M") -> 2 | K13: =IF(I13=0,"Aurigo-only",IF(I13=1,"Single source",IF(I13=2,"Two sources",IF(I13<=4,"Common (3-4)","Broad (5+)")))) -> Two sources | L13: =IF(J13>=3,"Tier 1: Must in 3+ sources",IF(J13=2,"Tier 2: Must in 2 sources",IF(J13=1,"Tier 3: Must in 1 source",IF(COUNTIF(M13:R13,"S")>0,"Tier 4: Should only",IF(COUNTIF(M13:R13,"C")>0,"Tier 5: Could only",IF(I13>0,"Tier 6: stated, no priority","Aurigo-only")))))) -> Tier 2: Must in 2 sources | M13: M | Q13: M | S13: NH DOT ROWMS & Rail Requirements: Tab 2 ROW Agent – row 13 [Required / High] Austin Transit Partnership RFQ (2025): Scope – A. Data Management [RFQ – requirement listed in scope] | V13: Covered (SOW) | W13: Demo: Parcel Milestones grid and Agreement Milestones grid | Z13: R02 | AA13: Project & parcel core | AB13: 18 | AC13: ROW-005
A14: ROW-011 | B14: Land Acquisition & Relocation | C14: Project & Parcel Setup | D14: Parcel record | E14: Configurable parcel attributes | F14: Attach typed attributes with status and comments to a parcel, chosen from an admin-managed library. | G14: Functional | H14: =IF(COUNTIF(M14:R14,"M")>0,"Must Have",IF(COUNTIF(M14:R14,"S")>0,"Should Have",IF(COUNTIF(M14:R14,"C")>0,"Could Have",IF(COUNTA(M14:R14)>0,"Stated – no priority","Aurigo-only (no RFP source)")))) -> Aurigo-only (no RFP source) | I14: =COUNTA(M14:R14) -> 0 | J14: =COUNTIF(M14:R14,"M") -> 0 | K14: =IF(I14=0,"Aurigo-only",IF(I14=1,"Single source",IF(I14=2,"Two sources",IF(I14<=4,"Common (3-4)","Broad (5+)")))) -> Aurigo-only | L14: =IF(J14>=3,"Tier 1: Must in 3+ sources",IF(J14=2,"Tier 2: Must in 2 sources",IF(J14=1,"Tier 3: Must in 1 source",IF(COUNTIF(M14:R14,"S")>0,"Tier 4: Should only",IF(COUNTIF(M14:R14,"C")>0,"Tier 5: Could only",IF(I14>0,"Tier 6: stated, no priority","Aurigo-only")))))) -> Aurigo-only | V14: Covered (SOW) | W14: Demo: Parcel Attributes grid; Pro SOW libraries 'Attribute Type', 'Attribute Status' | X14: Aurigo-only. | Z14: R02 | AA14: Project & parcel core | AB14: 19 | AC14: ROW-005
A15: ROW-012 | B15: Land Acquisition & Relocation | C15: Project & Parcel Setup | D15: Cost & budget | E15: Project / parcel cost estimating with version history | F15: Enter and track cost estimates by project/parcel across cost types (land by use, site improvements, relocation, indirect costs such as appraisal, negotiation, closing, title insurance). Changing an estimate must keep the original and show prior versions. ATX also lists estimated vs. actual costs (property, closing, condemnation). | G15: Functional | H15: =IF(COUNTIF(M15:R15,"M")>0,"Must Have",IF(COUNTIF(M15:R15,"S")>0,"Should Have",IF(COUNTIF(M15:R15,"C")>0,"Could Have",IF(COUNTA(M15:R15)>0,"Stated – no priority","Aurigo-only (no RFP source)")))) -> Must Have | I15: =COUNTA(M15:R15) -> 2 | J15: =COUNTIF(M15:R15,"M") -> 2 | K15: =IF(I15=0,"Aurigo-only",IF(I15=1,"Single source",IF(I15=2,"Two sources",IF(I15<=4,"Common (3-4)","Broad (5+)")))) -> Two sources | L15: =IF(J15>=3,"Tier 1: Must in 3+ sources",IF(J15=2,"Tier 2: Must in 2 sources",IF(J15=1,"Tier 3: Must in 1 source",IF(COUNTIF(M15:R15,"S")>0,"Tier 4: Should only",IF(COUNTIF(M15:R15,"C")>0,"Tier 5: Could only",IF(I15>0,"Tier 6: stated, no priority","Aurigo-only")))))) -> Tier 2: Must in 2 sources | N15: M | Q15: M | S15: Idaho ITD RFP Event 85 – ROWMS: §9 Project Information Requirements ['must' requirement (§9)] ×2 Austin Transit Partnership RFQ (2025): Scope – A. Data Management [RFQ – requirement listed in scope] | V15: Partial | W15: Demo: Design/Current Estimate fields; SOW dashboards 'ROW - Project Cost Summary'. Estimate versioning not evidenced | Z15: R04 | AA15: Project funding, parcel depth, acquisition plan & map viewer | AB15: 35 | AC15: ROW-004
A16: ROW-013 | B16: Land Acquisition & Relocation | C16: Project & Parcel Setup | D16: Cost & budget | E16: ROW budget and audit support (annual budgets) | F16: Support fiscal planning for ROW acquisitions and utility costs, including preparing annual budgets and adjustments. | G16: Functional | H16: =IF(COUNTIF(M16:R16,"M")>0,"Must Have",IF(COUNTIF(M16:R16,"S")>0,"Should Have",IF(COUNTIF(M16:R16,"C")>0,"Could Have",IF(COUNTA(M16:R16)>0,"Stated – no priority","Aurigo-only (no RFP source)")))) -> Must Have | I16: =COUNTA(M16:R16) -> 1 | J16: =COUNTIF(M16:R16,"M") -> 1 | K16: =IF(I16=0,"Aurigo-only",IF(I16=1,"Single source",IF(I16=2,"Two sources",IF(I16<=4,"Common (3-4)","Broad (5+)")))) -> Single source | L16: =IF(J16>=3,"Tier 1: Must in 3+ sources",IF(J16=2,"Tier 2: Must in 2 sources",IF(J16=1,"Tier 3: Must in 1 source",IF(COUNTIF(M16:R16,"S")>0,"Tier 4: Should only",IF(COUNTIF(M16:R16,"C")>0,"Tier 5: Could only",IF(I16>0,"Tier 6: stated, no priority","Aurigo-only")))))) -> Tier 3: Must in 1 source | O16: M | S16: NMDOT RFP 06-0100: App. A §1 Introduction [SOW scope item / RFP purpose] | V16: Not evidenced | W16: No matching item found in the provided Aurigo documents (SOW, demo script, deck, library list). | X16: Only a one-line description in NM Appendix A; no detail on required functions. | Z16: R04 | AA16: Project funding, parcel depth, acquisition plan & map viewer | AB16: 36 | AC16: ROW-004
A17: ROW-014 | B17: Land Acquisition & Relocation | C17: Ownership & Stakeholders | D17: Owners | E17: Owner and ownership-interest management (multiple interests per parcel) | F17: Record owners and every interest in a parcel (fee, easement, tenant, lender, trustee, life estate, owner representative, etc.) with names, vesting-deed legal name, addresses and phone/email. | G17: Functional | H17: =IF(COUNTIF(M17:R17,"M")>0,"Must Have",IF(COUNTIF(M17:R17,"S")>0,"Should Have",IF(COUNTIF(M17:R17,"C")>0,"Could Have",IF(COUNTA(M17:R17)>0,"Stated – no priority","Aurigo-only (no RFP source)")))) -> Must Have | I17: =COUNTA(M17:R17) -> 4 | J17: =COUNTIF(M17:R17,"M") -> 3 | K17: =IF(I17=0,"Aurigo-only",IF(I17=1,"Single source",IF(I17=2,"Two sources",IF(I17<=4,"Common (3-4)","Broad (5+)")))) -> Common (3-4) | L17: =IF(J17>=3,"Tier 1: Must in 3+ sources",IF(J17=2,"Tier 2: Must in 2 sources",IF(J17=1,"Tier 3: Must in 1 source",IF(COUNTIF(M17:R17,"S")>0,"Tier 4: Should only",IF(COUNTIF(M17:R17,"C")>0,"Tier 5: Could only",IF(I17>0,"Tier 6: stated, no priority","Aurigo-only")))))) -> Tier 1: Must in 3+ sources | M17: M | N17: M | P17: E | Q17: M | S17: NH DOT ROWMS & Rail Requirements: Tab 2 ROW Agent – row 5 [Required / High] Idaho ITD RFP Event 85 – ROWMS: §9 Project Information Requirements ['must' requirement (§9)] ×2 WSDOT RFI (2023): Perf. Requirements – Property Acquisition & Relocation Services [RFI – performance requirement list (no priority given)] Austin Transit Partnership RFQ (2025): Scope – IV. Data Requirements [RFQ – requirement listed in scope] | V17: Covered (SOW) | W17: Pro SOW: 'Ownership Interest'; Demo: Ownership Interests form (owner type, addresses, contacts, representatives) | Z17: R03 | AA17: Owners, stakeholders & parcel team | AB17: 25 | AC17: ROW-005
A18: ROW-015 | B18: Land Acquisition & Relocation | C18: Ownership & Stakeholders | D18: Owners | E18: Multiple contacts per parcel (attorneys, banks, designees) | F18: Manage several contacts per parcel, such as owners, attorneys, banks and owner designees. | G18: Functional | H18: =IF(COUNTIF(M18:R18,"M")>0,"Must Have",IF(COUNTIF(M18:R18,"S")>0,"Should Have",IF(COUNTIF(M18:R18,"C")>0,"Could Have",IF(COUNTA(M18:R18)>0,"Stated – no priority","Aurigo-only (no RFP source)")))) -> Must Have | I18: =COUNTA(M18:R18) -> 1 | J18: =COUNTIF(M18:R18,"M") -> 1 | K18: =IF(I18=0,"Aurigo-only",IF(I18=1,"Single source",IF(I18=2,"Two sources",IF(I18<=4,"Common (3-4)","Broad (5+)")))) -> Single source | L18: =IF(J18>=3,"Tier 1: Must in 3+ sources",IF(J18=2,"Tier 2: Must in 2 sources",IF(J18=1,"Tier 3: Must in 1 source",IF(COUNTIF(M18:R18,"S")>0,"Tier 4: Should only",IF(COUNTIF(M18:R18,"C")>0,"Tier 5: Could only",IF(I18>0,"Tier 6: stated, no priority","Aurigo-only")))))) -> Tier 3: Must in 1 source | M18: M | S18: NH DOT ROWMS & Rail Requirements: Tab 2 ROW Agent – row 40 [Required / High] | V18: Covered (SOW) | W18: Demo: 'Representatives and Associates' grid on Ownership form | Z18: R03 | AA18: Owners, stakeholders & parcel team | AB18: 27 | AC18: ROW-014
A19: ROW-016 | B19: Land Acquisition & Relocation | C19: Ownership & Stakeholders | D19: Owners | E19: Tenant / occupant information | F19: Store tenant name and contacts, insurance, evidence of a lease and lease details for parcels. | G19: Functional | H19: =IF(COUNTIF(M19:R19,"M")>0,"Must Have",IF(COUNTIF(M19:R19,"S")>0,"Should Have",IF(COUNTIF(M19:R19,"C")>0,"Could Have",IF(COUNTA(M19:R19)>0,"Stated – no priority","Aurigo-only (no RFP source)")))) -> Must Have | I19: =COUNTA(M19:R19) -> 2 | J19: =COUNTIF(M19:R19,"M") -> 2 | K19: =IF(I19=0,"Aurigo-only",IF(I19=1,"Single source",IF(I19=2,"Two sources",IF(I19<=4,"Common (3-4)","Broad (5+)")))) -> Two sources | L19: =IF(J19>=3,"Tier 1: Must in 3+ sources",IF(J19=2,"Tier 2: Must in 2 sources",IF(J19=1,"Tier 3: Must in 1 source",IF(COUNTIF(M19:R19,"S")>0,"Tier 4: Should only",IF(COUNTIF(M19:R19,"C")>0,"Tier 5: Could only",IF(I19>0,"Tier 6: stated, no priority","Aurigo-only")))))) -> Tier 2: Must in 2 sources | N19: M | Q19: M | S19: Idaho ITD RFP Event 85 – ROWMS: §9 Project Information Requirements ['must' requirement (§9)] Austin Transit Partnership RFQ (2025): Scope – IV. Data Requirements [RFQ – requirement listed in scope] | V19: Partial | W19: Ownership form captures owners/representatives; tenant lease details not evidenced | Z19: R03 | AA19: Owners, stakeholders & parcel team | AB19: 26 | AC19: ROW-014
A20: ROW-017 | B20: Land Acquisition & Relocation | C20: Ownership & Stakeholders | D20: Owners | E20: Abutters / interested-parties list | F20: Build a comprehensive list of abutters and all parties of interest for a parcel; the same data feeds hearing notices. | G20: Functional | H20: =IF(COUNTIF(M20:R20,"M")>0,"Must Have",IF(COUNTIF(M20:R20,"S")>0,"Should Have",IF(COUNTIF(M20:R20,"C")>0,"Could Have",IF(COUNTA(M20:R20)>0,"Stated – no priority","Aurigo-only (no RFP source)")))) -> Must Have | I20: =COUNTA(M20:R20) -> 1 | J20: =COUNTIF(M20:R20,"M") -> 1 | K20: =IF(I20=0,"Aurigo-only",IF(I20=1,"Single source",IF(I20=2,"Two sources",IF(I20<=4,"Common (3-4)","Broad (5+)")))) -> Single source | L20: =IF(J20>=3,"Tier 1: Must in 3+ sources",IF(J20=2,"Tier 2: Must in 2 sources",IF(J20=1,"Tier 3: Must in 1 source",IF(COUNTIF(M20:R20,"S")>0,"Tier 4: Should only",IF(COUNTIF(M20:R20,"C")>0,"Tier 5: Could only",IF(I20>0,"Tier 6: stated, no priority","Aurigo-only")))))) -> Tier 3: Must in 1 source | M20: M | S20: NH DOT ROWMS & Rail Requirements: Tab 4 Land Titles – row 10 [Required / High]; Tab 7 Administrative – row 2 [Required / High] | V20: Not evidenced | W20: No matching item found in the provided Aurigo documents (SOW, demo script, deck, library list). | Z20: R03 | AA20: Owners, stakeholders & parcel team | AB20: 28 | AC20: ROW-014
A21: ROW-018 | B21: Land Acquisition & Relocation | C21: Ownership & Stakeholders | D21: Owners | E21: Tax identification capture (W-9 / 1099) for payees | F21: Hold payee tax details (1099, W-9) on the owner record and securely collect information needed for IRS reporting. | G21: Functional | H21: =IF(COUNTIF(M21:R21,"M")>0,"Must Have",IF(COUNTIF(M21:R21,"S")>0,"Should Have",IF(COUNTIF(M21:R21,"C")>0,"Could Have",IF(COUNTA(M21:R21)>0,"Stated – no priority","Aurigo-only (no RFP source)")))) -> Must Have | I21: =COUNTA(M21:R21) -> 1 | J21: =COUNTIF(M21:R21,"M") -> 1 | K21: =IF(I21=0,"Aurigo-only",IF(I21=1,"Single source",IF(I21=2,"Two sources",IF(I21<=4,"Common (3-4)","Broad (5+)")))) -> Single source | L21: =IF(J21>=3,"Tier 1: Must in 3+ sources",IF(J21=2,"Tier 2: Must in 2 sources",IF(J21=1,"Tier 3: Must in 1 source",IF(COUNTIF(M21:R21,"S")>0,"Tier 4: Should only",IF(COUNTIF(M21:R21,"C")>0,"Tier 5: Could only",IF(I21>0,"Tier 6: stated, no priority","Aurigo-only")))))) -> Tier 3: Must in 1 source | M21: M | S21: NH DOT ROWMS & Rail Requirements: Tab 7 Administrative – row 6 [Required / High] | T21: IRS 1099 / W-9 | V21: Covered (SOW) | W21: Demo: Ownership form > Tax Information (1099, W-9) | Z21: R03 | AA21: Owners, stakeholders & parcel team | AB21: 29 | AC21: ROW-014
A22: ROW-019 | B22: Land Acquisition & Relocation | C22: Ownership & Stakeholders | D22: Team | E22: Team / role assignment per parcel | F22: Assign people to roles on each parcel (appraisal coordinator, appraiser, reviewer, counsel, negotiator in-house or consultant, relocation agent, project lead, FHWA, etc.). | G22: Functional | H22: =IF(COUNTIF(M22:R22,"M")>0,"Must Have",IF(COUNTIF(M22:R22,"S")>0,"Should Have",IF(COUNTIF(M22:R22,"C")>0,"Could Have",IF(COUNTA(M22:R22)>0,"Stated – no priority","Aurigo-only (no RFP source)")))) -> Must Have | I22: =COUNTA(M22:R22) -> 2 | J22: =COUNTIF(M22:R22,"M") -> 2 | K22: =IF(I22=0,"Aurigo-only",IF(I22=1,"Single source",IF(I22=2,"Two sources",IF(I22<=4,"Common (3-4)","Broad (5+)")))) -> Two sources | L22: =IF(J22>=3,"Tier 1: Must in 3+ sources",IF(J22=2,"Tier 2: Must in 2 sources",IF(J22=1,"Tier 3: Must in 1 source",IF(COUNTIF(M22:R22,"S")>0,"Tier 4: Should only",IF(COUNTIF(M22:R22,"C")>0,"Tier 5: Could only",IF(I22>0,"Tier 6: stated, no priority","Aurigo-only")))))) -> Tier 2: Must in 2 sources | M22: M | N22: M | S22: NH DOT ROWMS & Rail Requirements: Tab 2 ROW Agent – row 4 [Required / High] Idaho ITD RFP Event 85 – ROWMS: §9 Project Information Requirements ['must' requirement (§9)] | V22: Covered (SOW) | W22: Demo: Agent Details grid; SOW library 'Agent Type' | Z22: R03 | AA22: Owners, stakeholders & parcel team | AB22: 31 | AC22: ROW-014, ROW-212
A23: ROW-020 | B23: Land Acquisition & Relocation | C23: Ownership & Stakeholders | D23: Communication | E23: Communication / negotiation diary log | F23: Log calls, meetings, mailings, emails and contact attempts per parcel (who, when, how, what was promised or answered); NH asks that negotiation conversations be documented automatically; a printable summary of diary entries per parcel is also requested. | G23: Functional | H23: =IF(COUNTIF(M23:R23,"M")>0,"Must Have",IF(COUNTIF(M23:R23,"S")>0,"Should Have",IF(COUNTIF(M23:R23,"C")>0,"Could Have",IF(COUNTA(M23:R23)>0,"Stated – no priority","Aurigo-only (no RFP source)")))) -> Must Have | I23: =COUNTA(M23:R23) -> 4 | J23: =COUNTIF(M23:R23,"M") -> 4 | K23: =IF(I23=0,"Aurigo-only",IF(I23=1,"Single source",IF(I23=2,"Two sources",IF(I23<=4,"Common (3-4)","Broad (5+)")))) -> Common (3-4) | L23: =IF(J23>=3,"Tier 1: Must in 3+ sources",IF(J23=2,"Tier 2: Must in 2 sources",IF(J23=1,"Tier 3: Must in 1 source",IF(COUNTIF(M23:R23,"S")>0,"Tier 4: Should only",IF(COUNTIF(M23:R23,"C")>0,"Tier 5: Could only",IF(I23>0,"Tier 6: stated, no priority","Aurigo-only")))))) -> Tier 1: Must in 3+ sources | M23: M | N23: M | O23: M | Q23: M | S23: NH DOT ROWMS & Rail Requirements: Tab 2 ROW Agent – row 19 [Required / High]; Tab 2 ROW Agent – row 41 [Required / High]; Tab 9 Reports – row 20 [Required / High] Idaho ITD RFP Event 85 – ROWMS: §9 Negotiation and Acquisition Requirements ['must' requirement (§9)] NMDOT RFP 06-0100: App. A §1 Introduction [SOW scope item / RFP purpose] Austin Transit Partnership RFQ (2025): Scope – A. Data Management [RFQ – requirement listed in scope] | V23: Covered (SOW) | W23: Original SOW: 'Agent Log' (configurable process); Demo: Agent Notes / Parcel Notes | X23: 'AUTO document' in NH T2!R19 is not explained in the source; I read it as automatic logging of contact events but this is unconfirmed. | Z23: R03 | AA23: Owners, stakeholders & parcel team | AB23: 32 | AC23: ROW-014
A24: ROW-021 | B24: Land Acquisition & Relocation | C24: Ownership & Stakeholders | D24: Communication | E24: Parcel notes with permission-controlled create/delete | F24: Create and delete notes on a record according to permissions. | G24: Functional | H24: =IF(COUNTIF(M24:R24,"M")>0,"Must Have",IF(COUNTIF(M24:R24,"S")>0,"Should Have",IF(COUNTIF(M24:R24,"C")>0,"Could Have",IF(COUNTA(M24:R24)>0,"Stated – no priority","Aurigo-only (no RFP source)")))) -> Must Have | I24: =COUNTA(M24:R24) -> 1 | J24: =COUNTIF(M24:R24,"M") -> 1 | K24: =IF(I24=0,"Aurigo-only",IF(I24=1,"Single source",IF(I24=2,"Two sources",IF(I24<=4,"Common (3-4)","Broad (5+)")))) -> Single source | L24: =IF(J24>=3,"Tier 1: Must in 3+ sources",IF(J24=2,"Tier 2: Must in 2 sources",IF(J24=1,"Tier 3: Must in 1 source",IF(COUNTIF(M24:R24,"S")>0,"Tier 4: Should only",IF(COUNTIF(M24:R24,"C")>0,"Tier 5: Could only",IF(I24>0,"Tier 6: stated, no priority","Aurigo-only")))))) -> Tier 3: Must in 1 source | M24: M | S24: NH DOT ROWMS & Rail Requirements: Tab 9 Reports – row 9 [Required / High] | V24: Covered (SOW) | W24: Demo: Parcel Notes section (made by / made on / status) | Z24: R03 | AA24: Owners, stakeholders & parcel team | AB24: 33 | AC24: ROW-005, ROW-213
A25: ROW-022 | B25: Land Acquisition & Relocation | C25: Ownership & Stakeholders | D25: Demographics | E25: Owner / displacee demographic capture for civil-rights statistics | F25: Capture sex and ethnicity (minority / non-minority / female) of owners and displacees for statistical reporting. | G25: Functional | H25: =IF(COUNTIF(M25:R25,"M")>0,"Must Have",IF(COUNTIF(M25:R25,"S")>0,"Should Have",IF(COUNTIF(M25:R25,"C")>0,"Could Have",IF(COUNTA(M25:R25)>0,"Stated – no priority","Aurigo-only (no RFP source)")))) -> Must Have | I25: =COUNTA(M25:R25) -> 1 | J25: =COUNTIF(M25:R25,"M") -> 1 | K25: =IF(I25=0,"Aurigo-only",IF(I25=1,"Single source",IF(I25=2,"Two sources",IF(I25<=4,"Common (3-4)","Broad (5+)")))) -> Single source | L25: =IF(J25>=3,"Tier 1: Must in 3+ sources",IF(J25=2,"Tier 2: Must in 2 sources",IF(J25=1,"Tier 3: Must in 1 source",IF(COUNTIF(M25:R25,"S")>0,"Tier 4: Should only",IF(COUNTIF(M25:R25,"C")>0,"Tier 5: Could only",IF(I25>0,"Tier 6: stated, no priority","Aurigo-only")))))) -> Tier 3: Must in 1 source | N25: M | S25: Idaho ITD RFP Event 85 – ROWMS: §9 Negotiation and Acquisition Requirements ['must' requirement (§9)]; §9 Relocation Requirements ['must' requirement (§9)] | T25: Title VI (civil rights) reporting | V25: Not evidenced | W25: No matching item found in the provided Aurigo documents (SOW, demo script, deck, library list). | Z25: R03 | AA25: Owners, stakeholders & parcel team | AB25: 30 | AC25: ROW-014
A26: ROW-023 | B26: Land Acquisition & Relocation | C26: Title & Abstraction | D26: Title records | E26: Chain of title and historical ownership | F26: Manage chain of title and historical ownership records; identify landownership and existing encumbrances; record title information and title-report specifics on acquisitions, including liens and mortgages. | G26: Functional | H26: =IF(COUNTIF(M26:R26,"M")>0,"Must Have",IF(COUNTIF(M26:R26,"S")>0,"Should Have",IF(COUNTIF(M26:R26,"C")>0,"Could Have",IF(COUNTA(M26:R26)>0,"Stated – no priority","Aurigo-only (no RFP source)")))) -> Must Have | I26: =COUNTA(M26:R26) -> 4 | J26: =COUNTIF(M26:R26,"M") -> 3 | K26: =IF(I26=0,"Aurigo-only",IF(I26=1,"Single source",IF(I26=2,"Two sources",IF(I26<=4,"Common (3-4)","Broad (5+)")))) -> Common (3-4) | L26: =IF(J26>=3,"Tier 1: Must in 3+ sources",IF(J26=2,"Tier 2: Must in 2 sources",IF(J26=1,"Tier 3: Must in 1 source",IF(COUNTIF(M26:R26,"S")>0,"Tier 4: Should only",IF(COUNTIF(M26:R26,"C")>0,"Tier 5: Could only",IF(I26>0,"Tier 6: stated, no priority","Aurigo-only")))))) -> Tier 1: Must in 3+ sources | M26: M | O26: M | P26: E | Q26: M | S26: NH DOT ROWMS & Rail Requirements: Tab 4 Land Titles – row 3 [Required / High] NMDOT RFP 06-0100: App. A §1 Introduction [SOW scope item / RFP purpose] WSDOT RFI (2023): Perf. Requirements – Property Acquisition & Relocation Services [RFI – performance requirement list (no priority given)] Austin Transit Partnership RFQ (2025): Scope – IV. Data Requirements [RFQ – requirement listed in scope] | V26: Covered (SOW) | W26: Pro SOW: 'Title Search & Due Diligence' (core process) | Z26: R07 | AA26: Title & abstraction | AB26: 70 | AC26: ROW-005, ROW-014, ROW-157
A27: ROW-024 | B27: Land Acquisition & Relocation | C27: Title & Abstraction | D27: Title records | E27: Title defect / encumbrance tracking with alerts | F27: Track and flag/alert on title defects, encumbrances, easements and unresolved issues. | G27: Functional | H27: =IF(COUNTIF(M27:R27,"M")>0,"Must Have",IF(COUNTIF(M27:R27,"S")>0,"Should Have",IF(COUNTIF(M27:R27,"C")>0,"Could Have",IF(COUNTA(M27:R27)>0,"Stated – no priority","Aurigo-only (no RFP source)")))) -> Must Have | I27: =COUNTA(M27:R27) -> 1 | J27: =COUNTIF(M27:R27,"M") -> 1 | K27: =IF(I27=0,"Aurigo-only",IF(I27=1,"Single source",IF(I27=2,"Two sources",IF(I27<=4,"Common (3-4)","Broad (5+)")))) -> Single source | L27: =IF(J27>=3,"Tier 1: Must in 3+ sources",IF(J27=2,"Tier 2: Must in 2 sources",IF(J27=1,"Tier 3: Must in 1 source",IF(COUNTIF(M27:R27,"S")>0,"Tier 4: Should only",IF(COUNTIF(M27:R27,"C")>0,"Tier 5: Could only",IF(I27>0,"Tier 6: stated, no priority","Aurigo-only")))))) -> Tier 3: Must in 1 source | M27: M | S27: NH DOT ROWMS & Rail Requirements: Tab 4 Land Titles – row 4 [Required / High] | V27: Not evidenced | W27: No matching item found in the provided Aurigo documents (SOW, demo script, deck, library list). | Z27: R07 | AA27: Title & abstraction | AB27: 71 | AC27: ROW-023
A28: ROW-025 | B28: Land Acquisition & Relocation | C28: Title & Abstraction | D28: Title records | E28: Title commitment details | F28: Store title commitment number and expiration date as parcel data. | G28: Functional | H28: =IF(COUNTIF(M28:R28,"M")>0,"Must Have",IF(COUNTIF(M28:R28,"S")>0,"Should Have",IF(COUNTIF(M28:R28,"C")>0,"Could Have",IF(COUNTA(M28:R28)>0,"Stated – no priority","Aurigo-only (no RFP source)")))) -> Must Have | I28: =COUNTA(M28:R28) -> 1 | J28: =COUNTIF(M28:R28,"M") -> 1 | K28: =IF(I28=0,"Aurigo-only",IF(I28=1,"Single source",IF(I28=2,"Two sources",IF(I28<=4,"Common (3-4)","Broad (5+)")))) -> Single source | L28: =IF(J28>=3,"Tier 1: Must in 3+ sources",IF(J28=2,"Tier 2: Must in 2 sources",IF(J28=1,"Tier 3: Must in 1 source",IF(COUNTIF(M28:R28,"S")>0,"Tier 4: Should only",IF(COUNTIF(M28:R28,"C")>0,"Tier 5: Could only",IF(I28>0,"Tier 6: stated, no priority","Aurigo-only")))))) -> Tier 3: Must in 1 source | N28: M | S28: Idaho ITD RFP Event 85 – ROWMS: §9 Project Information Requirements ['must' requirement (§9)] | V28: Not evidenced | W28: No matching item found in the provided Aurigo documents (SOW, demo script, deck, library list). | Z28: R07 | AA28: Title & abstraction | AB28: 72 | AC28: ROW-023
A29: ROW-026 | B29: Land Acquisition & Relocation | C29: Title & Abstraction | D29: Title records | E29: Link and search title documents (deeds, plats, surveys, title reports) | F29: Store and link scanned deeds, plats, surveys and title reports to parcels/tracts; search by owner name, map/lot number, deed reference or parcel ID, including by GIS. | G29: Functional | H29: =IF(COUNTIF(M29:R29,"M")>0,"Must Have",IF(COUNTIF(M29:R29,"S")>0,"Should Have",IF(COUNTIF(M29:R29,"C")>0,"Could Have",IF(COUNTA(M29:R29)>0,"Stated – no priority","Aurigo-only (no RFP source)")))) -> Must Have | I29: =COUNTA(M29:R29) -> 1 | J29: =COUNTIF(M29:R29,"M") -> 1 | K29: =IF(I29=0,"Aurigo-only",IF(I29=1,"Single source",IF(I29=2,"Two sources",IF(I29<=4,"Common (3-4)","Broad (5+)")))) -> Single source | L29: =IF(J29>=3,"Tier 1: Must in 3+ sources",IF(J29=2,"Tier 2: Must in 2 sources",IF(J29=1,"Tier 3: Must in 1 source",IF(COUNTIF(M29:R29,"S")>0,"Tier 4: Should only",IF(COUNTIF(M29:R29,"C")>0,"Tier 5: Could only",IF(I29>0,"Tier 6: stated, no priority","Aurigo-only")))))) -> Tier 3: Must in 1 source | M29: M | S29: NH DOT ROWMS & Rail Requirements: Tab 4 Land Titles – row 5 [Required / High]; Tab 4 Land Titles – row 12 [Required / High]; Tab 8 Rail & Transit – row 19 [Required / High]; Tab 8 Rail & Transit – row 20 [Required / High] | V29: Not evidenced | W29: No matching item found in the provided Aurigo documents (SOW, demo script, deck, library list). | Z29: R07 | AA29: Title & abstraction | AB29: 73 | AC29: ROW-023, ROW-158
A30: ROW-027 | B30: Land Acquisition & Relocation | C30: Title & Abstraction | D30: Title records | E30: Title versioning and update flags through project lifecycle | F30: Track versions of modified title research and flag titles that must be updated as a project moves (e.g., preliminary to final); accept update requests. | G30: Functional | H30: =IF(COUNTIF(M30:R30,"M")>0,"Must Have",IF(COUNTIF(M30:R30,"S")>0,"Should Have",IF(COUNTIF(M30:R30,"C")>0,"Could Have",IF(COUNTA(M30:R30)>0,"Stated – no priority","Aurigo-only (no RFP source)")))) -> Must Have | I30: =COUNTA(M30:R30) -> 1 | J30: =COUNTIF(M30:R30,"M") -> 1 | K30: =IF(I30=0,"Aurigo-only",IF(I30=1,"Single source",IF(I30=2,"Two sources",IF(I30<=4,"Common (3-4)","Broad (5+)")))) -> Single source | L30: =IF(J30>=3,"Tier 1: Must in 3+ sources",IF(J30=2,"Tier 2: Must in 2 sources",IF(J30=1,"Tier 3: Must in 1 source",IF(COUNTIF(M30:R30,"S")>0,"Tier 4: Should only",IF(COUNTIF(M30:R30,"C")>0,"Tier 5: Could only",IF(I30>0,"Tier 6: stated, no priority","Aurigo-only")))))) -> Tier 3: Must in 1 source | M30: M | S30: NH DOT ROWMS & Rail Requirements: Tab 4 Land Titles – row 18 [Required / High]; Tab 4 Land Titles – row 20 [Required / High] | V30: Not evidenced | W30: No matching item found in the provided Aurigo documents (SOW, demo script, deck, library list). | Z30: R07 | AA30: Title & abstraction | AB30: 74 | AC30: ROW-023, ROW-160
A31: ROW-028 | B31: Land Acquisition & Relocation | C31: Title & Abstraction | D31: Title records | E31: Confidential title information by role | F31: Restrict sensitive title information by role (example: only legal can see confidential opinions). | G31: Functional | H31: =IF(COUNTIF(M31:R31,"M")>0,"Must Have",IF(COUNTIF(M31:R31,"S")>0,"Should Have",IF(COUNTIF(M31:R31,"C")>0,"Could Have",IF(COUNTA(M31:R31)>0,"Stated – no priority","Aurigo-only (no RFP source)")))) -> Must Have | I31: =COUNTA(M31:R31) -> 1 | J31: =COUNTIF(M31:R31,"M") -> 1 | K31: =IF(I31=0,"Aurigo-only",IF(I31=1,"Single source",IF(I31=2,"Two sources",IF(I31<=4,"Common (3-4)","Broad (5+)")))) -> Single source | L31: =IF(J31>=3,"Tier 1: Must in 3+ sources",IF(J31=2,"Tier 2: Must in 2 sources",IF(J31=1,"Tier 3: Must in 1 source",IF(COUNTIF(M31:R31,"S")>0,"Tier 4: Should only",IF(COUNTIF(M31:R31,"C")>0,"Tier 5: Could only",IF(I31>0,"Tier 6: stated, no priority","Aurigo-only")))))) -> Tier 3: Must in 1 source | M31: M | S31: NH DOT ROWMS & Rail Requirements: Tab 4 Land Titles – row 21 [Required / High] | V31: Not evidenced | W31: No matching item found in the provided Aurigo documents (SOW, demo script, deck, library list). | Z31: R07 | AA31: Title & abstraction | AB31: 75 | AC31: ROW-023, ROW-213
A32: ROW-029 | B32: Land Acquisition & Relocation | C32: Title & Abstraction | D32: Title records | E32: Land-type classification and grouping | F32: Identify/group parcels by land type (private, condo, conservation, recreation, etc.). | G32: Functional | H32: =IF(COUNTIF(M32:R32,"M")>0,"Must Have",IF(COUNTIF(M32:R32,"S")>0,"Should Have",IF(COUNTIF(M32:R32,"C")>0,"Could Have",IF(COUNTA(M32:R32)>0,"Stated – no priority","Aurigo-only (no RFP source)")))) -> Must Have | I32: =COUNTA(M32:R32) -> 1 | J32: =COUNTIF(M32:R32,"M") -> 1 | K32: =IF(I32=0,"Aurigo-only",IF(I32=1,"Single source",IF(I32=2,"Two sources",IF(I32<=4,"Common (3-4)","Broad (5+)")))) -> Single source | L32: =IF(J32>=3,"Tier 1: Must in 3+ sources",IF(J32=2,"Tier 2: Must in 2 sources",IF(J32=1,"Tier 3: Must in 1 source",IF(COUNTIF(M32:R32,"S")>0,"Tier 4: Should only",IF(COUNTIF(M32:R32,"C")>0,"Tier 5: Could only",IF(I32>0,"Tier 6: stated, no priority","Aurigo-only")))))) -> Tier 3: Must in 1 source | M32: M | S32: NH DOT ROWMS & Rail Requirements: Tab 4 Land Titles – row 9 [Required / High] | V32: Not evidenced | W32: No matching item found in the provided Aurigo documents (SOW, demo script, deck, library list). | X32: NH T4!R9 ends with 'Lchip et al.'; 'Lchip' is not defined in the file and I do not know what it refers to. | Z32: R07 | AA32: Title & abstraction | AB32: 76 | AC32: ROW-023
A33: ROW-030 | B33: Land Acquisition & Relocation | C33: Title & Abstraction | D33: Plans & workload | E33: ROW plan request tracking and workload/delivery estimating | F33: Capture ROW plan requests, project progress, reporting dates and progress indicators; help estimate workload and delivery dates; report levels of plan requests completed and abstracts/title reports completed per project. | G33: Functional | H33: =IF(COUNTIF(M33:R33,"M")>0,"Must Have",IF(COUNTIF(M33:R33,"S")>0,"Should Have",IF(COUNTIF(M33:R33,"C")>0,"Could Have",IF(COUNTA(M33:R33)>0,"Stated – no priority","Aurigo-only (no RFP source)")))) -> Must Have | I33: =COUNTA(M33:R33) -> 1 | J33: =COUNTIF(M33:R33,"M") -> 1 | K33: =IF(I33=0,"Aurigo-only",IF(I33=1,"Single source",IF(I33=2,"Two sources",IF(I33<=4,"Common (3-4)","Broad (5+)")))) -> Single source | L33: =IF(J33>=3,"Tier 1: Must in 3+ sources",IF(J33=2,"Tier 2: Must in 2 sources",IF(J33=1,"Tier 3: Must in 1 source",IF(COUNTIF(M33:R33,"S")>0,"Tier 4: Should only",IF(COUNTIF(M33:R33,"C")>0,"Tier 5: Could only",IF(I33>0,"Tier 6: stated, no priority","Aurigo-only")))))) -> Tier 3: Must in 1 source | M33: M | S33: NH DOT ROWMS & Rail Requirements: Tab 4 Land Titles – row 6 [Required / High]; Tab 4 Land Titles – row 8 [Required / High]; Tab 9 Reports – row 5 [Required / High]; Tab 9 Reports – row 6 [Required / High] | V33: Not evidenced | W33: No matching item found in the provided Aurigo documents (SOW, demo script, deck, library list). | Z33: R07 | AA33: Title & abstraction | AB33: 66 | AC33: ROW-005, ROW-166
A34: ROW-031 | B34: Land Acquisition & Relocation | C34: Title & Abstraction | D34: Vendors | E34: External title-examiner contracts and vendor portal | F34: Manage contracts with external fee-title examiners; external contractors access and upload through an external-facing portal. | G34: Functional | H34: =IF(COUNTIF(M34:R34,"M")>0,"Must Have",IF(COUNTIF(M34:R34,"S")>0,"Should Have",IF(COUNTIF(M34:R34,"C")>0,"Could Have",IF(COUNTA(M34:R34)>0,"Stated – no priority","Aurigo-only (no RFP source)")))) -> Must Have | I34: =COUNTA(M34:R34) -> 1 | J34: =COUNTIF(M34:R34,"M") -> 1 | K34: =IF(I34=0,"Aurigo-only",IF(I34=1,"Single source",IF(I34=2,"Two sources",IF(I34<=4,"Common (3-4)","Broad (5+)")))) -> Single source | L34: =IF(J34>=3,"Tier 1: Must in 3+ sources",IF(J34=2,"Tier 2: Must in 2 sources",IF(J34=1,"Tier 3: Must in 1 source",IF(COUNTIF(M34:R34,"S")>0,"Tier 4: Should only",IF(COUNTIF(M34:R34,"C")>0,"Tier 5: Could only",IF(I34>0,"Tier 6: stated, no priority","Aurigo-only")))))) -> Tier 3: Must in 1 source | M34: M | S34: NH DOT ROWMS & Rail Requirements: Tab 4 Land Titles – row 7 [Required / High]; Tab 1 General – row 3 [Required / High] | V34: Not evidenced | W34: No matching item found in the provided Aurigo documents (SOW, demo script, deck, library list). | Z34: R32 | AA34: External portals, public access & records | AB34: 298 | AC34: ROW-023, ROW-173
A35: ROW-032 | B35: Land Acquisition & Relocation | C35: Title & Abstraction | D35: Title records | E35: Title reports / templates with lookup (e.g., title front sheet) | F35: Report templates with interactive input/lookup (example: Title front sheet) and custom reports on title status, unresolved issues and number of titles across projects. | G35: Reporting | H35: =IF(COUNTIF(M35:R35,"M")>0,"Must Have",IF(COUNTIF(M35:R35,"S")>0,"Should Have",IF(COUNTIF(M35:R35,"C")>0,"Could Have",IF(COUNTA(M35:R35)>0,"Stated – no priority","Aurigo-only (no RFP source)")))) -> Must Have | I35: =COUNTA(M35:R35) -> 1 | J35: =COUNTIF(M35:R35,"M") -> 1 | K35: =IF(I35=0,"Aurigo-only",IF(I35=1,"Single source",IF(I35=2,"Two sources",IF(I35<=4,"Common (3-4)","Broad (5+)")))) -> Single source | L35: =IF(J35>=3,"Tier 1: Must in 3+ sources",IF(J35=2,"Tier 2: Must in 2 sources",IF(J35=1,"Tier 3: Must in 1 source",IF(COUNTIF(M35:R35,"S")>0,"Tier 4: Should only",IF(COUNTIF(M35:R35,"C")>0,"Tier 5: Could only",IF(I35>0,"Tier 6: stated, no priority","Aurigo-only")))))) -> Tier 3: Must in 1 source | M35: M | S35: NH DOT ROWMS & Rail Requirements: Tab 4 Land Titles – row 27 [n/a / n/a]; Tab 4 Land Titles – row 23 [Required / High] | V35: Not evidenced | W35: No matching item found in the provided Aurigo documents (SOW, demo script, deck, library list). | Z35: R07 | AA35: Title & abstraction | AB35: 78 | AC35: ROW-025, ROW-175
A36: ROW-033 | B36: Land Acquisition & Relocation | C36: Title & Abstraction | D36: Title records | E36: Hearing notification management | F36: Manage the hearing-notification process starting from the interested-party data in Land Titles: create hearing notices from templates with mail merge and keep an electronic copy by parcel with USPS delivery/receipt. | G36: Functional | H36: =IF(COUNTIF(M36:R36,"M")>0,"Must Have",IF(COUNTIF(M36:R36,"S")>0,"Should Have",IF(COUNTIF(M36:R36,"C")>0,"Could Have",IF(COUNTA(M36:R36)>0,"Stated – no priority","Aurigo-only (no RFP source)")))) -> Must Have | I36: =COUNTA(M36:R36) -> 1 | J36: =COUNTIF(M36:R36,"M") -> 1 | K36: =IF(I36=0,"Aurigo-only",IF(I36=1,"Single source",IF(I36=2,"Two sources",IF(I36<=4,"Common (3-4)","Broad (5+)")))) -> Single source | L36: =IF(J36>=3,"Tier 1: Must in 3+ sources",IF(J36=2,"Tier 2: Must in 2 sources",IF(J36=1,"Tier 3: Must in 1 source",IF(COUNTIF(M36:R36,"S")>0,"Tier 4: Should only",IF(COUNTIF(M36:R36,"C")>0,"Tier 5: Could only",IF(I36>0,"Tier 6: stated, no priority","Aurigo-only")))))) -> Tier 3: Must in 1 source | M36: M | S36: NH DOT ROWMS & Rail Requirements: Tab 7 Administrative – row 2 [Required / High]; Tab 7 Administrative – row 3 [Required / High]; Tab 7 Administrative – row 4 [Required / High] | V36: Not evidenced | W36: No matching item found in the provided Aurigo documents (SOW, demo script, deck, library list). | X36: 'Hearing' context is not explained in the source beyond these rows. | Z36: R07 | AA36: Title & abstraction | AB36: 79 | AC36: ROW-023, ROW-176
A37: ROW-034 | B37: Land Acquisition & Relocation | C37: Survey & Plans | D37: Survey data | E37: Survey data and CAD file management | F37: Securely store and manage raw survey data (field notes, GPS coordinates, total-station data) and upload/manage CAD files (DWG, DGN) with layers for control points, boundaries, easements and monuments. | G37: Functional | H37: =IF(COUNTIF(M37:R37,"M")>0,"Must Have",IF(COUNTIF(M37:R37,"S")>0,"Should Have",IF(COUNTIF(M37:R37,"C")>0,"Could Have",IF(COUNTA(M37:R37)>0,"Stated – no priority","Aurigo-only (no RFP source)")))) -> Must Have | I37: =COUNTA(M37:R37) -> 1 | J37: =COUNTIF(M37:R37,"M") -> 1 | K37: =IF(I37=0,"Aurigo-only",IF(I37=1,"Single source",IF(I37=2,"Two sources",IF(I37<=4,"Common (3-4)","Broad (5+)")))) -> Single source | L37: =IF(J37>=3,"Tier 1: Must in 3+ sources",IF(J37=2,"Tier 2: Must in 2 sources",IF(J37=1,"Tier 3: Must in 1 source",IF(COUNTIF(M37:R37,"S")>0,"Tier 4: Should only",IF(COUNTIF(M37:R37,"C")>0,"Tier 5: Could only",IF(I37>0,"Tier 6: stated, no priority","Aurigo-only")))))) -> Tier 3: Must in 1 source | M37: M | S37: NH DOT ROWMS & Rail Requirements: Tab 3 Survey – row 3 [Required / Med]; Tab 3 Survey – row 4 [Required / High] | V37: Not evidenced | W37: No matching item found in the provided Aurigo documents (SOW, demo script, deck, library list). | Z37: R08 | AA37: Survey, plans & appraisal package | AB37: 82 | AC37: ROW-035, ROW-157
A38: ROW-035 | B38: Land Acquisition & Relocation | C38: Survey & Plans | D38: Survey data | E38: Survey request tracking | F38: Track survey requests with submittal and completion dates. | G38: Functional | H38: =IF(COUNTIF(M38:R38,"M")>0,"Must Have",IF(COUNTIF(M38:R38,"S")>0,"Should Have",IF(COUNTIF(M38:R38,"C")>0,"Could Have",IF(COUNTA(M38:R38)>0,"Stated – no priority","Aurigo-only (no RFP source)")))) -> Must Have | I38: =COUNTA(M38:R38) -> 1 | J38: =COUNTIF(M38:R38,"M") -> 1 | K38: =IF(I38=0,"Aurigo-only",IF(I38=1,"Single source",IF(I38=2,"Two sources",IF(I38<=4,"Common (3-4)","Broad (5+)")))) -> Single source | L38: =IF(J38>=3,"Tier 1: Must in 3+ sources",IF(J38=2,"Tier 2: Must in 2 sources",IF(J38=1,"Tier 3: Must in 1 source",IF(COUNTIF(M38:R38,"S")>0,"Tier 4: Should only",IF(COUNTIF(M38:R38,"C")>0,"Tier 5: Could only",IF(I38>0,"Tier 6: stated, no priority","Aurigo-only")))))) -> Tier 3: Must in 1 source | M38: M | S38: NH DOT ROWMS & Rail Requirements: Tab 3 Survey – row 5 [Required / High] | V38: Not evidenced | W38: No matching item found in the provided Aurigo documents (SOW, demo script, deck, library list). | Z38: R08 | AA38: Survey, plans & appraisal package | AB38: 81 | AC38: ROW-005
A39: ROW-036 | B39: Land Acquisition & Relocation | C39: Survey & Plans | D39: Survey data | E39: Survey metadata and monumentation records | F39: Capture survey metadata (surveyor, date, location, project) and manage monumentation records including as-built plans and field books. | G39: Functional | H39: =IF(COUNTIF(M39:R39,"M")>0,"Must Have",IF(COUNTIF(M39:R39,"S")>0,"Should Have",IF(COUNTIF(M39:R39,"C")>0,"Could Have",IF(COUNTA(M39:R39)>0,"Stated – no priority","Aurigo-only (no RFP source)")))) -> Must Have | I39: =COUNTA(M39:R39) -> 1 | J39: =COUNTIF(M39:R39,"M") -> 1 | K39: =IF(I39=0,"Aurigo-only",IF(I39=1,"Single source",IF(I39=2,"Two sources",IF(I39<=4,"Common (3-4)","Broad (5+)")))) -> Single source | L39: =IF(J39>=3,"Tier 1: Must in 3+ sources",IF(J39=2,"Tier 2: Must in 2 sources",IF(J39=1,"Tier 3: Must in 1 source",IF(COUNTIF(M39:R39,"S")>0,"Tier 4: Should only",IF(COUNTIF(M39:R39,"C")>0,"Tier 5: Could only",IF(I39>0,"Tier 6: stated, no priority","Aurigo-only")))))) -> Tier 3: Must in 1 source | M39: M | S39: NH DOT ROWMS & Rail Requirements: Tab 3 Survey – row 10 [Desired/Optional / Med]; Tab 3 Survey – row 11 [Required / High] | V39: Not evidenced | W39: No matching item found in the provided Aurigo documents (SOW, demo script, deck, library list). | Z39: R08 | AA39: Survey, plans & appraisal package | AB39: 83 | AC39: ROW-034
A40: ROW-037 | B40: Land Acquisition & Relocation | C40: Survey & Plans | D40: Survey data | E40: Survey software interoperability | F40: Import/export with survey platforms such as MicroStation, Trimble Business Center or Carlson. | G40: Integration | H40: =IF(COUNTIF(M40:R40,"M")>0,"Must Have",IF(COUNTIF(M40:R40,"S")>0,"Should Have",IF(COUNTIF(M40:R40,"C")>0,"Could Have",IF(COUNTA(M40:R40)>0,"Stated – no priority","Aurigo-only (no RFP source)")))) -> Must Have | I40: =COUNTA(M40:R40) -> 1 | J40: =COUNTIF(M40:R40,"M") -> 1 | K40: =IF(I40=0,"Aurigo-only",IF(I40=1,"Single source",IF(I40=2,"Two sources",IF(I40<=4,"Common (3-4)","Broad (5+)")))) -> Single source | L40: =IF(J40>=3,"Tier 1: Must in 3+ sources",IF(J40=2,"Tier 2: Must in 2 sources",IF(J40=1,"Tier 3: Must in 1 source",IF(COUNTIF(M40:R40,"S")>0,"Tier 4: Should only",IF(COUNTIF(M40:R40,"C")>0,"Tier 5: Could only",IF(I40>0,"Tier 6: stated, no priority","Aurigo-only")))))) -> Tier 3: Must in 1 source | M40: M | S40: NH DOT ROWMS & Rail Requirements: Tab 3 Survey – row 15 [Required / High] | U40: MicroStation; Trimble Business Center; Carlson | V40: Not evidenced | W40: No matching item found in the provided Aurigo documents (SOW, demo script, deck, library list). | Z40: R34 | AA40: Document, mail, map & survey integrations | AB40: 316 | AC40: ROW-034
A41: ROW-038 | B41: Land Acquisition & Relocation | C41: Survey & Plans | D41: Survey data | E41: Migrate and integrate the existing field-book system | F41: Migrate and integrate the agency's existing field-book system into the new system. | G41: Data | H41: =IF(COUNTIF(M41:R41,"M")>0,"Must Have",IF(COUNTIF(M41:R41,"S")>0,"Should Have",IF(COUNTIF(M41:R41,"C")>0,"Could Have",IF(COUNTA(M41:R41)>0,"Stated – no priority","Aurigo-only (no RFP source)")))) -> Must Have | I41: =COUNTA(M41:R41) -> 1 | J41: =COUNTIF(M41:R41,"M") -> 1 | K41: =IF(I41=0,"Aurigo-only",IF(I41=1,"Single source",IF(I41=2,"Two sources",IF(I41<=4,"Common (3-4)","Broad (5+)")))) -> Single source | L41: =IF(J41>=3,"Tier 1: Must in 3+ sources",IF(J41=2,"Tier 2: Must in 2 sources",IF(J41=1,"Tier 3: Must in 1 source",IF(COUNTIF(M41:R41,"S")>0,"Tier 4: Should only",IF(COUNTIF(M41:R41,"C")>0,"Tier 5: Could only",IF(I41>0,"Tier 6: stated, no priority","Aurigo-only")))))) -> Tier 3: Must in 1 source | M41: M | S41: NH DOT ROWMS & Rail Requirements: Tab 3 Survey – row 16 [Required / High] | V41: Not evidenced | W41: No matching item found in the provided Aurigo documents (SOW, demo script, deck, library list). | Z41: R16 | AA41: Data import & legacy migration | AB41: 185 | AC41: ROW-034, ROW-203
A42: ROW-039 | B42: Land Acquisition & Relocation | C42: Survey & Plans | D42: Survey data | E42: Restricted editing of survey plans (e.g., Chief Surveyor only) | F42: Limit plan editing to the Chief Surveyor or authorised designees, and audit who accessed, changed or approved plans over time. | G42: Non-functional | H42: =IF(COUNTIF(M42:R42,"M")>0,"Must Have",IF(COUNTIF(M42:R42,"S")>0,"Should Have",IF(COUNTIF(M42:R42,"C")>0,"Could Have",IF(COUNTA(M42:R42)>0,"Stated – no priority","Aurigo-only (no RFP source)")))) -> Must Have | I42: =COUNTA(M42:R42) -> 1 | J42: =COUNTIF(M42:R42,"M") -> 1 | K42: =IF(I42=0,"Aurigo-only",IF(I42=1,"Single source",IF(I42=2,"Two sources",IF(I42<=4,"Common (3-4)","Broad (5+)")))) -> Single source | L42: =IF(J42>=3,"Tier 1: Must in 3+ sources",IF(J42=2,"Tier 2: Must in 2 sources",IF(J42=1,"Tier 3: Must in 1 source",IF(COUNTIF(M42:R42,"S")>0,"Tier 4: Should only",IF(COUNTIF(M42:R42,"C")>0,"Tier 5: Could only",IF(I42>0,"Tier 6: stated, no priority","Aurigo-only")))))) -> Tier 3: Must in 1 source | M42: M | S42: NH DOT ROWMS & Rail Requirements: Tab 3 Survey – row 24 [Required / High]; Tab 3 Survey – row 19 [Required / High] | V42: Not evidenced | W42: No matching item found in the provided Aurigo documents (SOW, demo script, deck, library list). | Z42: R08 | AA42: Survey, plans & appraisal package | AB42: 84 | AC42: ROW-034, ROW-213
A43: ROW-040 | B43: Land Acquisition & Relocation | C43: Survey & Plans | D43: Survey data | E43: Public-inquiry response and statewide-contract tracking | F43: Track, tag and store public inquiry responses; track project-responsibility reporting; manage and track statewide contracts. | G43: Functional | H43: =IF(COUNTIF(M43:R43,"M")>0,"Must Have",IF(COUNTIF(M43:R43,"S")>0,"Should Have",IF(COUNTIF(M43:R43,"C")>0,"Could Have",IF(COUNTA(M43:R43)>0,"Stated – no priority","Aurigo-only (no RFP source)")))) -> Must Have | I43: =COUNTA(M43:R43) -> 1 | J43: =COUNTIF(M43:R43,"M") -> 1 | K43: =IF(I43=0,"Aurigo-only",IF(I43=1,"Single source",IF(I43=2,"Two sources",IF(I43<=4,"Common (3-4)","Broad (5+)")))) -> Single source | L43: =IF(J43>=3,"Tier 1: Must in 3+ sources",IF(J43=2,"Tier 2: Must in 2 sources",IF(J43=1,"Tier 3: Must in 1 source",IF(COUNTIF(M43:R43,"S")>0,"Tier 4: Should only",IF(COUNTIF(M43:R43,"C")>0,"Tier 5: Could only",IF(I43>0,"Tier 6: stated, no priority","Aurigo-only")))))) -> Tier 3: Must in 1 source | M43: M | S43: NH DOT ROWMS & Rail Requirements: Tab 3 Survey – row 20 [Required / High]; Tab 3 Survey – row 21 [Required / High]; Tab 3 Survey – row 22 [Require / High] | V43: Not evidenced | W43: No matching item found in the provided Aurigo documents (SOW, demo script, deck, library list). | X43: Meaning of 'project responsibility reporting' is not explained in NH T3!R21. | Z43: R08 | AA43: Survey, plans & appraisal package | AB43: 85 | AC43: ROW-157
A44: ROW-041 | B44: Land Acquisition & Relocation | C44: Survey & Plans | D44: Survey data | E44: Survey status and performance reports | F44: Reports on ROW status, survey completeness and performance metrics (metrics TBD in source). | G44: Reporting | H44: =IF(COUNTIF(M44:R44,"M")>0,"Must Have",IF(COUNTIF(M44:R44,"S")>0,"Should Have",IF(COUNTIF(M44:R44,"C")>0,"Could Have",IF(COUNTA(M44:R44)>0,"Stated – no priority","Aurigo-only (no RFP source)")))) -> Must Have | I44: =COUNTA(M44:R44) -> 1 | J44: =COUNTIF(M44:R44,"M") -> 1 | K44: =IF(I44=0,"Aurigo-only",IF(I44=1,"Single source",IF(I44=2,"Two sources",IF(I44<=4,"Common (3-4)","Broad (5+)")))) -> Single source | L44: =IF(J44>=3,"Tier 1: Must in 3+ sources",IF(J44=2,"Tier 2: Must in 2 sources",IF(J44=1,"Tier 3: Must in 1 source",IF(COUNTIF(M44:R44,"S")>0,"Tier 4: Should only",IF(COUNTIF(M44:R44,"C")>0,"Tier 5: Could only",IF(I44>0,"Tier 6: stated, no priority","Aurigo-only")))))) -> Tier 3: Must in 1 source | M44: M | S44: NH DOT ROWMS & Rail Requirements: Tab 3 Survey – row 18 [Required / High] | V44: Not evidenced | W44: No matching item found in the provided Aurigo documents (SOW, demo script, deck, library list). | Z44: R08 | AA44: Survey, plans & appraisal package | AB44: 86 | AC44: ROW-035
A45: ROW-042 | B45: Land Acquisition & Relocation | C45: Appraisal & Review | D45: Assignment | E45: Appraisal assignment and tracking workflow (internal / external appraisers) | F45: Assign appraisals of a parcel to an appraiser (in-house or contract), enter a contract and payment structure, notify the appraiser by email, and log all related items; data entered once (project, parcel, owner, inspection dates) populates fields across the system. | G45: Functional | H45: =IF(COUNTIF(M45:R45,"M")>0,"Must Have",IF(COUNTIF(M45:R45,"S")>0,"Should Have",IF(COUNTIF(M45:R45,"C")>0,"Could Have",IF(COUNTA(M45:R45)>0,"Stated – no priority","Aurigo-only (no RFP source)")))) -> Must Have | I45: =COUNTA(M45:R45) -> 3 | J45: =COUNTIF(M45:R45,"M") -> 2 | K45: =IF(I45=0,"Aurigo-only",IF(I45=1,"Single source",IF(I45=2,"Two sources",IF(I45<=4,"Common (3-4)","Broad (5+)")))) -> Common (3-4) | L45: =IF(J45>=3,"Tier 1: Must in 3+ sources",IF(J45=2,"Tier 2: Must in 2 sources",IF(J45=1,"Tier 3: Must in 1 source",IF(COUNTIF(M45:R45,"S")>0,"Tier 4: Should only",IF(COUNTIF(M45:R45,"C")>0,"Tier 5: Could only",IF(I45>0,"Tier 6: stated, no priority","Aurigo-only")))))) -> Tier 2: Must in 2 sources | M45: M | N45: M | P45: E | S45: NH DOT ROWMS & Rail Requirements: Tab 5 Appraisal – row 7 [Required / High] Idaho ITD RFP Event 85 – ROWMS: §9 Appraisal Requirements ['must' requirement (§9)] ×2 WSDOT RFI (2023): Perf. Requirements – Property Acquisition & Relocation Services [RFI – performance requirement list (no priority given)] | V45: Covered (SOW) | W45: Pro SOW: 'Parcel-Appraisal'; Demo: Appraisal form (type, agent, reviewer; Draft > Appraise > Review > Approved) | Z45: R09 | AA45: Appraisal core | Utilities core (parallel track) | AB45: 91 | AC45: ROW-019, ROW-023, ROW-034, ROW-248
A46: ROW-043 | B46: Land Acquisition & Relocation | C46: Appraisal & Review | D46: Appraisal record | E46: Appraisal data capture (type, dates, valuation, basis) | F46: Store appraisal details: report type (e.g., Property Compensation Estimate, Form 2288, Before & After), report and inspection dates, fee, deadline, valuation, basis for valuation, rights being acquired, property type, size, zoning, improvements, approaches to value. | G46: Functional | H46: =IF(COUNTIF(M46:R46,"M")>0,"Must Have",IF(COUNTIF(M46:R46,"S")>0,"Should Have",IF(COUNTIF(M46:R46,"C")>0,"Could Have",IF(COUNTA(M46:R46)>0,"Stated – no priority","Aurigo-only (no RFP source)")))) -> Must Have | I46: =COUNTA(M46:R46) -> 2 | J46: =COUNTIF(M46:R46,"M") -> 2 | K46: =IF(I46=0,"Aurigo-only",IF(I46=1,"Single source",IF(I46=2,"Two sources",IF(I46<=4,"Common (3-4)","Broad (5+)")))) -> Two sources | L46: =IF(J46>=3,"Tier 1: Must in 3+ sources",IF(J46=2,"Tier 2: Must in 2 sources",IF(J46=1,"Tier 3: Must in 1 source",IF(COUNTIF(M46:R46,"S")>0,"Tier 4: Should only",IF(COUNTIF(M46:R46,"C")>0,"Tier 5: Could only",IF(I46>0,"Tier 6: stated, no priority","Aurigo-only")))))) -> Tier 2: Must in 2 sources | M46: M | N46: M | S46: NH DOT ROWMS & Rail Requirements: Tab 5 Appraisal – row 5 [Required / High] Idaho ITD RFP Event 85 – ROWMS: §9 Appraisal Requirements ['must' requirement (§9)] | V46: Covered (SOW) | W46: Demo: Appraisal form with Appraisal Amounts grid; SOW libraries 'Appraisal Type', 'Appraisal Amount Type' | Z46: R09 | AA46: Appraisal core | Utilities core (parallel track) | AB46: 92 | AC46: ROW-042
A47: ROW-044 | B47: Land Acquisition & Relocation | C47: Appraisal & Review | D47: Review | E47: Appraisal review workflow with accept/reject justification | F47: Assign internal/external review appraisers, record approval or disapproval with comments and justification, and return the appraisal electronically to the original appraiser for corrections. WSDOT also asks that review data be kept for each appraisal. | G47: Functional | H47: =IF(COUNTIF(M47:R47,"M")>0,"Must Have",IF(COUNTIF(M47:R47,"S")>0,"Should Have",IF(COUNTIF(M47:R47,"C")>0,"Could Have",IF(COUNTA(M47:R47)>0,"Stated – no priority","Aurigo-only (no RFP source)")))) -> Must Have | I47: =COUNTA(M47:R47) -> 3 | J47: =COUNTIF(M47:R47,"M") -> 2 | K47: =IF(I47=0,"Aurigo-only",IF(I47=1,"Single source",IF(I47=2,"Two sources",IF(I47<=4,"Common (3-4)","Broad (5+)")))) -> Common (3-4) | L47: =IF(J47>=3,"Tier 1: Must in 3+ sources",IF(J47=2,"Tier 2: Must in 2 sources",IF(J47=1,"Tier 3: Must in 1 source",IF(COUNTIF(M47:R47,"S")>0,"Tier 4: Should only",IF(COUNTIF(M47:R47,"C")>0,"Tier 5: Could only",IF(I47>0,"Tier 6: stated, no priority","Aurigo-only")))))) -> Tier 2: Must in 2 sources | M47: M | N47: M | P47: E | S47: NH DOT ROWMS & Rail Requirements: Tab 5 Appraisal – row 9 [Required / High] Idaho ITD RFP Event 85 – ROWMS: §9 Appraisal Requirements ['must' requirement (§9)] ×3 WSDOT RFI (2023): Perf. Requirements – Property Acquisition & Relocation Services [RFI – performance requirement list (no priority given)] | V47: Covered (SOW) | W47: Demo: Review Amounts grid and Appraisal workflow Appraise > Review > Approved | Z47: R09 | AA47: Appraisal core | Utilities core (parallel track) | AB47: 96 | AC47: ROW-043
A48: ROW-045 | B48: Land Acquisition & Relocation | C48: Appraisal & Review | D48: Appraisal record | E48: Multiple appraisals per parcel with history and change documentation | F48: Keep the history of several appraisals on one parcel (new approved appraisal archives the earlier one), document what changed in later appraisals, and link reviews to the correct appraisal; retain historical valuations for future cost estimating. | G48: Functional | H48: =IF(COUNTIF(M48:R48,"M")>0,"Must Have",IF(COUNTIF(M48:R48,"S")>0,"Should Have",IF(COUNTIF(M48:R48,"C")>0,"Could Have",IF(COUNTA(M48:R48)>0,"Stated – no priority","Aurigo-only (no RFP source)")))) -> Must Have | I48: =COUNTA(M48:R48) -> 3 | J48: =COUNTIF(M48:R48,"M") -> 2 | K48: =IF(I48=0,"Aurigo-only",IF(I48=1,"Single source",IF(I48=2,"Two sources",IF(I48<=4,"Common (3-4)","Broad (5+)")))) -> Common (3-4) | L48: =IF(J48>=3,"Tier 1: Must in 3+ sources",IF(J48=2,"Tier 2: Must in 2 sources",IF(J48=1,"Tier 3: Must in 1 source",IF(COUNTIF(M48:R48,"S")>0,"Tier 4: Should only",IF(COUNTIF(M48:R48,"C")>0,"Tier 5: Could only",IF(I48>0,"Tier 6: stated, no priority","Aurigo-only")))))) -> Tier 2: Must in 2 sources | M48: M | N48: M | P48: E | S48: NH DOT ROWMS & Rail Requirements: Tab 5 Appraisal – row 21 [Required / High] Idaho ITD RFP Event 85 – ROWMS: §9 Appraisal Requirements ['must' requirement (§9)] ×2 WSDOT RFI (2023): Perf. Requirements – Property Acquisition & Relocation Services [RFI – performance requirement list (no priority given)] | V48: Not evidenced | W48: No matching item found in the provided Aurigo documents (SOW, demo script, deck, library list). | Z48: R09 | AA48: Appraisal core | Utilities core (parallel track) | AB48: 97 | AC48: ROW-043
A49: ROW-046 | B49: Land Acquisition & Relocation | C49: Appraisal & Review | D49: Review | E49: Just-compensation approval (electronic) | F49: Authorised users review and approve just compensation used for initial or revised offers online; approved value is shown during negotiation. | G49: Functional | H49: =IF(COUNTIF(M49:R49,"M")>0,"Must Have",IF(COUNTIF(M49:R49,"S")>0,"Should Have",IF(COUNTIF(M49:R49,"C")>0,"Could Have",IF(COUNTA(M49:R49)>0,"Stated – no priority","Aurigo-only (no RFP source)")))) -> Must Have | I49: =COUNTA(M49:R49) -> 2 | J49: =COUNTIF(M49:R49,"M") -> 2 | K49: =IF(I49=0,"Aurigo-only",IF(I49=1,"Single source",IF(I49=2,"Two sources",IF(I49<=4,"Common (3-4)","Broad (5+)")))) -> Two sources | L49: =IF(J49>=3,"Tier 1: Must in 3+ sources",IF(J49=2,"Tier 2: Must in 2 sources",IF(J49=1,"Tier 3: Must in 1 source",IF(COUNTIF(M49:R49,"S")>0,"Tier 4: Should only",IF(COUNTIF(M49:R49,"C")>0,"Tier 5: Could only",IF(I49>0,"Tier 6: stated, no priority","Aurigo-only")))))) -> Tier 2: Must in 2 sources | M49: M | N49: M | S49: NH DOT ROWMS & Rail Requirements: Tab 2 ROW Agent – row 21 [Required / High] Idaho ITD RFP Event 85 – ROWMS: §9 Appraisal Requirements ['must' requirement (§9)] | V49: Covered (SOW) | W49: Demo: 'Approved Just Compensation ($)' field on Appraisal review | Z49: R09 | AA49: Appraisal core | Utilities core (parallel track) | AB49: 104 | AC49: ROW-044, ROW-253
A50: ROW-047 | B50: Land Acquisition & Relocation | C50: Appraisal & Review | D50: Appraisal record | E50: Appraisal document storage with version control and audit log | F50: Securely store draft/final appraisals, review appraisals and supporting documents (comps, plats, cost tables, waiver valuation documents) with version control and audit logs. | G50: Functional | H50: =IF(COUNTIF(M50:R50,"M")>0,"Must Have",IF(COUNTIF(M50:R50,"S")>0,"Should Have",IF(COUNTIF(M50:R50,"C")>0,"Could Have",IF(COUNTA(M50:R50)>0,"Stated – no priority","Aurigo-only (no RFP source)")))) -> Must Have | I50: =COUNTA(M50:R50) -> 2 | J50: =COUNTIF(M50:R50,"M") -> 2 | K50: =IF(I50=0,"Aurigo-only",IF(I50=1,"Single source",IF(I50=2,"Two sources",IF(I50<=4,"Common (3-4)","Broad (5+)")))) -> Two sources | L50: =IF(J50>=3,"Tier 1: Must in 3+ sources",IF(J50=2,"Tier 2: Must in 2 sources",IF(J50=1,"Tier 3: Must in 1 source",IF(COUNTIF(M50:R50,"S")>0,"Tier 4: Should only",IF(COUNTIF(M50:R50,"C")>0,"Tier 5: Could only",IF(I50>0,"Tier 6: stated, no priority","Aurigo-only")))))) -> Tier 2: Must in 2 sources | M50: M | N50: M | S50: NH DOT ROWMS & Rail Requirements: Tab 5 Appraisal – row 3 [Required / High]; Tab 5 Appraisal – row 4 [Required / High] Idaho ITD RFP Event 85 – ROWMS: §9 Appraisal Requirements ['must' requirement (§9)] | V50: Not evidenced | W50: No matching item found in the provided Aurigo documents (SOW, demo script, deck, library list). | Z50: R09 | AA50: Appraisal core | Utilities core (parallel track) | AB50: 98 | AC50: ROW-043, ROW-160
A51: ROW-048 | B51: Land Acquisition & Relocation | C51: Appraisal & Review | D51: Appraisal record | E51: Appraisal linked to parcel and proposed acquisition | F51: Link each appraisal directly to its parcel and the proposed acquisition. | G51: Functional | H51: =IF(COUNTIF(M51:R51,"M")>0,"Must Have",IF(COUNTIF(M51:R51,"S")>0,"Should Have",IF(COUNTIF(M51:R51,"C")>0,"Could Have",IF(COUNTA(M51:R51)>0,"Stated – no priority","Aurigo-only (no RFP source)")))) -> Must Have | I51: =COUNTA(M51:R51) -> 1 | J51: =COUNTIF(M51:R51,"M") -> 1 | K51: =IF(I51=0,"Aurigo-only",IF(I51=1,"Single source",IF(I51=2,"Two sources",IF(I51<=4,"Common (3-4)","Broad (5+)")))) -> Single source | L51: =IF(J51>=3,"Tier 1: Must in 3+ sources",IF(J51=2,"Tier 2: Must in 2 sources",IF(J51=1,"Tier 3: Must in 1 source",IF(COUNTIF(M51:R51,"S")>0,"Tier 4: Should only",IF(COUNTIF(M51:R51,"C")>0,"Tier 5: Could only",IF(I51>0,"Tier 6: stated, no priority","Aurigo-only")))))) -> Tier 3: Must in 1 source | M51: M | S51: NH DOT ROWMS & Rail Requirements: Tab 5 Appraisal – row 6 [Required / High] | V51: Covered (SOW) | W51: Demo/SOW: Appraisal is a child form under Parcel | Z51: R09 | AA51: Appraisal core | Utilities core (parallel track) | AB51: 99 | AC51: ROW-043
A52: ROW-049 | B52: Land Acquisition & Relocation | C52: Appraisal & Review | D52: Appraisal record | E52: Owner-submitted (third-party) appraisals | F52: Store and display an appraisal submitted by a property owner, indicate approval of all or parts, and submit approved values into the system. | G52: Functional | H52: =IF(COUNTIF(M52:R52,"M")>0,"Must Have",IF(COUNTIF(M52:R52,"S")>0,"Should Have",IF(COUNTIF(M52:R52,"C")>0,"Could Have",IF(COUNTA(M52:R52)>0,"Stated – no priority","Aurigo-only (no RFP source)")))) -> Must Have | I52: =COUNTA(M52:R52) -> 1 | J52: =COUNTIF(M52:R52,"M") -> 1 | K52: =IF(I52=0,"Aurigo-only",IF(I52=1,"Single source",IF(I52=2,"Two sources",IF(I52<=4,"Common (3-4)","Broad (5+)")))) -> Single source | L52: =IF(J52>=3,"Tier 1: Must in 3+ sources",IF(J52=2,"Tier 2: Must in 2 sources",IF(J52=1,"Tier 3: Must in 1 source",IF(COUNTIF(M52:R52,"S")>0,"Tier 4: Should only",IF(COUNTIF(M52:R52,"C")>0,"Tier 5: Could only",IF(I52>0,"Tier 6: stated, no priority","Aurigo-only")))))) -> Tier 3: Must in 1 source | N52: M | S52: Idaho ITD RFP Event 85 – ROWMS: §9 Appraisal Requirements ['must' requirement (§9)] | V52: Not evidenced | W52: No matching item found in the provided Aurigo documents (SOW, demo script, deck, library list). | Z52: R09 | AA52: Appraisal core | Utilities core (parallel track) | AB52: 100 | AC52: ROW-043
A53: ROW-050 | B53: Land Acquisition & Relocation | C53: Appraisal & Review | D53: Appraisal record | E53: Auto-generated appraisal summary sheet and status reports | F53: Generate an appraisal summary information sheet from entered data and report appraisal status by project (pending, prepared, approved, waiting resubmission, on hold, etc.). | G53: Reporting | H53: =IF(COUNTIF(M53:R53,"M")>0,"Must Have",IF(COUNTIF(M53:R53,"S")>0,"Should Have",IF(COUNTIF(M53:R53,"C")>0,"Could Have",IF(COUNTA(M53:R53)>0,"Stated – no priority","Aurigo-only (no RFP source)")))) -> Must Have | I53: =COUNTA(M53:R53) -> 1 | J53: =COUNTIF(M53:R53,"M") -> 1 | K53: =IF(I53=0,"Aurigo-only",IF(I53=1,"Single source",IF(I53=2,"Two sources",IF(I53<=4,"Common (3-4)","Broad (5+)")))) -> Single source | L53: =IF(J53>=3,"Tier 1: Must in 3+ sources",IF(J53=2,"Tier 2: Must in 2 sources",IF(J53=1,"Tier 3: Must in 1 source",IF(COUNTIF(M53:R53,"S")>0,"Tier 4: Should only",IF(COUNTIF(M53:R53,"C")>0,"Tier 5: Could only",IF(I53>0,"Tier 6: stated, no priority","Aurigo-only")))))) -> Tier 3: Must in 1 source | N53: M | S53: Idaho ITD RFP Event 85 – ROWMS: §9 Appraisal Requirements ['must' requirement (§9)] ×2 | V53: Not evidenced | W53: No matching item found in the provided Aurigo documents (SOW, demo script, deck, library list). | Z53: R09 | AA53: Appraisal core | Utilities core (parallel track) | AB53: 101 | AC53: ROW-043
A54: ROW-051 | B54: Land Acquisition & Relocation | C54: Appraisal & Review | D54: Appraisal record | E54: Appraisal report writing modules (template-populated) | F54: Report-writing modules per report type that populate templates with project, parcel and owner information. | G54: Functional | H54: =IF(COUNTIF(M54:R54,"M")>0,"Must Have",IF(COUNTIF(M54:R54,"S")>0,"Should Have",IF(COUNTIF(M54:R54,"C")>0,"Could Have",IF(COUNTA(M54:R54)>0,"Stated – no priority","Aurigo-only (no RFP source)")))) -> Must Have | I54: =COUNTA(M54:R54) -> 1 | J54: =COUNTIF(M54:R54,"M") -> 1 | K54: =IF(I54=0,"Aurigo-only",IF(I54=1,"Single source",IF(I54=2,"Two sources",IF(I54<=4,"Common (3-4)","Broad (5+)")))) -> Single source | L54: =IF(J54>=3,"Tier 1: Must in 3+ sources",IF(J54=2,"Tier 2: Must in 2 sources",IF(J54=1,"Tier 3: Must in 1 source",IF(COUNTIF(M54:R54,"S")>0,"Tier 4: Should only",IF(COUNTIF(M54:R54,"C")>0,"Tier 5: Could only",IF(I54>0,"Tier 6: stated, no priority","Aurigo-only")))))) -> Tier 3: Must in 1 source | M54: M | S54: NH DOT ROWMS & Rail Requirements: Tab 5 Appraisal – row 26 [Required / High] | V54: Not evidenced | W54: No matching item found in the provided Aurigo documents (SOW, demo script, deck, library list). | Z54: R10 | AA54: Appraisal depth | Utilities agreements & reimbursement (parallel track) | AB54: 114 | AC54: ROW-043, ROW-175
A55: ROW-052 | B55: Land Acquisition & Relocation | C55: Appraisal & Review | D55: Review | E55: Missing-element checks on appraisal reports | F55: Flag missing required elements via a checklist defined per report type. | G55: Functional | H55: =IF(COUNTIF(M55:R55,"M")>0,"Must Have",IF(COUNTIF(M55:R55,"S")>0,"Should Have",IF(COUNTIF(M55:R55,"C")>0,"Could Have",IF(COUNTA(M55:R55)>0,"Stated – no priority","Aurigo-only (no RFP source)")))) -> Should Have | I55: =COUNTA(M55:R55) -> 1 | J55: =COUNTIF(M55:R55,"M") -> 0 | K55: =IF(I55=0,"Aurigo-only",IF(I55=1,"Single source",IF(I55=2,"Two sources",IF(I55<=4,"Common (3-4)","Broad (5+)")))) -> Single source | L55: =IF(J55>=3,"Tier 1: Must in 3+ sources",IF(J55=2,"Tier 2: Must in 2 sources",IF(J55=1,"Tier 3: Must in 1 source",IF(COUNTIF(M55:R55,"S")>0,"Tier 4: Should only",IF(COUNTIF(M55:R55,"C")>0,"Tier 5: Could only",IF(I55>0,"Tier 6: stated, no priority","Aurigo-only")))))) -> Tier 4: Should only | M55: S | S55: NH DOT ROWMS & Rail Requirements: Tab 5 Appraisal – row 10 [Optional / Medium] | V55: Not evidenced | W55: No matching item found in the provided Aurigo documents (SOW, demo script, deck, library list). | Z55: R10 | AA55: Appraisal depth | Utilities agreements & reimbursement (parallel track) | AB55: 117 | AC55: ROW-044, ROW-051
A56: ROW-053 | B56: Land Acquisition & Relocation | C56: Appraisal & Review | D56: Valuation | E56: Waiver valuations and escalation to full appraisal | F56: Track offers made on a waiver / nominal-fee basis and when they must be elevated to appraisal; store waiver valuation documents; support waiver workflows. | G56: Functional | H56: =IF(COUNTIF(M56:R56,"M")>0,"Must Have",IF(COUNTIF(M56:R56,"S")>0,"Should Have",IF(COUNTIF(M56:R56,"C")>0,"Could Have",IF(COUNTA(M56:R56)>0,"Stated – no priority","Aurigo-only (no RFP source)")))) -> Must Have | I56: =COUNTA(M56:R56) -> 1 | J56: =COUNTIF(M56:R56,"M") -> 1 | K56: =IF(I56=0,"Aurigo-only",IF(I56=1,"Single source",IF(I56=2,"Two sources",IF(I56<=4,"Common (3-4)","Broad (5+)")))) -> Single source | L56: =IF(J56>=3,"Tier 1: Must in 3+ sources",IF(J56=2,"Tier 2: Must in 2 sources",IF(J56=1,"Tier 3: Must in 1 source",IF(COUNTIF(M56:R56,"S")>0,"Tier 4: Should only",IF(COUNTIF(M56:R56,"C")>0,"Tier 5: Could only",IF(I56>0,"Tier 6: stated, no priority","Aurigo-only")))))) -> Tier 3: Must in 1 source | M56: M | S56: NH DOT ROWMS & Rail Requirements: Tab 2 ROW Agent – row 32 [Required / High]; Tab 2 ROW Agent – row 12 [Required / High]; Tab 5 Appraisal – row 3 [Required / High] | V56: Not evidenced | W56: No matching item found in the provided Aurigo documents (SOW, demo script, deck, library list). | X56: 'Waiver' is used in NH without a definition; description reflects only what the rows say. | Z56: R10 | AA56: Appraisal depth | Utilities agreements & reimbursement (parallel track) | AB56: 111 | AC56: ROW-043
A57: ROW-054 | B57: Land Acquisition & Relocation | C57: Appraisal & Review | D57: Valuation | E57: Property-management valuations (broker opinions, rent studies, surplus appraisals) | F57: Create and review value determinations used in property management: market value appraisals, broker opinions of value, administrative compensation estimates, rent studies and other specialty reports; track surplus appraisals by project, parcel and GIS. | G57: Functional | H57: =IF(COUNTIF(M57:R57,"M")>0,"Must Have",IF(COUNTIF(M57:R57,"S")>0,"Should Have",IF(COUNTIF(M57:R57,"C")>0,"Could Have",IF(COUNTA(M57:R57)>0,"Stated – no priority","Aurigo-only (no RFP source)")))) -> Stated – no priority | I57: =COUNTA(M57:R57) -> 2 | J57: =COUNTIF(M57:R57,"M") -> 0 | K57: =IF(I57=0,"Aurigo-only",IF(I57=1,"Single source",IF(I57=2,"Two sources",IF(I57<=4,"Common (3-4)","Broad (5+)")))) -> Two sources | L57: =IF(J57>=3,"Tier 1: Must in 3+ sources",IF(J57=2,"Tier 2: Must in 2 sources",IF(J57=1,"Tier 3: Must in 1 source",IF(COUNTIF(M57:R57,"S")>0,"Tier 4: Should only",IF(COUNTIF(M57:R57,"C")>0,"Tier 5: Could only",IF(I57>0,"Tier 6: stated, no priority","Aurigo-only")))))) -> Tier 6: stated, no priority | M57: E | P57: E | S57: NH DOT ROWMS & Rail Requirements: Tab 5 Appraisal – row 32 [n/a / n/a] WSDOT RFI (2023): Perf. Requirements – Property Management [RFI – performance requirement list (no priority given)] | V57: Not evidenced | W57: No matching item found in the provided Aurigo documents (SOW, demo script, deck, library list). | Z57: R26 | AA57: Leases, occupancy & use agreements | AB57: 261 | AC57: ROW-042, ROW-117
A58: ROW-055 | B58: Land Acquisition & Relocation | C58: Appraisal & Review | D58: Appraiser management | E58: Contract-appraiser qualification, performance and scoring | F58: Track contract appraisers, qualifications, assignments and performance; automated scoring for awarding future contracts; track eligible-appraiser selection, RFPs/responses, regret and notice-to-proceed letters, bid amounts and due dates. Idaho adds appraiser licensing and agency rating reporting. | G58: Functional | H58: =IF(COUNTIF(M58:R58,"M")>0,"Must Have",IF(COUNTIF(M58:R58,"S")>0,"Should Have",IF(COUNTIF(M58:R58,"C")>0,"Could Have",IF(COUNTA(M58:R58)>0,"Stated – no priority","Aurigo-only (no RFP source)")))) -> Must Have | I58: =COUNTA(M58:R58) -> 2 | J58: =COUNTIF(M58:R58,"M") -> 2 | K58: =IF(I58=0,"Aurigo-only",IF(I58=1,"Single source",IF(I58=2,"Two sources",IF(I58<=4,"Common (3-4)","Broad (5+)")))) -> Two sources | L58: =IF(J58>=3,"Tier 1: Must in 3+ sources",IF(J58=2,"Tier 2: Must in 2 sources",IF(J58=1,"Tier 3: Must in 1 source",IF(COUNTIF(M58:R58,"S")>0,"Tier 4: Should only",IF(COUNTIF(M58:R58,"C")>0,"Tier 5: Could only",IF(I58>0,"Tier 6: stated, no priority","Aurigo-only")))))) -> Tier 2: Must in 2 sources | M58: M | N58: M | S58: NH DOT ROWMS & Rail Requirements: Tab 5 Appraisal – row 11 [Required / Medium]; Tab 5 Appraisal – row 12 [Required / High]; Tab 5 Appraisal – row 14 [Required / High] Idaho ITD RFP Event 85 – ROWMS: §9.14 Value Added Services ['must' requirement (§9)] | V58: Partial | W58: SOW library 'Appraisal Agent' / 'Consultant Firms' (Original SOW); scoring/RFP tracking not evidenced | Z58: R10 | AA58: Appraisal depth | Utilities agreements & reimbursement (parallel track) | AB58: 110 | AC58: ROW-042
A59: ROW-056 | B59: Land Acquisition & Relocation | C59: Appraisal & Review | D59: Appraiser management | E59: Appraiser scheduling (due dates, site visits) | F59: Scheduling feature to manage due dates, site visits and submission timelines. | G59: Functional | H59: =IF(COUNTIF(M59:R59,"M")>0,"Must Have",IF(COUNTIF(M59:R59,"S")>0,"Should Have",IF(COUNTIF(M59:R59,"C")>0,"Could Have",IF(COUNTA(M59:R59)>0,"Stated – no priority","Aurigo-only (no RFP source)")))) -> Must Have | I59: =COUNTA(M59:R59) -> 1 | J59: =COUNTIF(M59:R59,"M") -> 1 | K59: =IF(I59=0,"Aurigo-only",IF(I59=1,"Single source",IF(I59=2,"Two sources",IF(I59<=4,"Common (3-4)","Broad (5+)")))) -> Single source | L59: =IF(J59>=3,"Tier 1: Must in 3+ sources",IF(J59=2,"Tier 2: Must in 2 sources",IF(J59=1,"Tier 3: Must in 1 source",IF(COUNTIF(M59:R59,"S")>0,"Tier 4: Should only",IF(COUNTIF(M59:R59,"C")>0,"Tier 5: Could only",IF(I59>0,"Tier 6: stated, no priority","Aurigo-only")))))) -> Tier 3: Must in 1 source | M59: M | S59: NH DOT ROWMS & Rail Requirements: Tab 5 Appraisal – row 15 [Required / High] | V59: Not evidenced | W59: No matching item found in the provided Aurigo documents (SOW, demo script, deck, library list). | Z59: R10 | AA59: Appraisal depth | Utilities agreements & reimbursement (parallel track) | AB59: 112 | AC59: ROW-042
A60: ROW-057 | B60: Land Acquisition & Relocation | C60: Appraisal & Review | D60: Appraiser management | E60: Secure external appraiser upload and feedback | F60: External appraisers securely upload documents and receive feedback inside the platform ('better than an FTP'). | G60: Functional | H60: =IF(COUNTIF(M60:R60,"M")>0,"Must Have",IF(COUNTIF(M60:R60,"S")>0,"Should Have",IF(COUNTIF(M60:R60,"C")>0,"Could Have",IF(COUNTA(M60:R60)>0,"Stated – no priority","Aurigo-only (no RFP source)")))) -> Must Have | I60: =COUNTA(M60:R60) -> 1 | J60: =COUNTIF(M60:R60,"M") -> 1 | K60: =IF(I60=0,"Aurigo-only",IF(I60=1,"Single source",IF(I60=2,"Two sources",IF(I60<=4,"Common (3-4)","Broad (5+)")))) -> Single source | L60: =IF(J60>=3,"Tier 1: Must in 3+ sources",IF(J60=2,"Tier 2: Must in 2 sources",IF(J60=1,"Tier 3: Must in 1 source",IF(COUNTIF(M60:R60,"S")>0,"Tier 4: Should only",IF(COUNTIF(M60:R60,"C")>0,"Tier 5: Could only",IF(I60>0,"Tier 6: stated, no priority","Aurigo-only")))))) -> Tier 3: Must in 1 source | M60: M | S60: NH DOT ROWMS & Rail Requirements: Tab 5 Appraisal – row 16 [Required / High]; Tab 1 General – row 3 [Required / High] | V60: Not evidenced | W60: No matching item found in the provided Aurigo documents (SOW, demo script, deck, library list). | Z60: R32 | AA60: External portals, public access & records | AB60: 299 | AC60: ROW-042, ROW-173
A61: ROW-058 | B61: Land Acquisition & Relocation | C61: Appraisal & Review | D61: Appraiser management | E61: Appraiser payment initiation and tracking | F61: Initiate and track payment of contract appraisers. | G61: Functional | H61: =IF(COUNTIF(M61:R61,"M")>0,"Must Have",IF(COUNTIF(M61:R61,"S")>0,"Should Have",IF(COUNTIF(M61:R61,"C")>0,"Could Have",IF(COUNTA(M61:R61)>0,"Stated – no priority","Aurigo-only (no RFP source)")))) -> Must Have | I61: =COUNTA(M61:R61) -> 1 | J61: =COUNTIF(M61:R61,"M") -> 1 | K61: =IF(I61=0,"Aurigo-only",IF(I61=1,"Single source",IF(I61=2,"Two sources",IF(I61<=4,"Common (3-4)","Broad (5+)")))) -> Single source | L61: =IF(J61>=3,"Tier 1: Must in 3+ sources",IF(J61=2,"Tier 2: Must in 2 sources",IF(J61=1,"Tier 3: Must in 1 source",IF(COUNTIF(M61:R61,"S")>0,"Tier 4: Should only",IF(COUNTIF(M61:R61,"C")>0,"Tier 5: Could only",IF(I61>0,"Tier 6: stated, no priority","Aurigo-only")))))) -> Tier 3: Must in 1 source | M61: M | S61: NH DOT ROWMS & Rail Requirements: Tab 5 Appraisal – row 17 [Required / High] | V61: Not evidenced | W61: No matching item found in the provided Aurigo documents (SOW, demo script, deck, library list). | Z61: R13 | AA61: Payments & compensation (tracked in-system) | AB61: 158 | AC61: ROW-042, ROW-108
A62: ROW-059 | B62: Land Acquisition & Relocation | C62: Appraisal & Review | D62: Compliance | E62: Appraisal standards alignment and required review documents | F62: Workflows aligned with the Uniform Act (URA), USPAP and state DOT appraisal standards; generate review and approval documents required by the Uniform Act and ROW Manual. | G62: Functional | H62: =IF(COUNTIF(M62:R62,"M")>0,"Must Have",IF(COUNTIF(M62:R62,"S")>0,"Should Have",IF(COUNTIF(M62:R62,"C")>0,"Could Have",IF(COUNTA(M62:R62)>0,"Stated – no priority","Aurigo-only (no RFP source)")))) -> Must Have | I62: =COUNTA(M62:R62) -> 2 | J62: =COUNTIF(M62:R62,"M") -> 2 | K62: =IF(I62=0,"Aurigo-only",IF(I62=1,"Single source",IF(I62=2,"Two sources",IF(I62<=4,"Common (3-4)","Broad (5+)")))) -> Two sources | L62: =IF(J62>=3,"Tier 1: Must in 3+ sources",IF(J62=2,"Tier 2: Must in 2 sources",IF(J62=1,"Tier 3: Must in 1 source",IF(COUNTIF(M62:R62,"S")>0,"Tier 4: Should only",IF(COUNTIF(M62:R62,"C")>0,"Tier 5: Could only",IF(I62>0,"Tier 6: stated, no priority","Aurigo-only")))))) -> Tier 2: Must in 2 sources | M62: M | N62: M | S62: NH DOT ROWMS & Rail Requirements: Tab 5 Appraisal – row 19 [Optional / Medium]; Tab 5 Appraisal – row 20 [Required / High] Idaho ITD RFP Event 85 – ROWMS: §9 General Requirements: ['must' requirement (§9)] | T62: URA / Uniform Act; USPAP; ROW Manual | V62: Not evidenced | W62: No matching item found in the provided Aurigo documents (SOW, demo script, deck, library list). | Z62: R10 | AA62: Appraisal depth | Utilities agreements & reimbursement (parallel track) | AB62: 115 | AC62: ROW-044
A63: ROW-060 | B63: Land Acquisition & Relocation | C63: Appraisal & Review | D63: Market data | E63: Comparable sales database with GIS visualization | F63: Database of comparable sales/leases for all property types with multi-factor search, populated from fee appraisal reports; visualize comps on a GIS map with transaction data; support market analysis. | G63: Functional | H63: =IF(COUNTIF(M63:R63,"M")>0,"Must Have",IF(COUNTIF(M63:R63,"S")>0,"Should Have",IF(COUNTIF(M63:R63,"C")>0,"Could Have",IF(COUNTA(M63:R63)>0,"Stated – no priority","Aurigo-only (no RFP source)")))) -> Must Have | I63: =COUNTA(M63:R63) -> 1 | J63: =COUNTIF(M63:R63,"M") -> 1 | K63: =IF(I63=0,"Aurigo-only",IF(I63=1,"Single source",IF(I63=2,"Two sources",IF(I63<=4,"Common (3-4)","Broad (5+)")))) -> Single source | L63: =IF(J63>=3,"Tier 1: Must in 3+ sources",IF(J63=2,"Tier 2: Must in 2 sources",IF(J63=1,"Tier 3: Must in 1 source",IF(COUNTIF(M63:R63,"S")>0,"Tier 4: Should only",IF(COUNTIF(M63:R63,"C")>0,"Tier 5: Could only",IF(I63>0,"Tier 6: stated, no priority","Aurigo-only")))))) -> Tier 3: Must in 1 source | M63: M | S63: NH DOT ROWMS & Rail Requirements: Tab 5 Appraisal – row 28 [Required / Medium]; Tab 5 Appraisal – row 30 [Required / High]; Tab 9 Reports – row 16 [Required / High] | V63: Not evidenced | W63: No matching item found in the provided Aurigo documents (SOW, demo script, deck, library list). | Z63: R10 | AA63: Appraisal depth | Utilities agreements & reimbursement (parallel track) | AB63: 116 | AC63: ROW-043, ROW-180
A64: ROW-061 | B64: Land Acquisition & Relocation | C64: Appraisal & Review | D64: Market data | E64: Appraisal data extraction and cross-parcel summaries | F64: Extract key appraisal fields (land value, damages, parts taken, severance, improvements, cost to cure, total compensation) for reporting/mapping with keyword/fuzzy search; summarize outcomes across parcels or projects (e.g., average acquisition cost). | G64: Reporting | H64: =IF(COUNTIF(M64:R64,"M")>0,"Must Have",IF(COUNTIF(M64:R64,"S")>0,"Should Have",IF(COUNTIF(M64:R64,"C")>0,"Could Have",IF(COUNTA(M64:R64)>0,"Stated – no priority","Aurigo-only (no RFP source)")))) -> Should Have | I64: =COUNTA(M64:R64) -> 1 | J64: =COUNTIF(M64:R64,"M") -> 0 | K64: =IF(I64=0,"Aurigo-only",IF(I64=1,"Single source",IF(I64=2,"Two sources",IF(I64<=4,"Common (3-4)","Broad (5+)")))) -> Single source | L64: =IF(J64>=3,"Tier 1: Must in 3+ sources",IF(J64=2,"Tier 2: Must in 2 sources",IF(J64=1,"Tier 3: Must in 1 source",IF(COUNTIF(M64:R64,"S")>0,"Tier 4: Should only",IF(COUNTIF(M64:R64,"C")>0,"Tier 5: Could only",IF(I64>0,"Tier 6: stated, no priority","Aurigo-only")))))) -> Tier 4: Should only | M64: S | S64: NH DOT ROWMS & Rail Requirements: Tab 5 Appraisal – row 23 [Optional / Medium]; Tab 5 Appraisal – row 24 [Optional/Demo / Medium] | V64: Not evidenced | W64: No matching item found in the provided Aurigo documents (SOW, demo script, deck, library list). | Z64: R10 | AA64: Appraisal depth | Utilities agreements & reimbursement (parallel track) | AB64: 118 | AC64: ROW-043
A65: ROW-062 | B65: Land Acquisition & Relocation | C65: Appraisal & Review | D65: Market data | E65: Map-to-appraisal drill-through | F65: Link from the map view to the underlying appraisal report. | G65: Functional | H65: =IF(COUNTIF(M65:R65,"M")>0,"Must Have",IF(COUNTIF(M65:R65,"S")>0,"Should Have",IF(COUNTIF(M65:R65,"C")>0,"Could Have",IF(COUNTA(M65:R65)>0,"Stated – no priority","Aurigo-only (no RFP source)")))) -> Should Have | I65: =COUNTA(M65:R65) -> 1 | J65: =COUNTIF(M65:R65,"M") -> 0 | K65: =IF(I65=0,"Aurigo-only",IF(I65=1,"Single source",IF(I65=2,"Two sources",IF(I65<=4,"Common (3-4)","Broad (5+)")))) -> Single source | L65: =IF(J65>=3,"Tier 1: Must in 3+ sources",IF(J65=2,"Tier 2: Must in 2 sources",IF(J65=1,"Tier 3: Must in 1 source",IF(COUNTIF(M65:R65,"S")>0,"Tier 4: Should only",IF(COUNTIF(M65:R65,"C")>0,"Tier 5: Could only",IF(I65>0,"Tier 6: stated, no priority","Aurigo-only")))))) -> Tier 4: Should only | M65: S | S65: NH DOT ROWMS & Rail Requirements: Tab 5 Appraisal – row 29 [Optional / Medium] | V65: Not evidenced | W65: No matching item found in the provided Aurigo documents (SOW, demo script, deck, library list). | Z65: R10 | AA65: Appraisal depth | Utilities agreements & reimbursement (parallel track) | AB65: 119 | AC65: ROW-043, ROW-180
A66: ROW-063 | B66: Land Acquisition & Relocation | C66: Negotiation & Offers | D66: Offers | E66: Offer, counter-offer and agreement generation and tracking | F66: Generate, store and track offer letters, counter-offers and signed agreements; record negotiated settlement details in individual fields (date, amount, action, note) including payment/benefit breakdown and every offer/counter-offer. | G66: Functional | H66: =IF(COUNTIF(M66:R66,"M")>0,"Must Have",IF(COUNTIF(M66:R66,"S")>0,"Should Have",IF(COUNTIF(M66:R66,"C")>0,"Could Have",IF(COUNTA(M66:R66)>0,"Stated – no priority","Aurigo-only (no RFP source)")))) -> Must Have | I66: =COUNTA(M66:R66) -> 4 | J66: =COUNTIF(M66:R66,"M") -> 3 | K66: =IF(I66=0,"Aurigo-only",IF(I66=1,"Single source",IF(I66=2,"Two sources",IF(I66<=4,"Common (3-4)","Broad (5+)")))) -> Common (3-4) | L66: =IF(J66>=3,"Tier 1: Must in 3+ sources",IF(J66=2,"Tier 2: Must in 2 sources",IF(J66=1,"Tier 3: Must in 1 source",IF(COUNTIF(M66:R66,"S")>0,"Tier 4: Should only",IF(COUNTIF(M66:R66,"C")>0,"Tier 5: Could only",IF(I66>0,"Tier 6: stated, no priority","Aurigo-only")))))) -> Tier 1: Must in 3+ sources | M66: M | N66: M | P66: E | Q66: M | S66: NH DOT ROWMS & Rail Requirements: Tab 2 ROW Agent – row 18 [Required / High]; Tab 2 ROW Agent – row 20 [Required / High] Idaho ITD RFP Event 85 – ROWMS: §9 Negotiation and Acquisition Requirements ['must' requirement (§9)] WSDOT RFI (2023): Perf. Requirements – Property Acquisition & Relocation Services [RFI – performance requirement list (no priority given)] Austin Transit Partnership RFQ (2025): Scope – IV. Data Requirements [RFQ – requirement listed in scope] | V66: Covered (SOW) | W66: Pro SOW: 'Acquisition' > 'Negotiation'; Demo: Agreement form > Offers grid (Offer Type library) and Negotiation Amount Breakdown | Z66: R11 | AA66: Pre-offer review, offers & negotiation | AB66: 133 | AC66: ROW-046, ROW-175, ROW-256
A67: ROW-064 | B67: Land Acquisition & Relocation | C67: Negotiation & Offers | D67: Offers | E67: Negotiator assignment and notification | F67: Assign a negotiator (in-house or consultant) to each parcel and notify the project lead and negotiator in-system and by email; notify negotiator when appraisal approval makes a parcel ready for negotiation. | G67: Functional | H67: =IF(COUNTIF(M67:R67,"M")>0,"Must Have",IF(COUNTIF(M67:R67,"S")>0,"Should Have",IF(COUNTIF(M67:R67,"C")>0,"Could Have",IF(COUNTA(M67:R67)>0,"Stated – no priority","Aurigo-only (no RFP source)")))) -> Must Have | I67: =COUNTA(M67:R67) -> 1 | J67: =COUNTIF(M67:R67,"M") -> 1 | K67: =IF(I67=0,"Aurigo-only",IF(I67=1,"Single source",IF(I67=2,"Two sources",IF(I67<=4,"Common (3-4)","Broad (5+)")))) -> Single source | L67: =IF(J67>=3,"Tier 1: Must in 3+ sources",IF(J67=2,"Tier 2: Must in 2 sources",IF(J67=1,"Tier 3: Must in 1 source",IF(COUNTIF(M67:R67,"S")>0,"Tier 4: Should only",IF(COUNTIF(M67:R67,"C")>0,"Tier 5: Could only",IF(I67>0,"Tier 6: stated, no priority","Aurigo-only")))))) -> Tier 3: Must in 1 source | N67: M | S67: Idaho ITD RFP Event 85 – ROWMS: §9 Negotiation and Acquisition Requirements ['must' requirement (§9)] ×2; §9 Appraisal Requirements ['must' requirement (§9)] | V67: Not evidenced | W67: No matching item found in the provided Aurigo documents (SOW, demo script, deck, library list). | Z67: R11 | AA67: Pre-offer review, offers & negotiation | AB67: 132 | AC67: ROW-019, ROW-046
A68: ROW-065 | B68: Land Acquisition & Relocation | C68: Negotiation & Offers | D68: Offers | E68: Settlement and administrative-settlement recording | F68: Record the amount of any administrative settlement and settlement details; create an Acquisition Review Report summarizing the settlement; track just compensation vs. agreed settlement with reminders for related approval-agenda deadlines. | G68: Functional | H68: =IF(COUNTIF(M68:R68,"M")>0,"Must Have",IF(COUNTIF(M68:R68,"S")>0,"Should Have",IF(COUNTIF(M68:R68,"C")>0,"Could Have",IF(COUNTA(M68:R68)>0,"Stated – no priority","Aurigo-only (no RFP source)")))) -> Must Have | I68: =COUNTA(M68:R68) -> 2 | J68: =COUNTIF(M68:R68,"M") -> 2 | K68: =IF(I68=0,"Aurigo-only",IF(I68=1,"Single source",IF(I68=2,"Two sources",IF(I68<=4,"Common (3-4)","Broad (5+)")))) -> Two sources | L68: =IF(J68>=3,"Tier 1: Must in 3+ sources",IF(J68=2,"Tier 2: Must in 2 sources",IF(J68=1,"Tier 3: Must in 1 source",IF(COUNTIF(M68:R68,"S")>0,"Tier 4: Should only",IF(COUNTIF(M68:R68,"C")>0,"Tier 5: Could only",IF(I68>0,"Tier 6: stated, no priority","Aurigo-only")))))) -> Tier 2: Must in 2 sources | M68: M | N68: M | S68: NH DOT ROWMS & Rail Requirements: Tab 2 ROW Agent – row 21 [Required / High] Idaho ITD RFP Event 85 – ROWMS: §9 Negotiation and Acquisition Requirements ['must' requirement (§9)] ×2 | V68: Covered (SOW) | W68: Demo: Agreement form > Administrative Settlement section | X68: NH T2!R21 mentions 'G&C agenda items'; 'G&C' is not defined in the file. | Z68: R11 | AA68: Pre-offer review, offers & negotiation | AB68: 139 | AC68: ROW-063
A69: ROW-066 | B69: Land Acquisition & Relocation | C69: Negotiation & Offers | D69: Offers | E69: Offer package and delivery tracking | F69: Identify the documents in the original offer (Advice of Rights, brochure, appraisal, claim for payment, ROW contract, deeds, easements, possession agreement, relocation brochure) and record date and method delivered; record the date Advice of Rights was presented. | G69: Functional | H69: =IF(COUNTIF(M69:R69,"M")>0,"Must Have",IF(COUNTIF(M69:R69,"S")>0,"Should Have",IF(COUNTIF(M69:R69,"C")>0,"Could Have",IF(COUNTA(M69:R69)>0,"Stated – no priority","Aurigo-only (no RFP source)")))) -> Must Have | I69: =COUNTA(M69:R69) -> 1 | J69: =COUNTIF(M69:R69,"M") -> 1 | K69: =IF(I69=0,"Aurigo-only",IF(I69=1,"Single source",IF(I69=2,"Two sources",IF(I69<=4,"Common (3-4)","Broad (5+)")))) -> Single source | L69: =IF(J69>=3,"Tier 1: Must in 3+ sources",IF(J69=2,"Tier 2: Must in 2 sources",IF(J69=1,"Tier 3: Must in 1 source",IF(COUNTIF(M69:R69,"S")>0,"Tier 4: Should only",IF(COUNTIF(M69:R69,"C")>0,"Tier 5: Could only",IF(I69>0,"Tier 6: stated, no priority","Aurigo-only")))))) -> Tier 3: Must in 1 source | N69: M | S69: Idaho ITD RFP Event 85 – ROWMS: §9 Negotiation and Acquisition Requirements ['must' requirement (§9)] ×2 | V69: Not evidenced | W69: No matching item found in the provided Aurigo documents (SOW, demo script, deck, library list). | Z69: R11 | AA69: Pre-offer review, offers & negotiation | AB69: 134 | AC69: ROW-063
A70: ROW-067 | B70: Land Acquisition & Relocation | C70: Negotiation & Offers | D70: Offers | E70: Impasse letter and condemnation-recommendation data | F70: Generate an impasse letter (final notice that negotiations cease, request for possession agreement, condemnation to proceed after a deadline) and capture last offer, owner's ask, number of attempts and reasons for recommending condemnation. | G70: Functional | H70: =IF(COUNTIF(M70:R70,"M")>0,"Must Have",IF(COUNTIF(M70:R70,"S")>0,"Should Have",IF(COUNTIF(M70:R70,"C")>0,"Could Have",IF(COUNTA(M70:R70)>0,"Stated – no priority","Aurigo-only (no RFP source)")))) -> Must Have | I70: =COUNTA(M70:R70) -> 1 | J70: =COUNTIF(M70:R70,"M") -> 1 | K70: =IF(I70=0,"Aurigo-only",IF(I70=1,"Single source",IF(I70=2,"Two sources",IF(I70<=4,"Common (3-4)","Broad (5+)")))) -> Single source | L70: =IF(J70>=3,"Tier 1: Must in 3+ sources",IF(J70=2,"Tier 2: Must in 2 sources",IF(J70=1,"Tier 3: Must in 1 source",IF(COUNTIF(M70:R70,"S")>0,"Tier 4: Should only",IF(COUNTIF(M70:R70,"C")>0,"Tier 5: Could only",IF(I70>0,"Tier 6: stated, no priority","Aurigo-only")))))) -> Tier 3: Must in 1 source | N70: M | S70: Idaho ITD RFP Event 85 – ROWMS: §9 Negotiation and Acquisition Requirements ['must' requirement (§9)] ×2 | V70: Not evidenced | W70: No matching item found in the provided Aurigo documents (SOW, demo script, deck, library list). | Z70: R11 | AA70: Pre-offer review, offers & negotiation | AB70: 140 | AC70: ROW-063
A71: ROW-068 | B71: Land Acquisition & Relocation | C71: Negotiation & Offers | D71: Offers | E71: Owner retention of improvements / salvage valuation | F71: Record an owner's request to retain improvements and appurtenances and show updated (salvage) valuation, storing the salvage form. | G71: Functional | H71: =IF(COUNTIF(M71:R71,"M")>0,"Must Have",IF(COUNTIF(M71:R71,"S")>0,"Should Have",IF(COUNTIF(M71:R71,"C")>0,"Could Have",IF(COUNTA(M71:R71)>0,"Stated – no priority","Aurigo-only (no RFP source)")))) -> Must Have | I71: =COUNTA(M71:R71) -> 1 | J71: =COUNTIF(M71:R71,"M") -> 1 | K71: =IF(I71=0,"Aurigo-only",IF(I71=1,"Single source",IF(I71=2,"Two sources",IF(I71<=4,"Common (3-4)","Broad (5+)")))) -> Single source | L71: =IF(J71>=3,"Tier 1: Must in 3+ sources",IF(J71=2,"Tier 2: Must in 2 sources",IF(J71=1,"Tier 3: Must in 1 source",IF(COUNTIF(M71:R71,"S")>0,"Tier 4: Should only",IF(COUNTIF(M71:R71,"C")>0,"Tier 5: Could only",IF(I71>0,"Tier 6: stated, no priority","Aurigo-only")))))) -> Tier 3: Must in 1 source | N71: M | S71: Idaho ITD RFP Event 85 – ROWMS: §9 Negotiation and Acquisition Requirements ['must' requirement (§9)] ×2 | V71: Not evidenced | W71: No matching item found in the provided Aurigo documents (SOW, demo script, deck, library list). | Z71: R11 | AA71: Pre-offer review, offers & negotiation | AB71: 141 | AC71: ROW-063
A72: ROW-069 | B72: Land Acquisition & Relocation | C72: Negotiation & Offers | D72: Offers | E72: Negotiator progress report | F72: Monthly (or user-defined period) report of assigned parcels by project and parcel number. | G72: Reporting | H72: =IF(COUNTIF(M72:R72,"M")>0,"Must Have",IF(COUNTIF(M72:R72,"S")>0,"Should Have",IF(COUNTIF(M72:R72,"C")>0,"Could Have",IF(COUNTA(M72:R72)>0,"Stated – no priority","Aurigo-only (no RFP source)")))) -> Must Have | I72: =COUNTA(M72:R72) -> 1 | J72: =COUNTIF(M72:R72,"M") -> 1 | K72: =IF(I72=0,"Aurigo-only",IF(I72=1,"Single source",IF(I72=2,"Two sources",IF(I72<=4,"Common (3-4)","Broad (5+)")))) -> Single source | L72: =IF(J72>=3,"Tier 1: Must in 3+ sources",IF(J72=2,"Tier 2: Must in 2 sources",IF(J72=1,"Tier 3: Must in 1 source",IF(COUNTIF(M72:R72,"S")>0,"Tier 4: Should only",IF(COUNTIF(M72:R72,"C")>0,"Tier 5: Could only",IF(I72>0,"Tier 6: stated, no priority","Aurigo-only")))))) -> Tier 3: Must in 1 source | N72: M | S72: Idaho ITD RFP Event 85 – ROWMS: §9 Negotiation and Acquisition Requirements ['must' requirement (§9)] | V72: Not evidenced | W72: No matching item found in the provided Aurigo documents (SOW, demo script, deck, library list). | Z72: R11 | AA72: Pre-offer review, offers & negotiation | AB72: 142 | AC72: ROW-064
A73: ROW-070 | B73: Land Acquisition & Relocation | C73: Negotiation & Offers | D73: Offers | E73: Key / property-item turnover at closing | F73: Document collection of keys, garage-door openers etc. at closing, with date, by whom and delivered to whom. | G73: Functional | H73: =IF(COUNTIF(M73:R73,"M")>0,"Must Have",IF(COUNTIF(M73:R73,"S")>0,"Should Have",IF(COUNTIF(M73:R73,"C")>0,"Could Have",IF(COUNTA(M73:R73)>0,"Stated – no priority","Aurigo-only (no RFP source)")))) -> Must Have | I73: =COUNTA(M73:R73) -> 1 | J73: =COUNTIF(M73:R73,"M") -> 1 | K73: =IF(I73=0,"Aurigo-only",IF(I73=1,"Single source",IF(I73=2,"Two sources",IF(I73<=4,"Common (3-4)","Broad (5+)")))) -> Single source | L73: =IF(J73>=3,"Tier 1: Must in 3+ sources",IF(J73=2,"Tier 2: Must in 2 sources",IF(J73=1,"Tier 3: Must in 1 source",IF(COUNTIF(M73:R73,"S")>0,"Tier 4: Should only",IF(COUNTIF(M73:R73,"C")>0,"Tier 5: Could only",IF(I73>0,"Tier 6: stated, no priority","Aurigo-only")))))) -> Tier 3: Must in 1 source | N73: M | S73: Idaho ITD RFP Event 85 – ROWMS: §9 Negotiation and Acquisition Requirements ['must' requirement (§9)] | V73: Not evidenced | W73: No matching item found in the provided Aurigo documents (SOW, demo script, deck, library list). | Z73: R12 | AA73: Agreements, easements & alternative acquisition paths | AB73: 144 | AC73: ROW-065
A74: ROW-071 | B74: Land Acquisition & Relocation | C74: Acquisition Workflow & Compliance | D74: Workflow | E74: Configurable workflow per acquisition type | F74: Customizable workflows for each acquisition type (acquisition, waiver, appraisal; fee, easement, temporary, donation) and for transactions such as leases, purchases and surplus conveyances. | G74: Functional | H74: =IF(COUNTIF(M74:R74,"M")>0,"Must Have",IF(COUNTIF(M74:R74,"S")>0,"Should Have",IF(COUNTIF(M74:R74,"C")>0,"Could Have",IF(COUNTA(M74:R74)>0,"Stated – no priority","Aurigo-only (no RFP source)")))) -> Must Have | I74: =COUNTA(M74:R74) -> 4 | J74: =COUNTIF(M74:R74,"M") -> 2 | K74: =IF(I74=0,"Aurigo-only",IF(I74=1,"Single source",IF(I74=2,"Two sources",IF(I74<=4,"Common (3-4)","Broad (5+)")))) -> Common (3-4) | L74: =IF(J74>=3,"Tier 1: Must in 3+ sources",IF(J74=2,"Tier 2: Must in 2 sources",IF(J74=1,"Tier 3: Must in 1 source",IF(COUNTIF(M74:R74,"S")>0,"Tier 4: Should only",IF(COUNTIF(M74:R74,"C")>0,"Tier 5: Could only",IF(I74>0,"Tier 6: stated, no priority","Aurigo-only")))))) -> Tier 2: Must in 2 sources | M74: M | N74: M | O74: S | P74: E | S74: NH DOT ROWMS & Rail Requirements: Tab 2 ROW Agent – row 12 [Required / High] Idaho ITD RFP Event 85 – ROWMS: §9 General Requirements: ['must' requirement (§9)] NMDOT RFP 06-0100: App. A §2 Project Objectives [SOW project objective ('system should')] WSDOT RFI (2023): Perf. Requirements – Property Acquisition & Relocation Services [RFI – performance requirement list (no priority given)] | V74: Covered (SOW) | W74: Platform workflow engine; SOW: preconfigured workflows on business-process forms; Pro SOW 'Workflow adhering to compliance' | Z74: R06 | AA74: Acquisition rules, authorization, compliance & alerts | AB74: 52 | AC74: ROW-165
A75: ROW-072 | B75: Land Acquisition & Relocation | C75: Acquisition Workflow & Compliance | D75: Workflow | E75: Ordered acquisition steps with step-gating | F75: Define required acquisition steps in order and, on request, block moving to the next step until prior steps are complete. NH example: with no NEPA approval date, no acquisition work may start (appraising may). | G75: Functional | H75: =IF(COUNTIF(M75:R75,"M")>0,"Must Have",IF(COUNTIF(M75:R75,"S")>0,"Should Have",IF(COUNTIF(M75:R75,"C")>0,"Could Have",IF(COUNTA(M75:R75)>0,"Stated – no priority","Aurigo-only (no RFP source)")))) -> Must Have | I75: =COUNTA(M75:R75) -> 2 | J75: =COUNTIF(M75:R75,"M") -> 2 | K75: =IF(I75=0,"Aurigo-only",IF(I75=1,"Single source",IF(I75=2,"Two sources",IF(I75<=4,"Common (3-4)","Broad (5+)")))) -> Two sources | L75: =IF(J75>=3,"Tier 1: Must in 3+ sources",IF(J75=2,"Tier 2: Must in 2 sources",IF(J75=1,"Tier 3: Must in 1 source",IF(COUNTIF(M75:R75,"S")>0,"Tier 4: Should only",IF(COUNTIF(M75:R75,"C")>0,"Tier 5: Could only",IF(I75>0,"Tier 6: stated, no priority","Aurigo-only")))))) -> Tier 2: Must in 2 sources | M75: M | N75: M | S75: NH DOT ROWMS & Rail Requirements: Tab 2 ROW Agent – row 13 [Required / High] Idaho ITD RFP Event 85 – ROWMS: §9 Negotiation and Acquisition Requirements ['must' requirement (§9)] | V75: Partial | W75: Demo: state-based workflows (e.g., Acquisition > Negotiation/Condemnation > Audit > Acquired); rule-based gating not evidenced | Z75: R06 | AA75: Acquisition rules, authorization, compliance & alerts | AB75: 55 | AC75: ROW-071
A76: ROW-073 | B76: Land Acquisition & Relocation | C76: Acquisition Workflow & Compliance | D76: Workflow | E76: Statutory timelines, auto-assigned deadlines and delay alerts | F76: Track acquisition dates against statutory timelines; auto-assign deadlines and alert on delays (date-time window); account for waivers that change time frames; start from an external notice-to-proceed trigger. | G76: Functional | H76: =IF(COUNTIF(M76:R76,"M")>0,"Must Have",IF(COUNTIF(M76:R76,"S")>0,"Should Have",IF(COUNTIF(M76:R76,"C")>0,"Could Have",IF(COUNTA(M76:R76)>0,"Stated – no priority","Aurigo-only (no RFP source)")))) -> Must Have | I76: =COUNTA(M76:R76) -> 1 | J76: =COUNTIF(M76:R76,"M") -> 1 | K76: =IF(I76=0,"Aurigo-only",IF(I76=1,"Single source",IF(I76=2,"Two sources",IF(I76<=4,"Common (3-4)","Broad (5+)")))) -> Single source | L76: =IF(J76>=3,"Tier 1: Must in 3+ sources",IF(J76=2,"Tier 2: Must in 2 sources",IF(J76=1,"Tier 3: Must in 1 source",IF(COUNTIF(M76:R76,"S")>0,"Tier 4: Should only",IF(COUNTIF(M76:R76,"C")>0,"Tier 5: Could only",IF(I76>0,"Tier 6: stated, no priority","Aurigo-only")))))) -> Tier 3: Must in 1 source | M76: M | S76: NH DOT ROWMS & Rail Requirements: Tab 2 ROW Agent – row 4 [Required / High]; Tab 2 ROW Agent – row 15 [Required / High] | T76: Statutory time lines (state/URA) | V76: Not evidenced | W76: No matching item found in the provided Aurigo documents (SOW, demo script, deck, library list). | Z76: R06 | AA76: Acquisition rules, authorization, compliance & alerts | AB76: 61 | AC76: ROW-010, ROW-071, ROW-170
A77: ROW-074 | B77: Land Acquisition & Relocation | C77: Acquisition Workflow & Compliance | D77: Workflow | E77: URA-based reminders for next action | F77: Prompt the next action per property and affected party based on the URA; allow multiple reminders, an outstanding-items report and editable reminder dates. | G77: Functional | H77: =IF(COUNTIF(M77:R77,"M")>0,"Must Have",IF(COUNTIF(M77:R77,"S")>0,"Should Have",IF(COUNTIF(M77:R77,"C")>0,"Could Have",IF(COUNTA(M77:R77)>0,"Stated – no priority","Aurigo-only (no RFP source)")))) -> Must Have | I77: =COUNTA(M77:R77) -> 1 | J77: =COUNTIF(M77:R77,"M") -> 1 | K77: =IF(I77=0,"Aurigo-only",IF(I77=1,"Single source",IF(I77=2,"Two sources",IF(I77<=4,"Common (3-4)","Broad (5+)")))) -> Single source | L77: =IF(J77>=3,"Tier 1: Must in 3+ sources",IF(J77=2,"Tier 2: Must in 2 sources",IF(J77=1,"Tier 3: Must in 1 source",IF(COUNTIF(M77:R77,"S")>0,"Tier 4: Should only",IF(COUNTIF(M77:R77,"C")>0,"Tier 5: Could only",IF(I77>0,"Tier 6: stated, no priority","Aurigo-only")))))) -> Tier 3: Must in 1 source | M77: M | S77: NH DOT ROWMS & Rail Requirements: Tab 2 ROW Agent – row 8 [Required / High] | T77: URA | V77: Not evidenced | W77: No matching item found in the provided Aurigo documents (SOW, demo script, deck, library list). | Z77: R06 | AA77: Acquisition rules, authorization, compliance & alerts | AB77: 62 | AC77: ROW-073
A78: ROW-075 | B78: Land Acquisition & Relocation | C78: Acquisition Workflow & Compliance | D78: Compliance | E78: URA / Uniform Act-aligned acquisition process | F78: Acquisition and relocation workflow aligned with the Uniform Relocation Assistance and Real Property Acquisition Policies Act and kept current; also state law (e.g., Texas Property Code per ATX). | G78: Functional | H78: =IF(COUNTIF(M78:R78,"M")>0,"Must Have",IF(COUNTIF(M78:R78,"S")>0,"Should Have",IF(COUNTIF(M78:R78,"C")>0,"Could Have",IF(COUNTA(M78:R78)>0,"Stated – no priority","Aurigo-only (no RFP source)")))) -> Must Have | I78: =COUNTA(M78:R78) -> 5 | J78: =COUNTIF(M78:R78,"M") -> 3 | K78: =IF(I78=0,"Aurigo-only",IF(I78=1,"Single source",IF(I78=2,"Two sources",IF(I78<=4,"Common (3-4)","Broad (5+)")))) -> Broad (5+) | L78: =IF(J78>=3,"Tier 1: Must in 3+ sources",IF(J78=2,"Tier 2: Must in 2 sources",IF(J78=1,"Tier 3: Must in 1 source",IF(COUNTIF(M78:R78,"S")>0,"Tier 4: Should only",IF(COUNTIF(M78:R78,"C")>0,"Tier 5: Could only",IF(I78>0,"Tier 6: stated, no priority","Aurigo-only")))))) -> Tier 1: Must in 3+ sources | M78: M | N78: M | O78: S | P78: E | Q78: M | S78: NH DOT ROWMS & Rail Requirements: Tab 2 ROW Agent – row 23 [Required / High] Idaho ITD RFP Event 85 – ROWMS: §9 General Requirements: ['must' requirement (§9)] NMDOT RFP 06-0100: App. A §2 Project Objectives [SOW project objective ('system should')] WSDOT RFI (2023): Perf. Requirements – Property Acquisition & Relocation Services [RFI – performance requirement list (no priority given)] Austin Transit Partnership RFQ (2025): Scope of Services [RFQ – requirement listed in scope] | T78: URA (49 CFR 24 not cited in sources); Texas Property Code; ROW Manual | V78: Covered (SOW) | W78: Pro SOW: 'Workflow adhering to compliance'; Deck: 'Adherence to Legal Compliance' | Z78: R06 | AA78: Acquisition rules, authorization, compliance & alerts | AB78: 54 | AC78: ROW-071
A79: ROW-076 | B79: Land Acquisition & Relocation | C79: Acquisition Workflow & Compliance | D79: Compliance | E79: Environmental (NEPA) clearance tracking | F79: Track environmental clearance status and use it to gate acquisition; report clearance status (Environmental clearance, ROW certification, possession, acquisition) and clearance performance vs. target. | G79: Functional | H79: =IF(COUNTIF(M79:R79,"M")>0,"Must Have",IF(COUNTIF(M79:R79,"S")>0,"Should Have",IF(COUNTIF(M79:R79,"C")>0,"Could Have",IF(COUNTA(M79:R79)>0,"Stated – no priority","Aurigo-only (no RFP source)")))) -> Must Have | I79: =COUNTA(M79:R79) -> 3 | J79: =COUNTIF(M79:R79,"M") -> 3 | K79: =IF(I79=0,"Aurigo-only",IF(I79=1,"Single source",IF(I79=2,"Two sources",IF(I79<=4,"Common (3-4)","Broad (5+)")))) -> Common (3-4) | L79: =IF(J79>=3,"Tier 1: Must in 3+ sources",IF(J79=2,"Tier 2: Must in 2 sources",IF(J79=1,"Tier 3: Must in 1 source",IF(COUNTIF(M79:R79,"S")>0,"Tier 4: Should only",IF(COUNTIF(M79:R79,"C")>0,"Tier 5: Could only",IF(I79>0,"Tier 6: stated, no priority","Aurigo-only")))))) -> Tier 1: Must in 3+ sources | M79: M | N79: M | Q79: M | S79: NH DOT ROWMS & Rail Requirements: Tab 2 ROW Agent – row 13 [Required / High] Idaho ITD RFP Event 85 – ROWMS: §9 Management Reporting – Project Management Reports ['must' requirement (§9)]; §9 Management Reporting - Performance Measures ['must' requirement (§9)] Austin Transit Partnership RFQ (2025): Scope – IV. Data Requirements [RFQ – requirement listed in scope] | V79: Not evidenced | W79: No matching item found in the provided Aurigo documents (SOW, demo script, deck, library list). | Z79: R06 | AA79: Acquisition rules, authorization, compliance & alerts | AB79: 56 | AC79: ROW-072
A80: ROW-077 | B80: Land Acquisition & Relocation | C80: Acquisition Workflow & Compliance | D80: Compliance | E80: Right-of-entry management | F80: Track rights of entry as part of pre-acquisition and report on all rights of entry. | G80: Functional | H80: =IF(COUNTIF(M80:R80,"M")>0,"Must Have",IF(COUNTIF(M80:R80,"S")>0,"Should Have",IF(COUNTIF(M80:R80,"C")>0,"Could Have",IF(COUNTA(M80:R80)>0,"Stated – no priority","Aurigo-only (no RFP source)")))) -> Must Have | I80: =COUNTA(M80:R80) -> 2 | J80: =COUNTIF(M80:R80,"M") -> 2 | K80: =IF(I80=0,"Aurigo-only",IF(I80=1,"Single source",IF(I80=2,"Two sources",IF(I80<=4,"Common (3-4)","Broad (5+)")))) -> Two sources | L80: =IF(J80>=3,"Tier 1: Must in 3+ sources",IF(J80=2,"Tier 2: Must in 2 sources",IF(J80=1,"Tier 3: Must in 1 source",IF(COUNTIF(M80:R80,"S")>0,"Tier 4: Should only",IF(COUNTIF(M80:R80,"C")>0,"Tier 5: Could only",IF(I80>0,"Tier 6: stated, no priority","Aurigo-only")))))) -> Tier 2: Must in 2 sources | Q80: M | R80: M | S80: Austin Transit Partnership RFQ (2025): Scope – A. Data Management [RFQ – requirement listed in scope] Osceola County BRD §6.1.7 (real estate/ROW): BRD §6.1.7/§7.1 – Req 1184 [Must Have] | V80: Not evidenced | W80: No matching item found in the provided Aurigo documents (SOW, demo script, deck, library list). | Z80: R06 | AA80: Acquisition rules, authorization, compliance & alerts | AB80: 57 | AC80: ROW-014, ROW-072
A81: ROW-078 | B81: Land Acquisition & Relocation | C81: Acquisition Workflow & Compliance | D81: Compliance | E81: Easement management (types, locations, expiry) | F81: Record easements: type, purpose, location, grantor/grantee, legal description, recorded-document information, start/end dates; track temporary easements with time limits, expiration dates and notification requirements; report all easements. | G81: Functional | H81: =IF(COUNTIF(M81:R81,"M")>0,"Must Have",IF(COUNTIF(M81:R81,"S")>0,"Should Have",IF(COUNTIF(M81:R81,"C")>0,"Could Have",IF(COUNTA(M81:R81)>0,"Stated – no priority","Aurigo-only (no RFP source)")))) -> Must Have | I81: =COUNTA(M81:R81) -> 3 | J81: =COUNTIF(M81:R81,"M") -> 2 | K81: =IF(I81=0,"Aurigo-only",IF(I81=1,"Single source",IF(I81=2,"Two sources",IF(I81<=4,"Common (3-4)","Broad (5+)")))) -> Common (3-4) | L81: =IF(J81>=3,"Tier 1: Must in 3+ sources",IF(J81=2,"Tier 2: Must in 2 sources",IF(J81=1,"Tier 3: Must in 1 source",IF(COUNTIF(M81:R81,"S")>0,"Tier 4: Should only",IF(COUNTIF(M81:R81,"C")>0,"Tier 5: Could only",IF(I81>0,"Tier 6: stated, no priority","Aurigo-only")))))) -> Tier 2: Must in 2 sources | P81: E | Q81: M | R81: M | S81: WSDOT RFI (2023): Perf. Requirements – Property Acquisition & Relocation Services [RFI – performance requirement list (no priority given)] Austin Transit Partnership RFQ (2025): Scope – IV. Data Requirements [RFQ – requirement listed in scope] Osceola County BRD §6.1.7 (real estate/ROW): BRD §6.1.7/§7.1 – Req 1185 [Must Have] | V81: Covered (SOW) | W81: Demo: Easements form (type, dates, start/end station); SOW library 'Easement Type' | Z81: R12 | AA81: Agreements, easements & alternative acquisition paths | AB81: 143 | AC81: ROW-014, ROW-065
A82: ROW-079 | B82: Land Acquisition & Relocation | C82: Acquisition Workflow & Compliance | D82: Compliance | E82: Audit trail and documentation for federal review / reimbursement | F82: Maintain a clear audit trail and the documentation required for federal review or reimbursement, and be able to satisfy an FHWA audit. | G82: Non-functional | H82: =IF(COUNTIF(M82:R82,"M")>0,"Must Have",IF(COUNTIF(M82:R82,"S")>0,"Should Have",IF(COUNTIF(M82:R82,"C")>0,"Could Have",IF(COUNTA(M82:R82)>0,"Stated – no priority","Aurigo-only (no RFP source)")))) -> Must Have | I82: =COUNTA(M82:R82) -> 1 | J82: =COUNTIF(M82:R82,"M") -> 1 | K82: =IF(I82=0,"Aurigo-only",IF(I82=1,"Single source",IF(I82=2,"Two sources",IF(I82<=4,"Common (3-4)","Broad (5+)")))) -> Single source | L82: =IF(J82>=3,"Tier 1: Must in 3+ sources",IF(J82=2,"Tier 2: Must in 2 sources",IF(J82=1,"Tier 3: Must in 1 source",IF(COUNTIF(M82:R82,"S")>0,"Tier 4: Should only",IF(COUNTIF(M82:R82,"C")>0,"Tier 5: Could only",IF(I82>0,"Tier 6: stated, no priority","Aurigo-only")))))) -> Tier 3: Must in 1 source | M82: M | S82: NH DOT ROWMS & Rail Requirements: Tab 2 ROW Agent – row 24 [Required / High]; Tab 1 General – row 39 [Required / High] | T82: FHWA audit | V82: Not evidenced | W82: No matching item found in the provided Aurigo documents (SOW, demo script, deck, library list). | Z82: R06 | AA82: Acquisition rules, authorization, compliance & alerts | AB82: 65 | AC82: ROW-071, ROW-214
A83: ROW-080 | B83: Land Acquisition & Relocation | C83: Acquisition Workflow & Compliance | D83: Compliance | E83: Acquisition request intake and approval | F83: Internal and external users electronically request acquisition of a property; requests capture desired parameters and go through an approval workflow. | G83: Functional | H83: =IF(COUNTIF(M83:R83,"M")>0,"Must Have",IF(COUNTIF(M83:R83,"S")>0,"Should Have",IF(COUNTIF(M83:R83,"C")>0,"Could Have",IF(COUNTA(M83:R83)>0,"Stated – no priority","Aurigo-only (no RFP source)")))) -> Must Have | I83: =COUNTA(M83:R83) -> 1 | J83: =COUNTIF(M83:R83,"M") -> 1 | K83: =IF(I83=0,"Aurigo-only",IF(I83=1,"Single source",IF(I83=2,"Two sources",IF(I83<=4,"Common (3-4)","Broad (5+)")))) -> Single source | L83: =IF(J83>=3,"Tier 1: Must in 3+ sources",IF(J83=2,"Tier 2: Must in 2 sources",IF(J83=1,"Tier 3: Must in 1 source",IF(COUNTIF(M83:R83,"S")>0,"Tier 4: Should only",IF(COUNTIF(M83:R83,"C")>0,"Tier 5: Could only",IF(I83>0,"Tier 6: stated, no priority","Aurigo-only")))))) -> Tier 3: Must in 1 source | R83: M | S83: Osceola County BRD §6.1.7 (real estate/ROW): BRD §6.1.7/§7.1 – Req 1175 [Must Have]; BRD §6.1.7/§7.1 – Req 1176 [Must Have] | V83: Not evidenced | W83: No matching item found in the provided Aurigo documents (SOW, demo script, deck, library list). | Z83: R06 | AA83: Acquisition rules, authorization, compliance & alerts | AB83: 50 | AC83: ROW-005, ROW-165
A84: ROW-081 | B84: Land Acquisition & Relocation | C84: Acquisition Workflow & Compliance | D84: Compliance | E84: Acquisition agreement milestones and threshold alerts | F84: Capture agreement details (funding required, letter of intent, due diligence, title-work dates and deadlines) and alert when dollar limits or due dates are exceeded. | G84: Functional | H84: =IF(COUNTIF(M84:R84,"M")>0,"Must Have",IF(COUNTIF(M84:R84,"S")>0,"Should Have",IF(COUNTIF(M84:R84,"C")>0,"Could Have",IF(COUNTA(M84:R84)>0,"Stated – no priority","Aurigo-only (no RFP source)")))) -> Must Have | I84: =COUNTA(M84:R84) -> 1 | J84: =COUNTIF(M84:R84,"M") -> 1 | K84: =IF(I84=0,"Aurigo-only",IF(I84=1,"Single source",IF(I84=2,"Two sources",IF(I84<=4,"Common (3-4)","Broad (5+)")))) -> Single source | L84: =IF(J84>=3,"Tier 1: Must in 3+ sources",IF(J84=2,"Tier 2: Must in 2 sources",IF(J84=1,"Tier 3: Must in 1 source",IF(COUNTIF(M84:R84,"S")>0,"Tier 4: Should only",IF(COUNTIF(M84:R84,"C")>0,"Tier 5: Could only",IF(I84>0,"Tier 6: stated, no priority","Aurigo-only")))))) -> Tier 3: Must in 1 source | R84: M | S84: Osceola County BRD §6.1.7 (real estate/ROW): BRD §6.1.7/§7.1 – Req 1144 [Must Have] | V84: Not evidenced | W84: No matching item found in the provided Aurigo documents (SOW, demo script, deck, library list). | Z84: R12 | AA84: Agreements, easements & alternative acquisition paths | AB84: 145 | AC84: ROW-063, ROW-170
A85: ROW-082 | B85: Land Acquisition & Relocation | C85: Acquisition Workflow & Compliance | D85: Handoff | E85: Handoff from acquisition to property management | F85: Transfer responsibility from the acquisition agent to property-management care and tracking; auto-transfer acquired parcels (post-construction remnants) into property management. | G85: Functional | H85: =IF(COUNTIF(M85:R85,"M")>0,"Must Have",IF(COUNTIF(M85:R85,"S")>0,"Should Have",IF(COUNTIF(M85:R85,"C")>0,"Could Have",IF(COUNTA(M85:R85)>0,"Stated – no priority","Aurigo-only (no RFP source)")))) -> Should Have | I85: =COUNTA(M85:R85) -> 1 | J85: =COUNTIF(M85:R85,"M") -> 0 | K85: =IF(I85=0,"Aurigo-only",IF(I85=1,"Single source",IF(I85=2,"Two sources",IF(I85<=4,"Common (3-4)","Broad (5+)")))) -> Single source | L85: =IF(J85>=3,"Tier 1: Must in 3+ sources",IF(J85=2,"Tier 2: Must in 2 sources",IF(J85=1,"Tier 3: Must in 1 source",IF(COUNTIF(M85:R85,"S")>0,"Tier 4: Should only",IF(COUNTIF(M85:R85,"C")>0,"Tier 5: Could only",IF(I85>0,"Tier 6: stated, no priority","Aurigo-only")))))) -> Tier 4: Should only | M85: S | S85: NH DOT ROWMS & Rail Requirements: Tab 2 ROW Agent – row 16 [n/a / n/a]; Tab 6 Property Mgmt – row 7 [Desired / Medium] | V85: Not evidenced | W85: No matching item found in the provided Aurigo documents (SOW, demo script, deck, library list). | X85: NH T2!R16 has no Required/Priority value in the file. | Z85: R25 | AA85: Property inventory & handoff | AB85: 251 | AC85: ROW-065, ROW-117
A86: ROW-083 | B86: Land Acquisition & Relocation | C86: Acquisition Workflow & Compliance | D86: Handoff | E86: Lease-back / occupancy agreement after acquisition | F86: After relocation, show whether the area is leased back to the owner/tenant, whether an occupancy agreement exists and the rent charged. | G86: Functional | H86: =IF(COUNTIF(M86:R86,"M")>0,"Must Have",IF(COUNTIF(M86:R86,"S")>0,"Should Have",IF(COUNTIF(M86:R86,"C")>0,"Could Have",IF(COUNTA(M86:R86)>0,"Stated – no priority","Aurigo-only (no RFP source)")))) -> Must Have | I86: =COUNTA(M86:R86) -> 1 | J86: =COUNTIF(M86:R86,"M") -> 1 | K86: =IF(I86=0,"Aurigo-only",IF(I86=1,"Single source",IF(I86=2,"Two sources",IF(I86<=4,"Common (3-4)","Broad (5+)")))) -> Single source | L86: =IF(J86>=3,"Tier 1: Must in 3+ sources",IF(J86=2,"Tier 2: Must in 2 sources",IF(J86=1,"Tier 3: Must in 1 source",IF(COUNTIF(M86:R86,"S")>0,"Tier 4: Should only",IF(COUNTIF(M86:R86,"C")>0,"Tier 5: Could only",IF(I86>0,"Tier 6: stated, no priority","Aurigo-only")))))) -> Tier 3: Must in 1 source | M86: M | S86: NH DOT ROWMS & Rail Requirements: Tab 2 ROW Agent – row 34 [Required / High] | V86: Not evidenced | W86: No matching item found in the provided Aurigo documents (SOW, demo script, deck, library list). | Z86: R26 | AA86: Leases, occupancy & use agreements | AB86: 260 | AC86: ROW-082, ROW-125
A87: ROW-084 | B87: Land Acquisition & Relocation | C87: Acquisition Workflow & Compliance | D87: Integration | E87: Cross-module data sharing (title, acquisition, appraisal, relocation) | F87: Title records integrate with acquisition, appraisal and relocation modules, and the solution operates as a single integrated whole so data entered once is available everywhere. | G87: Functional | H87: =IF(COUNTIF(M87:R87,"M")>0,"Must Have",IF(COUNTIF(M87:R87,"S")>0,"Should Have",IF(COUNTIF(M87:R87,"C")>0,"Could Have",IF(COUNTA(M87:R87)>0,"Stated – no priority","Aurigo-only (no RFP source)")))) -> Must Have | I87: =COUNTA(M87:R87) -> 2 | J87: =COUNTIF(M87:R87,"M") -> 2 | K87: =IF(I87=0,"Aurigo-only",IF(I87=1,"Single source",IF(I87=2,"Two sources",IF(I87<=4,"Common (3-4)","Broad (5+)")))) -> Two sources | L87: =IF(J87>=3,"Tier 1: Must in 3+ sources",IF(J87=2,"Tier 2: Must in 2 sources",IF(J87=1,"Tier 3: Must in 1 source",IF(COUNTIF(M87:R87,"S")>0,"Tier 4: Should only",IF(COUNTIF(M87:R87,"C")>0,"Tier 5: Could only",IF(I87>0,"Tier 6: stated, no priority","Aurigo-only")))))) -> Tier 2: Must in 2 sources | M87: M | O87: M | S87: NH DOT ROWMS & Rail Requirements: Tab 4 Land Titles – row 17 [Required / High]; Tab 1 General – row 11 [Required / High] NMDOT RFP 06-0100: App. A §3.2.1 [SOW scope item / RFP purpose] | V87: Not evidenced | W87: No matching item found in the provided Aurigo documents (SOW, demo script, deck, library list). | Z87: R01 | AA87: Platform foundation & UI standards | AB87: 4 | AC87: None
A88: ROW-085 | B88: Land Acquisition & Relocation | C88: Relocation Assistance | D88: Relocation case | E88: Relocation case management (residential and non-residential) | F88: Document potential residential and non-residential relocations of owners, tenants and property; store displacee details, unique relocation ID, relocation type, claims and notices; confirm displacee list per parcel. | G88: Functional | H88: =IF(COUNTIF(M88:R88,"M")>0,"Must Have",IF(COUNTIF(M88:R88,"S")>0,"Should Have",IF(COUNTIF(M88:R88,"C")>0,"Could Have",IF(COUNTA(M88:R88)>0,"Stated – no priority","Aurigo-only (no RFP source)")))) -> Must Have | I88: =COUNTA(M88:R88) -> 4 | J88: =COUNTIF(M88:R88,"M") -> 3 | K88: =IF(I88=0,"Aurigo-only",IF(I88=1,"Single source",IF(I88=2,"Two sources",IF(I88<=4,"Common (3-4)","Broad (5+)")))) -> Common (3-4) | L88: =IF(J88>=3,"Tier 1: Must in 3+ sources",IF(J88=2,"Tier 2: Must in 2 sources",IF(J88=1,"Tier 3: Must in 1 source",IF(COUNTIF(M88:R88,"S")>0,"Tier 4: Should only",IF(COUNTIF(M88:R88,"C")>0,"Tier 5: Could only",IF(I88>0,"Tier 6: stated, no priority","Aurigo-only")))))) -> Tier 1: Must in 3+ sources | M88: M | N88: M | P88: E | Q88: M | S88: NH DOT ROWMS & Rail Requirements: Tab 2 ROW Agent – row 4 [Required / High] Idaho ITD RFP Event 85 – ROWMS: §9 Relocation Requirements ['must' requirement (§9)] ×2 WSDOT RFI (2023): Perf. Requirements – Property Acquisition & Relocation Services [RFI – performance requirement list (no priority given)] Austin Transit Partnership RFQ (2025): Scope – IV. Data Requirements [RFQ – requirement listed in scope] | T88: Federal relocation regulations (URA) | V88: Covered (SOW) | W88: Pro SOW: 'Parcel-Relocation', 'Residential Relocation', 'Non-Residential Relocation'; Demo: Relocation form | Z88: R18 | AA88: Relocation case, planning & notices | AB88: 194 | AC88: ROW-014, ROW-065
A89: ROW-086 | B89: Land Acquisition & Relocation | C89: Relocation Assistance | D89: Relocation case | E89: Relocation questionnaires and pre-populated worksheets | F89: Residential and non-residential relocation questionnaires (occupants, housing cost, business details, plans, lease terms) with worksheets pre-populated from earlier data. | G89: Functional | H89: =IF(COUNTIF(M89:R89,"M")>0,"Must Have",IF(COUNTIF(M89:R89,"S")>0,"Should Have",IF(COUNTIF(M89:R89,"C")>0,"Could Have",IF(COUNTA(M89:R89)>0,"Stated – no priority","Aurigo-only (no RFP source)")))) -> Must Have | I89: =COUNTA(M89:R89) -> 1 | J89: =COUNTIF(M89:R89,"M") -> 1 | K89: =IF(I89=0,"Aurigo-only",IF(I89=1,"Single source",IF(I89=2,"Two sources",IF(I89<=4,"Common (3-4)","Broad (5+)")))) -> Single source | L89: =IF(J89>=3,"Tier 1: Must in 3+ sources",IF(J89=2,"Tier 2: Must in 2 sources",IF(J89=1,"Tier 3: Must in 1 source",IF(COUNTIF(M89:R89,"S")>0,"Tier 4: Should only",IF(COUNTIF(M89:R89,"C")>0,"Tier 5: Could only",IF(I89>0,"Tier 6: stated, no priority","Aurigo-only")))))) -> Tier 3: Must in 1 source | N89: M | S89: Idaho ITD RFP Event 85 – ROWMS: §9 Relocation Requirements ['must' requirement (§9)] ×3 | V89: Covered (SOW) | W89: Pro SOW: 'Relocation Questionnaire'; Demo: Questionnaire form | Z89: R18 | AA89: Relocation case, planning & notices | AB89: 199 | AC89: ROW-085
A90: ROW-087 | B90: Land Acquisition & Relocation | C90: Relocation Assistance | D90: Calculations | E90: Relocation payment calculation (eligibility and amounts) | F90: Calculate eligible relocation payments for residential and business displacees under alternatives; NH adds calculating mortgage and assistance rates based on URA; store results in the system. | G90: Functional | H90: =IF(COUNTIF(M90:R90,"M")>0,"Must Have",IF(COUNTIF(M90:R90,"S")>0,"Should Have",IF(COUNTIF(M90:R90,"C")>0,"Could Have",IF(COUNTA(M90:R90)>0,"Stated – no priority","Aurigo-only (no RFP source)")))) -> Must Have | I90: =COUNTA(M90:R90) -> 3 | J90: =COUNTIF(M90:R90,"M") -> 2 | K90: =IF(I90=0,"Aurigo-only",IF(I90=1,"Single source",IF(I90=2,"Two sources",IF(I90<=4,"Common (3-4)","Broad (5+)")))) -> Common (3-4) | L90: =IF(J90>=3,"Tier 1: Must in 3+ sources",IF(J90=2,"Tier 2: Must in 2 sources",IF(J90=1,"Tier 3: Must in 1 source",IF(COUNTIF(M90:R90,"S")>0,"Tier 4: Should only",IF(COUNTIF(M90:R90,"C")>0,"Tier 5: Could only",IF(I90>0,"Tier 6: stated, no priority","Aurigo-only")))))) -> Tier 2: Must in 2 sources | M90: M | N90: M | P90: E | S90: NH DOT ROWMS & Rail Requirements: Tab 2 ROW Agent – row 9 [Required / High] Idaho ITD RFP Event 85 – ROWMS: §9 Relocation Requirements ['must' requirement (§9)] WSDOT RFI (2023): Perf. Requirements – Property Acquisition & Relocation Services [RFI – performance requirement list (no priority given)] | T90: URA | V90: Partial | W90: Demo: Relocation Eligibility (claim limit vs claimed) and Relocation Payments; calculation engine not evidenced | Z90: R19 | AA90: Replacement housing, eligibility & payment calculations | AB90: 205 | AC90: ROW-086
A91: ROW-088 | B91: Land Acquisition & Relocation | C91: Relocation Assistance | D91: Calculations | E91: Mortgage interest differential calculation | F91: Calculate the mortgage differential payment capturing loan balance, new loan amount, terms, rate, existing payment, points and amount financed. | G91: Functional | H91: =IF(COUNTIF(M91:R91,"M")>0,"Must Have",IF(COUNTIF(M91:R91,"S")>0,"Should Have",IF(COUNTIF(M91:R91,"C")>0,"Could Have",IF(COUNTA(M91:R91)>0,"Stated – no priority","Aurigo-only (no RFP source)")))) -> Must Have | I91: =COUNTA(M91:R91) -> 1 | J91: =COUNTIF(M91:R91,"M") -> 1 | K91: =IF(I91=0,"Aurigo-only",IF(I91=1,"Single source",IF(I91=2,"Two sources",IF(I91<=4,"Common (3-4)","Broad (5+)")))) -> Single source | L91: =IF(J91>=3,"Tier 1: Must in 3+ sources",IF(J91=2,"Tier 2: Must in 2 sources",IF(J91=1,"Tier 3: Must in 1 source",IF(COUNTIF(M91:R91,"S")>0,"Tier 4: Should only",IF(COUNTIF(M91:R91,"C")>0,"Tier 5: Could only",IF(I91>0,"Tier 6: stated, no priority","Aurigo-only")))))) -> Tier 3: Must in 1 source | N91: M | S91: Idaho ITD RFP Event 85 – ROWMS: §9 Relocation Requirements ['must' requirement (§9)] | V91: Not evidenced | W91: No matching item found in the provided Aurigo documents (SOW, demo script, deck, library list). | Z91: R19 | AA91: Replacement housing, eligibility & payment calculations | AB91: 207 | AC91: ROW-087, ROW-092
A92: ROW-089 | B92: Land Acquisition & Relocation | C92: Relocation Assistance | D92: Calculations | E92: Price differential calculation | F92: Store/calculate price differential (carve-outs, easements, adjusted FMV, list price of selected comparable). | G92: Functional | H92: =IF(COUNTIF(M92:R92,"M")>0,"Must Have",IF(COUNTIF(M92:R92,"S")>0,"Should Have",IF(COUNTIF(M92:R92,"C")>0,"Could Have",IF(COUNTA(M92:R92)>0,"Stated – no priority","Aurigo-only (no RFP source)")))) -> Must Have | I92: =COUNTA(M92:R92) -> 1 | J92: =COUNTIF(M92:R92,"M") -> 1 | K92: =IF(I92=0,"Aurigo-only",IF(I92=1,"Single source",IF(I92=2,"Two sources",IF(I92<=4,"Common (3-4)","Broad (5+)")))) -> Single source | L92: =IF(J92>=3,"Tier 1: Must in 3+ sources",IF(J92=2,"Tier 2: Must in 2 sources",IF(J92=1,"Tier 3: Must in 1 source",IF(COUNTIF(M92:R92,"S")>0,"Tier 4: Should only",IF(COUNTIF(M92:R92,"C")>0,"Tier 5: Could only",IF(I92>0,"Tier 6: stated, no priority","Aurigo-only")))))) -> Tier 3: Must in 1 source | N92: M | S92: Idaho ITD RFP Event 85 – ROWMS: §9 Relocation Requirements ['must' requirement (§9)] | V92: Not evidenced | W92: No matching item found in the provided Aurigo documents (SOW, demo script, deck, library list). | Z92: R19 | AA92: Replacement housing, eligibility & payment calculations | AB92: 208 | AC92: ROW-087, ROW-092
A93: ROW-090 | B93: Land Acquisition & Relocation | C93: Relocation Assistance | D93: Calculations | E93: Rental assistance payment calculation | F93: Store/calculate rental assistance using replacement vs. displacement rent and utilities, low-income classification and a maximum of monthly assistance times 42 months. | G93: Functional | H93: =IF(COUNTIF(M93:R93,"M")>0,"Must Have",IF(COUNTIF(M93:R93,"S")>0,"Should Have",IF(COUNTIF(M93:R93,"C")>0,"Could Have",IF(COUNTA(M93:R93)>0,"Stated – no priority","Aurigo-only (no RFP source)")))) -> Must Have | I93: =COUNTA(M93:R93) -> 1 | J93: =COUNTIF(M93:R93,"M") -> 1 | K93: =IF(I93=0,"Aurigo-only",IF(I93=1,"Single source",IF(I93=2,"Two sources",IF(I93<=4,"Common (3-4)","Broad (5+)")))) -> Single source | L93: =IF(J93>=3,"Tier 1: Must in 3+ sources",IF(J93=2,"Tier 2: Must in 2 sources",IF(J93=1,"Tier 3: Must in 1 source",IF(COUNTIF(M93:R93,"S")>0,"Tier 4: Should only",IF(COUNTIF(M93:R93,"C")>0,"Tier 5: Could only",IF(I93>0,"Tier 6: stated, no priority","Aurigo-only")))))) -> Tier 3: Must in 1 source | N93: M | S93: Idaho ITD RFP Event 85 – ROWMS: §9 Relocation Requirements ['must' requirement (§9)] | V93: Not evidenced | W93: No matching item found in the provided Aurigo documents (SOW, demo script, deck, library list). | Z93: R19 | AA93: Replacement housing, eligibility & payment calculations | AB93: 209 | AC93: ROW-087, ROW-092
A94: ROW-091 | B94: Land Acquisition & Relocation | C94: Relocation Assistance | D94: Calculations | E94: Integration with external relocation calculators | F94: Integrate with Excel-based or internal relocation calculators and link/store the worksheets. | G94: Integration | H94: =IF(COUNTIF(M94:R94,"M")>0,"Must Have",IF(COUNTIF(M94:R94,"S")>0,"Should Have",IF(COUNTIF(M94:R94,"C")>0,"Could Have",IF(COUNTA(M94:R94)>0,"Stated – no priority","Aurigo-only (no RFP source)")))) -> Must Have | I94: =COUNTA(M94:R94) -> 1 | J94: =COUNTIF(M94:R94,"M") -> 1 | K94: =IF(I94=0,"Aurigo-only",IF(I94=1,"Single source",IF(I94=2,"Two sources",IF(I94<=4,"Common (3-4)","Broad (5+)")))) -> Single source | L94: =IF(J94>=3,"Tier 1: Must in 3+ sources",IF(J94=2,"Tier 2: Must in 2 sources",IF(J94=1,"Tier 3: Must in 1 source",IF(COUNTIF(M94:R94,"S")>0,"Tier 4: Should only",IF(COUNTIF(M94:R94,"C")>0,"Tier 5: Could only",IF(I94>0,"Tier 6: stated, no priority","Aurigo-only")))))) -> Tier 3: Must in 1 source | N94: M | S94: Idaho ITD RFP Event 85 – ROWMS: §9 Relocation Requirements ['must' requirement (§9)] | V94: Not evidenced | W94: No matching item found in the provided Aurigo documents (SOW, demo script, deck, library list). | Z94: R34 | AA94: Document, mail, map & survey integrations | AB94: 317 | AC94: ROW-087
A95: ROW-092 | B95: Land Acquisition & Relocation | C95: Relocation Assistance | D95: Replacement housing | E95: Replacement-housing study and comparables | F95: Prepare a replacement housing study triggered by appraisal completion; record available replacement housing (location, price/rent, attributes, inspected by whom). | G95: Functional | H95: =IF(COUNTIF(M95:R95,"M")>0,"Must Have",IF(COUNTIF(M95:R95,"S")>0,"Should Have",IF(COUNTIF(M95:R95,"C")>0,"Could Have",IF(COUNTA(M95:R95)>0,"Stated – no priority","Aurigo-only (no RFP source)")))) -> Must Have | I95: =COUNTA(M95:R95) -> 1 | J95: =COUNTIF(M95:R95,"M") -> 1 | K95: =IF(I95=0,"Aurigo-only",IF(I95=1,"Single source",IF(I95=2,"Two sources",IF(I95<=4,"Common (3-4)","Broad (5+)")))) -> Single source | L95: =IF(J95>=3,"Tier 1: Must in 3+ sources",IF(J95=2,"Tier 2: Must in 2 sources",IF(J95=1,"Tier 3: Must in 1 source",IF(COUNTIF(M95:R95,"S")>0,"Tier 4: Should only",IF(COUNTIF(M95:R95,"C")>0,"Tier 5: Could only",IF(I95>0,"Tier 6: stated, no priority","Aurigo-only")))))) -> Tier 3: Must in 1 source | N95: M | S95: Idaho ITD RFP Event 85 – ROWMS: §9 Relocation Requirements ['must' requirement (§9)] ×2 | V95: Not evidenced | W95: No matching item found in the provided Aurigo documents (SOW, demo script, deck, library list). | Z95: R19 | AA95: Replacement housing, eligibility & payment calculations | AB95: 204 | AC95: ROW-086
A96: ROW-093 | B96: Land Acquisition & Relocation | C96: Relocation Assistance | D96: Claims & notices | E96: Relocation claim forms and statement of rent and income | F96: Generate and store claim forms for residential and non-residential displacees and a pre-populated statement of rent and income (occupant, rent, utilities, verification method, income). | G96: Functional | H96: =IF(COUNTIF(M96:R96,"M")>0,"Must Have",IF(COUNTIF(M96:R96,"S")>0,"Should Have",IF(COUNTIF(M96:R96,"C")>0,"Could Have",IF(COUNTA(M96:R96)>0,"Stated – no priority","Aurigo-only (no RFP source)")))) -> Must Have | I96: =COUNTA(M96:R96) -> 1 | J96: =COUNTIF(M96:R96,"M") -> 1 | K96: =IF(I96=0,"Aurigo-only",IF(I96=1,"Single source",IF(I96=2,"Two sources",IF(I96<=4,"Common (3-4)","Broad (5+)")))) -> Single source | L96: =IF(J96>=3,"Tier 1: Must in 3+ sources",IF(J96=2,"Tier 2: Must in 2 sources",IF(J96=1,"Tier 3: Must in 1 source",IF(COUNTIF(M96:R96,"S")>0,"Tier 4: Should only",IF(COUNTIF(M96:R96,"C")>0,"Tier 5: Could only",IF(I96>0,"Tier 6: stated, no priority","Aurigo-only")))))) -> Tier 3: Must in 1 source | N96: M | S96: Idaho ITD RFP Event 85 – ROWMS: §9 Relocation Requirements ['must' requirement (§9)] ×3 | V96: Not evidenced | W96: No matching item found in the provided Aurigo documents (SOW, demo script, deck, library list). | Z96: R18 | AA96: Relocation case, planning & notices | AB96: 200 | AC96: ROW-085
A97: ROW-094 | B97: Land Acquisition & Relocation | C97: Relocation Assistance | D97: Claims & notices | E97: Relocation notices (30/90-day, eligibility, brochure delivery) | F97: Generate 30-day vacate notices; record 90-day letter, Notice of Eligibility (replacement housing amount), and to whom/when the relocation brochure was delivered. | G97: Functional | H97: =IF(COUNTIF(M97:R97,"M")>0,"Must Have",IF(COUNTIF(M97:R97,"S")>0,"Should Have",IF(COUNTIF(M97:R97,"C")>0,"Could Have",IF(COUNTA(M97:R97)>0,"Stated – no priority","Aurigo-only (no RFP source)")))) -> Must Have | I97: =COUNTA(M97:R97) -> 2 | J97: =COUNTIF(M97:R97,"M") -> 2 | K97: =IF(I97=0,"Aurigo-only",IF(I97=1,"Single source",IF(I97=2,"Two sources",IF(I97<=4,"Common (3-4)","Broad (5+)")))) -> Two sources | L97: =IF(J97>=3,"Tier 1: Must in 3+ sources",IF(J97=2,"Tier 2: Must in 2 sources",IF(J97=1,"Tier 3: Must in 1 source",IF(COUNTIF(M97:R97,"S")>0,"Tier 4: Should only",IF(COUNTIF(M97:R97,"C")>0,"Tier 5: Could only",IF(I97>0,"Tier 6: stated, no priority","Aurigo-only")))))) -> Tier 2: Must in 2 sources | N97: M | Q97: M | S97: Idaho ITD RFP Event 85 – ROWMS: §9 Relocation Requirements ['must' requirement (§9)] ×3 Austin Transit Partnership RFQ (2025): Scope – IV. Data Requirements [RFQ – requirement listed in scope] | V97: Covered (SOW) | W97: Pro SOW: 'Relocation Notice' | Z97: R18 | AA97: Relocation case, planning & notices | AB97: 201 | AC97: ROW-085, ROW-170, ROW-175
A98: ROW-095 | B98: Land Acquisition & Relocation | C98: Relocation Assistance | D98: Claims & notices | E98: Eligibility-by-date computation and claim-expiry alerts | F98: Compute whether displacees can claim based on occupancy/displacement dates and alert (plus letter) a user-defined number of months before the claim eligibility expires. | G98: Functional | H98: =IF(COUNTIF(M98:R98,"M")>0,"Must Have",IF(COUNTIF(M98:R98,"S")>0,"Should Have",IF(COUNTIF(M98:R98,"C")>0,"Could Have",IF(COUNTA(M98:R98)>0,"Stated – no priority","Aurigo-only (no RFP source)")))) -> Must Have | I98: =COUNTA(M98:R98) -> 1 | J98: =COUNTIF(M98:R98,"M") -> 1 | K98: =IF(I98=0,"Aurigo-only",IF(I98=1,"Single source",IF(I98=2,"Two sources",IF(I98<=4,"Common (3-4)","Broad (5+)")))) -> Single source | L98: =IF(J98>=3,"Tier 1: Must in 3+ sources",IF(J98=2,"Tier 2: Must in 2 sources",IF(J98=1,"Tier 3: Must in 1 source",IF(COUNTIF(M98:R98,"S")>0,"Tier 4: Should only",IF(COUNTIF(M98:R98,"C")>0,"Tier 5: Could only",IF(I98>0,"Tier 6: stated, no priority","Aurigo-only")))))) -> Tier 3: Must in 1 source | N98: M | S98: Idaho ITD RFP Event 85 – ROWMS: §9 Relocation Requirements ['must' requirement (§9)] ×2 | V98: Not evidenced | W98: No matching item found in the provided Aurigo documents (SOW, demo script, deck, library list). | Z98: R18 | AA98: Relocation case, planning & notices | AB98: 202 | AC98: ROW-094
A99: ROW-096 | B99: Land Acquisition & Relocation | C99: Relocation Assistance | D99: Claims & notices | E99: Displacee contact and new-address tracking | F99: Document contact with displacees including new address/contact and replacement dwelling. | G99: Functional | H99: =IF(COUNTIF(M99:R99,"M")>0,"Must Have",IF(COUNTIF(M99:R99,"S")>0,"Should Have",IF(COUNTIF(M99:R99,"C")>0,"Could Have",IF(COUNTA(M99:R99)>0,"Stated – no priority","Aurigo-only (no RFP source)")))) -> Must Have | I99: =COUNTA(M99:R99) -> 1 | J99: =COUNTIF(M99:R99,"M") -> 1 | K99: =IF(I99=0,"Aurigo-only",IF(I99=1,"Single source",IF(I99=2,"Two sources",IF(I99<=4,"Common (3-4)","Broad (5+)")))) -> Single source | L99: =IF(J99>=3,"Tier 1: Must in 3+ sources",IF(J99=2,"Tier 2: Must in 2 sources",IF(J99=1,"Tier 3: Must in 1 source",IF(COUNTIF(M99:R99,"S")>0,"Tier 4: Should only",IF(COUNTIF(M99:R99,"C")>0,"Tier 5: Could only",IF(I99>0,"Tier 6: stated, no priority","Aurigo-only")))))) -> Tier 3: Must in 1 source | N99: M | S99: Idaho ITD RFP Event 85 – ROWMS: §9 Relocation Requirements ['must' requirement (§9)] | V99: Not evidenced | W99: No matching item found in the provided Aurigo documents (SOW, demo script, deck, library list). | Z99: R18 | AA99: Relocation case, planning & notices | AB99: 195 | AC99: ROW-085
A100: ROW-097 | B100: Land Acquisition & Relocation | C100: Relocation Assistance | D100: Payments | E100: Relocation payment approval workflow and request | F100: Rules-based review/approval workflow for relocation payments; initiate payment requests and record warrant numbers/dates and date paid (paper check or electronic); document payment types (taxable vs non-taxable; possible 1099 support). | G100: Functional | H100: =IF(COUNTIF(M100:R100,"M")>0,"Must Have",IF(COUNTIF(M100:R100,"S")>0,"Should Have",IF(COUNTIF(M100:R100,"C")>0,"Could Have",IF(COUNTA(M100:R100)>0,"Stated – no priority","Aurigo-only (no RFP source)")))) -> Must Have | I100: =COUNTA(M100:R100) -> 1 | J100: =COUNTIF(M100:R100,"M") -> 1 | K100: =IF(I100=0,"Aurigo-only",IF(I100=1,"Single source",IF(I100=2,"Two sources",IF(I100<=4,"Common (3-4)","Broad (5+)")))) -> Single source | L100: =IF(J100>=3,"Tier 1: Must in 3+ sources",IF(J100=2,"Tier 2: Must in 2 sources",IF(J100=1,"Tier 3: Must in 1 source",IF(COUNTIF(M100:R100,"S")>0,"Tier 4: Should only",IF(COUNTIF(M100:R100,"C")>0,"Tier 5: Could only",IF(I100>0,"Tier 6: stated, no priority","Aurigo-only")))))) -> Tier 3: Must in 1 source | N100: M | S100: Idaho ITD RFP Event 85 – ROWMS: §9 Relocation Requirements ['must' requirement (§9)] ×3 | T100: IRS 1099 (tax treatment of payments) | V100: Partial | W100: Demo: Relocation Payments section and workflow; rules-based approval not evidenced | Z100: R20 | AA100: Relocation payments, appeals & reports | AB100: 214 | AC100: ROW-087, ROW-108
A101: ROW-098 | B101: Land Acquisition & Relocation | C101: Relocation Assistance | D101: Relocation case | E101: Demolition and property-securing requests | F101: Store date of request and completion of demolition; submit requests to the District for maintenance, boarding up or changing locks on acquired structures. | G101: Functional | H101: =IF(COUNTIF(M101:R101,"M")>0,"Must Have",IF(COUNTIF(M101:R101,"S")>0,"Should Have",IF(COUNTIF(M101:R101,"C")>0,"Could Have",IF(COUNTA(M101:R101)>0,"Stated – no priority","Aurigo-only (no RFP source)")))) -> Must Have | I101: =COUNTA(M101:R101) -> 1 | J101: =COUNTIF(M101:R101,"M") -> 1 | K101: =IF(I101=0,"Aurigo-only",IF(I101=1,"Single source",IF(I101=2,"Two sources",IF(I101<=4,"Common (3-4)","Broad (5+)")))) -> Single source | L101: =IF(J101>=3,"Tier 1: Must in 3+ sources",IF(J101=2,"Tier 2: Must in 2 sources",IF(J101=1,"Tier 3: Must in 1 source",IF(COUNTIF(M101:R101,"S")>0,"Tier 4: Should only",IF(COUNTIF(M101:R101,"C")>0,"Tier 5: Could only",IF(I101>0,"Tier 6: stated, no priority","Aurigo-only")))))) -> Tier 3: Must in 1 source | N101: M | S101: Idaho ITD RFP Event 85 – ROWMS: §9 Property Management Requirements ['must' requirement (§9)] ×2; §9.14 Value Added Services [(E) evaluated – 'may have'] | V101: Covered (SOW) | W101: Original SOW: 'Demolition Request' (Property Management configurable process) | Z101: R18 | AA101: Relocation case, planning & notices | AB101: 203 | AC101: ROW-085
...

Sheet City-County ROW Use
A1: CITY / COUNTY LEVEL REQUIREMENTS – NOT PART OF THE CORE ROW MODULE
A2: These requirements come from city/county documents (Detroit, Calgary, Regina, Smart ROW matrix) about managing USE of public right-of-way: permits, inspections, work scheduling, fees, street/curb data. They are separate from ROW land acquisition and are kept for reference only. A few state-DOT items that overlap (e.g., inspections, conflict analysis) are included where they matter here.
A3: Feature ID | B3: Level | C3: Category | D3: Sub-category | E3: Feature | F3: Description (plain English) | G3: Requirement type | H3: Consolidated priority | I3: # sources | J3: # sources rating Must | K3: Breadth | L3: Consensus tier | M3: NH | N3: ID | O3: NM | P3: WA | Q3: ATX | R3: OSC | S3: DET | T3: CAL | U3: REG | V3: SRW | W3: Source references (document – location [source's own priority label]) | X3: Named systems / tools | Y3: Notes / open questions
A4: CTY-001 | B4: City / County | C4: Permit Intake & Application | D4: Application | E4: Online permit application and submission | F4: Applicants complete a digital application form, attach supporting documents, submit for approval, see status and cancel requests; staff handle intake and workflow-based processing across permit types. | G4: Functional | H4: =IF(COUNTIF(M4:V4,"M")>0,"Must Have",IF(COUNTIF(M4:V4,"S")>0,"Should Have",IF(COUNTIF(M4:V4,"C")>0,"Could Have",IF(COUNTA(M4:V4)>0,"Stated – no priority","Aurigo-only (no RFP source)")))) -> Must Have | I4: =COUNTA(M4:V4) -> 4 | J4: =COUNTIF(M4:V4,"M") -> 2 | K4: =IF(I4=0,"Aurigo-only",IF(I4=1,"Single source",IF(I4=2,"Two sources",IF(I4<=4,"Common (3-4)","Broad (5+)")))) -> Common (3-4) | L4: =IF(J4>=3,"Tier 1: Must in 3+ sources",IF(J4=2,"Tier 2: Must in 2 sources",IF(J4=1,"Tier 3: Must in 1 source",IF(COUNTIF(M4:V4,"S")>0,"Tier 4: Should only",IF(COUNTIF(M4:V4,"C")>0,"Tier 5: Could only",IF(I4>0,"Tier 6: stated, no priority","Aurigo-only")))))) -> Tier 2: Must in 2 sources | S4: E | T4: E | U4: M | V4: M | W4: City of Detroit RFP 185263: §2 Statement of Work [RFP – stated expectation (no priority given)] City of Calgary RFI 25-006: §2.4 Functional capabilities [RFI – expected capability (no priority given)] City of Regina RFI 25-00072: §4 Required features – General [RFI – 'Required software features'] ×4 Smart ROW Features Matrix (DM1343 App. D): Features List – row 17 [Must Have] | Y4: Domain note: this and the following permit features come from Regina, Calgary, Detroit and Smart ROW documents, which concern permits for using public right-of-way (street use, excavation, utility work) rather than land acquisition.
A5: CTY-002 | B5: City / County | C5: Permit Intake & Application | D5: Application | E5: Permit-type-specific forms and configurable form fields | F5: Each permit type has its own form and submission requirements, pre-populated where possible; form fields can be changed over time; mandatory fields must be complete before submission; permit generation configurable by administrators. | G5: Functional | H5: =IF(COUNTIF(M5:V5,"M")>0,"Must Have",IF(COUNTIF(M5:V5,"S")>0,"Should Have",IF(COUNTIF(M5:V5,"C")>0,"Could Have",IF(COUNTA(M5:V5)>0,"Stated – no priority","Aurigo-only (no RFP source)")))) -> Must Have | I5: =COUNTA(M5:V5) -> 2 | J5: =COUNTIF(M5:V5,"M") -> 1 | K5: =IF(I5=0,"Aurigo-only",IF(I5=1,"Single source",IF(I5=2,"Two sources",IF(I5<=4,"Common (3-4)","Broad (5+)")))) -> Two sources | L5: =IF(J5>=3,"Tier 1: Must in 3+ sources",IF(J5=2,"Tier 2: Must in 2 sources",IF(J5=1,"Tier 3: Must in 1 source",IF(COUNTIF(M5:V5,"S")>0,"Tier 4: Should only",IF(COUNTIF(M5:V5,"C")>0,"Tier 5: Could only",IF(I5>0,"Tier 6: stated, no priority","Aurigo-only")))))) -> Tier 3: Must in 1 source | T5: E | U5: M | W5: City of Calgary RFI 25-006: §2.4 Functional capabilities [RFI – expected capability (no priority given)] City of Regina RFI 25-00072: §4 Required features – External Applicants [RFI – 'Required software features'] ×2; §4 Required features – General [RFI – 'Required software features']
A6: CTY-003 | B6: City / County | C6: Permit Intake & Application | D6: Application | E6: Map-based work-area drawing and location selection | F6: Applicants draw/select the affected area on a map using points, lines or polygons; staff can edit the shape. | G6: Functional | H6: =IF(COUNTIF(M6:V6,"M")>0,"Must Have",IF(COUNTIF(M6:V6,"S")>0,"Should Have",IF(COUNTIF(M6:V6,"C")>0,"Could Have",IF(COUNTA(M6:V6)>0,"Stated – no priority","Aurigo-only (no RFP source)")))) -> Must Have | I6: =COUNTA(M6:V6) -> 2 | J6: =COUNTIF(M6:V6,"M") -> 1 | K6: =IF(I6=0,"Aurigo-only",IF(I6=1,"Single source",IF(I6=2,"Two sources",IF(I6<=4,"Common (3-4)","Broad (5+)")))) -> Two sources | L6: =IF(J6>=3,"Tier 1: Must in 3+ sources",IF(J6=2,"Tier 2: Must in 2 sources",IF(J6=1,"Tier 3: Must in 1 source",IF(COUNTIF(M6:V6,"S")>0,"Tier 4: Should only",IF(COUNTIF(M6:V6,"C")>0,"Tier 5: Could only",IF(I6>0,"Tier 6: stated, no priority","Aurigo-only")))))) -> Tier 3: Must in 1 source | T6: E | U6: M | W6: City of Calgary RFI 25-006: §2.4 Functional capabilities [RFI – expected capability (no priority given)] City of Regina RFI 25-00072: §4 Required features – General [RFI – 'Required software features']; §4 Required features – Permit Management [RFI – 'Required software features']; §4 Optional features – Permit Management [RFI – 'Optional software features']
A7: CTY-004 | B7: City / County | C7: Permit Intake & Application | D7: Accounts | E7: External self-service accounts and internal login | F7: Internal users sign in with their organisation login; external users self-register with an automated approval path when information is complete; group-based company access; corporate administrators who can see all company requests (optional). | G7: Functional | H7: =IF(COUNTIF(M7:V7,"M")>0,"Must Have",IF(COUNTIF(M7:V7,"S")>0,"Should Have",IF(COUNTIF(M7:V7,"C")>0,"Could Have",IF(COUNTA(M7:V7)>0,"Stated – no priority","Aurigo-only (no RFP source)")))) -> Must Have | I7: =COUNTA(M7:V7) -> 2 | J7: =COUNTIF(M7:V7,"M") -> 1 | K7: =IF(I7=0,"Aurigo-only",IF(I7=1,"Single source",IF(I7=2,"Two sources",IF(I7<=4,"Common (3-4)","Broad (5+)")))) -> Two sources | L7: =IF(J7>=3,"Tier 1: Must in 3+ sources",IF(J7=2,"Tier 2: Must in 2 sources",IF(J7=1,"Tier 3: Must in 1 source",IF(COUNTIF(M7:V7,"S")>0,"Tier 4: Should only",IF(COUNTIF(M7:V7,"C")>0,"Tier 5: Could only",IF(I7>0,"Tier 6: stated, no priority","Aurigo-only")))))) -> Tier 3: Must in 1 source | T7: E | U7: M | W7: City of Calgary RFI 25-006: §2.4 Functional capabilities [RFI – expected capability (no priority given)] City of Regina RFI 25-00072: §4 Required features – General [RFI – 'Required software features']; §4 Optional features – External Applicants [RFI – 'Optional software features'] ×2; §4 Optional features – Permit Management [RFI – 'Optional software features']; §4 Optional features – General [RFI – 'Optional software features'] | X7: Calgary: Azure-based myID
A8: CTY-005 | B8: City / County | C8: Permit Intake & Application | D8: Application | E8: Staff-entered requests and ad hoc paper-permit capture | F8: Staff can enter requests on behalf of utility companies, and store ad hoc requests that need a paper-based permit. | G8: Functional | H8: =IF(COUNTIF(M8:V8,"M")>0,"Must Have",IF(COUNTIF(M8:V8,"S")>0,"Should Have",IF(COUNTIF(M8:V8,"C")>0,"Could Have",IF(COUNTA(M8:V8)>0,"Stated – no priority","Aurigo-only (no RFP source)")))) -> Must Have | I8: =COUNTA(M8:V8) -> 1 | J8: =COUNTIF(M8:V8,"M") -> 1 | K8: =IF(I8=0,"Aurigo-only",IF(I8=1,"Single source",IF(I8=2,"Two sources",IF(I8<=4,"Common (3-4)","Broad (5+)")))) -> Single source | L8: =IF(J8>=3,"Tier 1: Must in 3+ sources",IF(J8=2,"Tier 2: Must in 2 sources",IF(J8=1,"Tier 3: Must in 1 source",IF(COUNTIF(M8:V8,"S")>0,"Tier 4: Should only",IF(COUNTIF(M8:V8,"C")>0,"Tier 5: Could only",IF(I8>0,"Tier 6: stated, no priority","Aurigo-only")))))) -> Tier 3: Must in 1 source | U8: M | W8: City of Regina RFI 25-00072: §4 Required features – External Applicants [RFI – 'Required software features']; §4 Required features – Permit Management [RFI – 'Required software features']
A9: CTY-006 | B9: City / County | C9: Permit Intake & Application | D9: Application | E9: Lead-time validation and blackout dates/areas | F9: Warn applicants when the request is inside the minimum lead time for the permit type; define dates and areas where work cannot be requested; set minimum lead time per permit type. | G9: Functional | H9: =IF(COUNTIF(M9:V9,"M")>0,"Must Have",IF(COUNTIF(M9:V9,"S")>0,"Should Have",IF(COUNTIF(M9:V9,"C")>0,"Could Have",IF(COUNTA(M9:V9)>0,"Stated – no priority","Aurigo-only (no RFP source)")))) -> Must Have | I9: =COUNTA(M9:V9) -> 1 | J9: =COUNTIF(M9:V9,"M") -> 1 | K9: =IF(I9=0,"Aurigo-only",IF(I9=1,"Single source",IF(I9=2,"Two sources",IF(I9<=4,"Common (3-4)","Broad (5+)")))) -> Single source | L9: =IF(J9>=3,"Tier 1: Must in 3+ sources",IF(J9=2,"Tier 2: Must in 2 sources",IF(J9=1,"Tier 3: Must in 1 source",IF(COUNTIF(M9:V9,"S")>0,"Tier 4: Should only",IF(COUNTIF(M9:V9,"C")>0,"Tier 5: Could only",IF(I9>0,"Tier 6: stated, no priority","Aurigo-only")))))) -> Tier 3: Must in 1 source | U9: M | W9: City of Regina RFI 25-00072: §4 Required features – General [RFI – 'Required software features']; §4 Optional features – Permit Management [RFI – 'Optional software features'] ×2
A10: CTY-007 | B10: City / County | C10: Permit Intake & Application | D10: Application | E10: Repeat-event copy and multi-phase work plans | F10: Copy a prior permit/work plan for repeating events; program multi-phase accommodation work under one permit. | G10: Functional | H10: =IF(COUNTIF(M10:V10,"M")>0,"Must Have",IF(COUNTIF(M10:V10,"S")>0,"Should Have",IF(COUNTIF(M10:V10,"C")>0,"Could Have",IF(COUNTA(M10:V10)>0,"Stated – no priority","Aurigo-only (no RFP source)")))) -> Could Have | I10: =COUNTA(M10:V10) -> 1 | J10: =COUNTIF(M10:V10,"M") -> 0 | K10: =IF(I10=0,"Aurigo-only",IF(I10=1,"Single source",IF(I10=2,"Two sources",IF(I10<=4,"Common (3-4)","Broad (5+)")))) -> Single source | L10: =IF(J10>=3,"Tier 1: Must in 3+ sources",IF(J10=2,"Tier 2: Must in 2 sources",IF(J10=1,"Tier 3: Must in 1 source",IF(COUNTIF(M10:V10,"S")>0,"Tier 4: Should only",IF(COUNTIF(M10:V10,"C")>0,"Tier 5: Could only",IF(I10>0,"Tier 6: stated, no priority","Aurigo-only")))))) -> Tier 5: Could only | U10: C | W10: City of Regina RFI 25-00072: §4 Optional features – General [RFI – 'Optional software features']; §4 Optional features – Permit Management [RFI – 'Optional software features'] ×2
A11: CTY-008 | B11: City / County | C11: Permit Intake & Application | D11: Application | E11: Over-dimensional move routing | F11: Requestor plots a travel path and vehicle height; check the route against GIS conflict points such as traffic signals. | G11: Functional | H11: =IF(COUNTIF(M11:V11,"M")>0,"Must Have",IF(COUNTIF(M11:V11,"S")>0,"Should Have",IF(COUNTIF(M11:V11,"C")>0,"Could Have",IF(COUNTA(M11:V11)>0,"Stated – no priority","Aurigo-only (no RFP source)")))) -> Could Have | I11: =COUNTA(M11:V11) -> 1 | J11: =COUNTIF(M11:V11,"M") -> 0 | K11: =IF(I11=0,"Aurigo-only",IF(I11=1,"Single source",IF(I11=2,"Two sources",IF(I11<=4,"Common (3-4)","Broad (5+)")))) -> Single source | L11: =IF(J11>=3,"Tier 1: Must in 3+ sources",IF(J11=2,"Tier 2: Must in 2 sources",IF(J11=1,"Tier 3: Must in 1 source",IF(COUNTIF(M11:V11,"S")>0,"Tier 4: Should only",IF(COUNTIF(M11:V11,"C")>0,"Tier 5: Could only",IF(I11>0,"Tier 6: stated, no priority","Aurigo-only")))))) -> Tier 5: Could only | U11: C | W11: City of Regina RFI 25-00072: §4 Optional features – General [RFI – 'Optional software features']; §4 Optional features – Permit Management [RFI – 'Optional software features']
A12: CTY-009 | B12: City / County | C12: Permit Intake & Application | D12: Application | E12: Visibility rules by applicant type (own vs. city vs. external requests) | F12: External parties see only their own submissions; internal users see their own and City requests in detail and only general information and primary contact for external requests; internal customers have the same options as external ones. | G12: Functional | H12: =IF(COUNTIF(M12:V12,"M")>0,"Must Have",IF(COUNTIF(M12:V12,"S")>0,"Should Have",IF(COUNTIF(M12:V12,"C")>0,"Could Have",IF(COUNTA(M12:V12)>0,"Stated – no priority","Aurigo-only (no RFP source)")))) -> Must Have | I12: =COUNTA(M12:V12) -> 1 | J12: =COUNTIF(M12:V12,"M") -> 1 | K12: =IF(I12=0,"Aurigo-only",IF(I12=1,"Single source",IF(I12=2,"Two sources",IF(I12<=4,"Common (3-4)","Broad (5+)")))) -> Single source | L12: =IF(J12>=3,"Tier 1: Must in 3+ sources",IF(J12=2,"Tier 2: Must in 2 sources",IF(J12=1,"Tier 3: Must in 1 source",IF(COUNTIF(M12:V12,"S")>0,"Tier 4: Should only",IF(COUNTIF(M12:V12,"C")>0,"Tier 5: Could only",IF(I12>0,"Tier 6: stated, no priority","Aurigo-only")))))) -> Tier 3: Must in 1 source | U12: M | W12: City of Regina RFI 25-00072: §4 Required features – External Applicants [RFI – 'Required software features']; §4 Required features – Internal Applicants [RFI – 'Required software features'] ×2
A13: CTY-010 | B13: City / County | C13: Permit Intake & Application | D13: Application | E13: Traffic accommodation plan selection and self-serve accommodation set-up | F13: Applicants indicate whether a traffic accommodation plan is needed; internal parties can self-serve simple set-ups (e.g., their own no-parking signs) but still submit a request so City-wide work is tracked, with an acknowledgement to check the conflict tool; internal request type defaults to Traffic Accommodation where possible. | G13: Functional | H13: =IF(COUNTIF(M13:V13,"M")>0,"Must Have",IF(COUNTIF(M13:V13,"S")>0,"Should Have",IF(COUNTIF(M13:V13,"C")>0,"Could Have",IF(COUNTA(M13:V13)>0,"Stated – no priority","Aurigo-only (no RFP source)")))) -> Must Have | I13: =COUNTA(M13:V13) -> 1 | J13: =COUNTIF(M13:V13,"M") -> 1 | K13: =IF(I13=0,"Aurigo-only",IF(I13=1,"Single source",IF(I13=2,"Two sources",IF(I13<=4,"Common (3-4)","Broad (5+)")))) -> Single source | L13: =IF(J13>=3,"Tier 1: Must in 3+ sources",IF(J13=2,"Tier 2: Must in 2 sources",IF(J13=1,"Tier 3: Must in 1 source",IF(COUNTIF(M13:V13,"S")>0,"Tier 4: Should only",IF(COUNTIF(M13:V13,"C")>0,"Tier 5: Could only",IF(I13>0,"Tier 6: stated, no priority","Aurigo-only")))))) -> Tier 3: Must in 1 source | U13: M | W13: City of Regina RFI 25-00072: §4 Required features – External Applicants [RFI – 'Required software features']; §4 Required features – Internal Applicants [RFI – 'Required software features']; §4 Optional features – Internal Applicants [RFI – 'Optional software features'] | X13: C3DR (Regina conflict-viewing tool)
A14: CTY-011 | B14: City / County | C14: Permit Intake & Application | D14: Application | E14: Additional permit contacts with special instructions | F14: Identify other contacts for a permit and specify special instructions for them. | G14: Functional | H14: =IF(COUNTIF(M14:V14,"M")>0,"Must Have",IF(COUNTIF(M14:V14,"S")>0,"Should Have",IF(COUNTIF(M14:V14,"C")>0,"Could Have",IF(COUNTA(M14:V14)>0,"Stated – no priority","Aurigo-only (no RFP source)")))) -> Must Have | I14: =COUNTA(M14:V14) -> 1 | J14: =COUNTIF(M14:V14,"M") -> 1 | K14: =IF(I14=0,"Aurigo-only",IF(I14=1,"Single source",IF(I14=2,"Two sources",IF(I14<=4,"Common (3-4)","Broad (5+)")))) -> Single source | L14: =IF(J14>=3,"Tier 1: Must in 3+ sources",IF(J14=2,"Tier 2: Must in 2 sources",IF(J14=1,"Tier 3: Must in 1 source",IF(COUNTIF(M14:V14,"S")>0,"Tier 4: Should only",IF(COUNTIF(M14:V14,"C")>0,"Tier 5: Could only",IF(I14>0,"Tier 6: stated, no priority","Aurigo-only")))))) -> Tier 3: Must in 1 source | U14: M | W14: City of Regina RFI 25-00072: §4 Required features – General [RFI – 'Required software features']
A15: CTY-012 | B15: City / County | C15: Permit Review & Approval | D15: Review | E15: Permit review, requirements requests and approval workflow | F15: City review can ask for requirements (insurance, plans) that must be supplied before approval; operator workflow presents relevant information per user type; group/role-based approvals; Director override logged in history; pre-approval for some request types. | G15: Functional | H15: =IF(COUNTIF(M15:V15,"M")>0,"Must Have",IF(COUNTIF(M15:V15,"S")>0,"Should Have",IF(COUNTIF(M15:V15,"C")>0,"Could Have",IF(COUNTA(M15:V15)>0,"Stated – no priority","Aurigo-only (no RFP source)")))) -> Must Have | I15: =COUNTA(M15:V15) -> 3 | J15: =COUNTIF(M15:V15,"M") -> 2 | K15: =IF(I15=0,"Aurigo-only",IF(I15=1,"Single source",IF(I15=2,"Two sources",IF(I15<=4,"Common (3-4)","Broad (5+)")))) -> Common (3-4) | L15: =IF(J15>=3,"Tier 1: Must in 3+ sources",IF(J15=2,"Tier 2: Must in 2 sources",IF(J15=1,"Tier 3: Must in 1 source",IF(COUNTIF(M15:V15,"S")>0,"Tier 4: Should only",IF(COUNTIF(M15:V15,"C")>0,"Tier 5: Could only",IF(I15>0,"Tier 6: stated, no priority","Aurigo-only")))))) -> Tier 2: Must in 2 sources | O15: M | T15: E | U15: M | W15: NMDOT RFP 06-0100: App. A §3.2.2 [SOW scope item / RFP purpose] City of Calgary RFI 25-006: §2.4 Functional capabilities [RFI – expected capability (no priority given)] City of Regina RFI 25-00072: §4 Required features – External Applicants [RFI – 'Required software features']; §4 Required features – Permit Management [RFI – 'Required software features'] ×3
A16: CTY-013 | B16: City / County | C16: Permit Review & Approval | D16: Review | E16: Permit and area conflict detection | F16: Flag permits that conflict with one another or with flagged areas/dates for review, with override for approvals; Smart ROW calls for automated conflict detection among ingested features and regulations; NM asks for spatial conflict analysis. | G16: Functional | H16: =IF(COUNTIF(M16:V16,"M")>0,"Must Have",IF(COUNTIF(M16:V16,"S")>0,"Should Have",IF(COUNTIF(M16:V16,"C")>0,"Could Have",IF(COUNTA(M16:V16)>0,"Stated – no priority","Aurigo-only (no RFP source)")))) -> Must Have | I16: =COUNTA(M16:V16) -> 4 | J16: =COUNTIF(M16:V16,"M") -> 3 | K16: =IF(I16=0,"Aurigo-only",IF(I16=1,"Single source",IF(I16=2,"Two sources",IF(I16<=4,"Common (3-4)","Broad (5+)")))) -> Common (3-4) | L16: =IF(J16>=3,"Tier 1: Must in 3+ sources",IF(J16=2,"Tier 2: Must in 2 sources",IF(J16=1,"Tier 3: Must in 1 source",IF(COUNTIF(M16:V16,"S")>0,"Tier 4: Should only",IF(COUNTIF(M16:V16,"C")>0,"Tier 5: Could only",IF(I16>0,"Tier 6: stated, no priority","Aurigo-only")))))) -> Tier 1: Must in 3+ sources | O16: M | S16: E | U16: M | V16: M | W16: NMDOT RFP 06-0100: App. A §3.2.4 [SOW scope item / RFP purpose] City of Detroit RFP 185263: §2 Statement of Work [RFP – stated expectation (no priority given)] City of Regina RFI 25-00072: §4 Required features – Permit Management [RFI – 'Required software features'] Smart ROW Features Matrix (DM1343 App. D): Features List – row 11 [Must Have]
A17: CTY-014 | B17: City / County | C17: Permit Review & Approval | D17: Review | E17: Request for comments (RFC) to internal stakeholders | F17: Send a request for comments with reminders to specific parties and store replies centrally without forcing a formal approval bottleneck. | G17: Functional | H17: =IF(COUNTIF(M17:V17,"M")>0,"Must Have",IF(COUNTIF(M17:V17,"S")>0,"Should Have",IF(COUNTIF(M17:V17,"C")>0,"Could Have",IF(COUNTA(M17:V17)>0,"Stated – no priority","Aurigo-only (no RFP source)")))) -> Could Have | I17: =COUNTA(M17:V17) -> 1 | J17: =COUNTIF(M17:V17,"M") -> 0 | K17: =IF(I17=0,"Aurigo-only",IF(I17=1,"Single source",IF(I17=2,"Two sources",IF(I17<=4,"Common (3-4)","Broad (5+)")))) -> Single source | L17: =IF(J17>=3,"Tier 1: Must in 3+ sources",IF(J17=2,"Tier 2: Must in 2 sources",IF(J17=1,"Tier 3: Must in 1 source",IF(COUNTIF(M17:V17,"S")>0,"Tier 4: Should only",IF(COUNTIF(M17:V17,"C")>0,"Tier 5: Could only",IF(I17>0,"Tier 6: stated, no priority","Aurigo-only")))))) -> Tier 5: Could only | U17: C | W17: City of Regina RFI 25-00072: §4 Optional features – Permit Management [RFI – 'Optional software features']
A18: CTY-015 | B18: City / County | C18: Permit Review & Approval | D18: Review | E18: Change tracking and re-approval on updates | F18: Show changes to dates/contacts, keep history of initial request details, resubmit approved requests for approval after changes, and trigger fresh review when scheduling changes. | G18: Functional | H18: =IF(COUNTIF(M18:V18,"M")>0,"Must Have",IF(COUNTIF(M18:V18,"S")>0,"Should Have",IF(COUNTIF(M18:V18,"C")>0,"Could Have",IF(COUNTA(M18:V18)>0,"Stated – no priority","Aurigo-only (no RFP source)")))) -> Must Have | I18: =COUNTA(M18:V18) -> 1 | J18: =COUNTIF(M18:V18,"M") -> 1 | K18: =IF(I18=0,"Aurigo-only",IF(I18=1,"Single source",IF(I18=2,"Two sources",IF(I18<=4,"Common (3-4)","Broad (5+)")))) -> Single source | L18: =IF(J18>=3,"Tier 1: Must in 3+ sources",IF(J18=2,"Tier 2: Must in 2 sources",IF(J18=1,"Tier 3: Must in 1 source",IF(COUNTIF(M18:V18,"S")>0,"Tier 4: Should only",IF(COUNTIF(M18:V18,"C")>0,"Tier 5: Could only",IF(I18>0,"Tier 6: stated, no priority","Aurigo-only")))))) -> Tier 3: Must in 1 source | U18: M | W18: City of Regina RFI 25-00072: §4 Required features – Permit Management [RFI – 'Required software features'] ×2
A19: CTY-016 | B19: City / County | C19: Permit Review & Approval | D19: Review | E19: Stale-request auto-cancellation | F19: Automatically cancel and notify when a request awaiting customer information has been stale for X days. | G19: Functional | H19: =IF(COUNTIF(M19:V19,"M")>0,"Must Have",IF(COUNTIF(M19:V19,"S")>0,"Should Have",IF(COUNTIF(M19:V19,"C")>0,"Could Have",IF(COUNTA(M19:V19)>0,"Stated – no priority","Aurigo-only (no RFP source)")))) -> Could Have | I19: =COUNTA(M19:V19) -> 1 | J19: =COUNTIF(M19:V19,"M") -> 0 | K19: =IF(I19=0,"Aurigo-only",IF(I19=1,"Single source",IF(I19=2,"Two sources",IF(I19<=4,"Common (3-4)","Broad (5+)")))) -> Single source | L19: =IF(J19>=3,"Tier 1: Must in 3+ sources",IF(J19=2,"Tier 2: Must in 2 sources",IF(J19=1,"Tier 3: Must in 1 source",IF(COUNTIF(M19:V19,"S")>0,"Tier 4: Should only",IF(COUNTIF(M19:V19,"C")>0,"Tier 5: Could only",IF(I19>0,"Tier 6: stated, no priority","Aurigo-only")))))) -> Tier 5: Could only | U19: C | W19: City of Regina RFI 25-00072: §4 Optional features – Data and Governance [RFI – 'Optional software features']
A20: CTY-017 | B20: City / County | C20: Permit Review & Approval | D20: Review | E20: Segment-based spatial mapping of ROW impacts and activity coordination | F20: Map ROW impacts by street segment and coordinate utility, capital-project and special-event activity in the right-of-way. | G20: Functional | H20: =IF(COUNTIF(M20:V20,"M")>0,"Must Have",IF(COUNTIF(M20:V20,"S")>0,"Should Have",IF(COUNTIF(M20:V20,"C")>0,"Could Have",IF(COUNTA(M20:V20)>0,"Stated – no priority","Aurigo-only (no RFP source)")))) -> Stated – no priority | I20: =COUNTA(M20:V20) -> 1 | J20: =COUNTIF(M20:V20,"M") -> 0 | K20: =IF(I20=0,"Aurigo-only",IF(I20=1,"Single source",IF(I20=2,"Two sources",IF(I20<=4,"Common (3-4)","Broad (5+)")))) -> Single source | L20: =IF(J20>=3,"Tier 1: Must in 3+ sources",IF(J20=2,"Tier 2: Must in 2 sources",IF(J20=1,"Tier 3: Must in 1 source",IF(COUNTIF(M20:V20,"S")>0,"Tier 4: Should only",IF(COUNTIF(M20:V20,"C")>0,"Tier 5: Could only",IF(I20>0,"Tier 6: stated, no priority","Aurigo-only")))))) -> Tier 6: stated, no priority | S20: E | W20: City of Detroit RFP 185263: §2 Statement of Work [RFP – stated expectation (no priority given)] ×2 | Y20: Detroit's Attachment G (system specs) is referenced but was not in the file, so Detroit contributes only these high-level objectives and its data/API expectations.
A21: CTY-018 | B21: City / County | C21: Permit Review & Approval | D21: Review | E21: Modular architecture and future-proofing (incl. AI) | F21: Modular design so features/permit types can be added without disrupting others; describe roadmap and how AI may optimize workflow; automation features and error detection/correction for data from external sources. | G21: Non-functional | H21: =IF(COUNTIF(M21:V21,"M")>0,"Must Have",IF(COUNTIF(M21:V21,"S")>0,"Should Have",IF(COUNTIF(M21:V21,"C")>0,"Could Have",IF(COUNTA(M21:V21)>0,"Stated – no priority","Aurigo-only (no RFP source)")))) -> Must Have | I21: =COUNTA(M21:V21) -> 2 | J21: =COUNTIF(M21:V21,"M") -> 1 | K21: =IF(I21=0,"Aurigo-only",IF(I21=1,"Single source",IF(I21=2,"Two sources",IF(I21<=4,"Common (3-4)","Broad (5+)")))) -> Two sources | L21: =IF(J21>=3,"Tier 1: Must in 3+ sources",IF(J21=2,"Tier 2: Must in 2 sources",IF(J21=1,"Tier 3: Must in 1 source",IF(COUNTIF(M21:V21,"S")>0,"Tier 4: Should only",IF(COUNTIF(M21:V21,"C")>0,"Tier 5: Could only",IF(I21>0,"Tier 6: stated, no priority","Aurigo-only")))))) -> Tier 3: Must in 1 source | T21: E | U21: M | W21: City of Calgary RFI 25-006: §2.4 Functional capabilities [RFI – expected capability (no priority given)] ×5 City of Regina RFI 25-00072: §4 Required features – Permit Management [RFI – 'Required software features']
A22: CTY-019 | B22: City / County | C22: Permit Review & Approval | D22: Search | E22: Permit search and location-based lookup | F22: Flexible filtering across permits, inspections, customers, permit types and dates; administrators search by road name, job number, area, start/end dates, and select a location to find all current or future permits there. | G22: Functional | H22: =IF(COUNTIF(M22:V22,"M")>0,"Must Have",IF(COUNTIF(M22:V22,"S")>0,"Should Have",IF(COUNTIF(M22:V22,"C")>0,"Could Have",IF(COUNTA(M22:V22)>0,"Stated – no priority","Aurigo-only (no RFP source)")))) -> Must Have | I22: =COUNTA(M22:V22) -> 1 | J22: =COUNTIF(M22:V22,"M") -> 1 | K22: =IF(I22=0,"Aurigo-only",IF(I22=1,"Single source",IF(I22=2,"Two sources",IF(I22<=4,"Common (3-4)","Broad (5+)")))) -> Single source | L22: =IF(J22>=3,"Tier 1: Must in 3+ sources",IF(J22=2,"Tier 2: Must in 2 sources",IF(J22=1,"Tier 3: Must in 1 source",IF(COUNTIF(M22:V22,"S")>0,"Tier 4: Should only",IF(COUNTIF(M22:V22,"C")>0,"Tier 5: Could only",IF(I22>0,"Tier 6: stated, no priority","Aurigo-only")))))) -> Tier 3: Must in 1 source | U22: M | W22: City of Regina RFI 25-00072: §4 Required features – Permit Management [RFI – 'Required software features'] ×2
A23: CTY-020 | B23: City / County | C23: Permit Issuance & Documents | D23: Issuance | E23: Auto-generated permit document with terms and conditions | F23: Approved requests auto-generate an editable permit document, application details, terms and conditions (by permit type, updateable) and financial invoice, pre-filled with applicant and approver details. | G23: Functional | H23: =IF(COUNTIF(M23:V23,"M")>0,"Must Have",IF(COUNTIF(M23:V23,"S")>0,"Should Have",IF(COUNTIF(M23:V23,"C")>0,"Could Have",IF(COUNTA(M23:V23)>0,"Stated – no priority","Aurigo-only (no RFP source)")))) -> Must Have | I23: =COUNTA(M23:V23) -> 1 | J23: =COUNTIF(M23:V23,"M") -> 1 | K23: =IF(I23=0,"Aurigo-only",IF(I23=1,"Single source",IF(I23=2,"Two sources",IF(I23<=4,"Common (3-4)","Broad (5+)")))) -> Single source | L23: =IF(J23>=3,"Tier 1: Must in 3+ sources",IF(J23=2,"Tier 2: Must in 2 sources",IF(J23=1,"Tier 3: Must in 1 source",IF(COUNTIF(M23:V23,"S")>0,"Tier 4: Should only",IF(COUNTIF(M23:V23,"C")>0,"Tier 5: Could only",IF(I23>0,"Tier 6: stated, no priority","Aurigo-only")))))) -> Tier 3: Must in 1 source | U23: M | W23: City of Regina RFI 25-00072: §4 Required features – Permit Management [RFI – 'Required software features'] ×3
A24: CTY-021 | B24: City / County | C24: Permit Issuance & Documents | D24: Issuance | E24: Applicant acceptance of conditions before permit release | F24: Applicant must agree to each condition and see the cost before viewing the permit; permit number is withheld until accepted; approved permits are sent digitally. | G24: Functional | H24: =IF(COUNTIF(M24:V24,"M")>0,"Must Have",IF(COUNTIF(M24:V24,"S")>0,"Should Have",IF(COUNTIF(M24:V24,"C")>0,"Could Have",IF(COUNTA(M24:V24)>0,"Stated – no priority","Aurigo-only (no RFP source)")))) -> Must Have | I24: =COUNTA(M24:V24) -> 1 | J24: =COUNTIF(M24:V24,"M") -> 1 | K24: =IF(I24=0,"Aurigo-only",IF(I24=1,"Single source",IF(I24=2,"Two sources",IF(I24<=4,"Common (3-4)","Broad (5+)")))) -> Single source | L24: =IF(J24>=3,"Tier 1: Must in 3+ sources",IF(J24=2,"Tier 2: Must in 2 sources",IF(J24=1,"Tier 3: Must in 1 source",IF(COUNTIF(M24:V24,"S")>0,"Tier 4: Should only",IF(COUNTIF(M24:V24,"C")>0,"Tier 5: Could only",IF(I24>0,"Tier 6: stated, no priority","Aurigo-only")))))) -> Tier 3: Must in 1 source | U24: M | W24: City of Regina RFI 25-00072: §4 Required features – General [RFI – 'Required software features'] ×3
A25: CTY-022 | B25: City / County | C25: Permit Issuance & Documents | D25: Issuance | E25: Permit status, change history and unique permit ID | F25: Status shown on the permit record with automatic tracking of what changed, when and by whom; each permit/job gets an autogenerated ID to link related information; who created/updated/scheduled/completed is traceable. | G25: Functional | H25: =IF(COUNTIF(M25:V25,"M")>0,"Must Have",IF(COUNTIF(M25:V25,"S")>0,"Should Have",IF(COUNTIF(M25:V25,"C")>0,"Could Have",IF(COUNTA(M25:V25)>0,"Stated – no priority","Aurigo-only (no RFP source)")))) -> Must Have | I25: =COUNTA(M25:V25) -> 2 | J25: =COUNTIF(M25:V25,"M") -> 1 | K25: =IF(I25=0,"Aurigo-only",IF(I25=1,"Single source",IF(I25=2,"Two sources",IF(I25<=4,"Common (3-4)","Broad (5+)")))) -> Two sources | L25: =IF(J25>=3,"Tier 1: Must in 3+ sources",IF(J25=2,"Tier 2: Must in 2 sources",IF(J25=1,"Tier 3: Must in 1 source",IF(COUNTIF(M25:V25,"S")>0,"Tier 4: Should only",IF(COUNTIF(M25:V25,"C")>0,"Tier 5: Could only",IF(I25>0,"Tier 6: stated, no priority","Aurigo-only")))))) -> Tier 3: Must in 1 source | T25: E | U25: M | W25: City of Calgary RFI 25-006: §2.4 Functional capabilities [RFI – expected capability (no priority given)] ×2 City of Regina RFI 25-00072: §4 Required features – Permit Management [RFI – 'Required software features'] ×3; §4 Required features – Data and Governance [RFI – 'Required software features']
A26: CTY-023 | B26: City / County | C26: Permit Issuance & Documents | D26: Issuance | E26: Permit-expiry reminders and post-permit survey | F26: Auto-email customers when a long-running permit is nearing its end (customizable template, selectable permit types); auto-send a feedback survey at permit conclusion. | G26: Functional | H26: =IF(COUNTIF(M26:V26,"M")>0,"Must Have",IF(COUNTIF(M26:V26,"S")>0,"Should Have",IF(COUNTIF(M26:V26,"C")>0,"Could Have",IF(COUNTA(M26:V26)>0,"Stated – no priority","Aurigo-only (no RFP source)")))) -> Could Have | I26: =COUNTA(M26:V26) -> 1 | J26: =COUNTIF(M26:V26,"M") -> 0 | K26: =IF(I26=0,"Aurigo-only",IF(I26=1,"Single source",IF(I26=2,"Two sources",IF(I26<=4,"Common (3-4)","Broad (5+)")))) -> Single source | L26: =IF(J26>=3,"Tier 1: Must in 3+ sources",IF(J26=2,"Tier 2: Must in 2 sources",IF(J26=1,"Tier 3: Must in 1 source",IF(COUNTIF(M26:V26,"S")>0,"Tier 4: Should only",IF(COUNTIF(M26:V26,"C")>0,"Tier 5: Could only",IF(I26>0,"Tier 6: stated, no priority","Aurigo-only")))))) -> Tier 5: Could only | U26: C | W26: City of Regina RFI 25-00072: §4 Optional features – Permit Management [RFI – 'Optional software features'] ×2
A27: CTY-024 | B27: City / County | C27: Permit Issuance & Documents | D27: Issuance | E27: Consistent permit process across permit sources | F27: One business process for all ROW permits and their files (capital work, internal maintenance, external applications, three-way agreements); Calgary lists 37 existing permit types across three tools to be consolidated. | G27: Functional | H27: =IF(COUNTIF(M27:V27,"M")>0,"Must Have",IF(COUNTIF(M27:V27,"S")>0,"Should Have",IF(COUNTIF(M27:V27,"C")>0,"Could Have",IF(COUNTA(M27:V27)>0,"Stated – no priority","Aurigo-only (no RFP source)")))) -> Must Have | I27: =COUNTA(M27:V27) -> 2 | J27: =COUNTIF(M27:V27,"M") -> 1 | K27: =IF(I27=0,"Aurigo-only",IF(I27=1,"Single source",IF(I27=2,"Two sources",IF(I27<=4,"Common (3-4)","Broad (5+)")))) -> Two sources | L27: =IF(J27>=3,"Tier 1: Must in 3+ sources",IF(J27=2,"Tier 2: Must in 2 sources",IF(J27=1,"Tier 3: Must in 1 source",IF(COUNTIF(M27:V27,"S")>0,"Tier 4: Should only",IF(COUNTIF(M27:V27,"C")>0,"Tier 5: Could only",IF(I27>0,"Tier 6: stated, no priority","Aurigo-only")))))) -> Tier 3: Must in 1 source | T27: E | U27: M | W27: City of Calgary RFI 25-006: §2.4 Functional capabilities [RFI – expected capability (no priority given)] ×2 City of Regina RFI 25-00072: §4 Required features – Permit Management [RFI – 'Required software features'] ×2 | Y27: Calgary's unified-interface statement is in section 2.2; the 37-permit list is in Appendix B.
A28: CTY-025 | B28: City / County | C28: Inspections & Compliance | D28: Inspections | E28: Permit inspection scheduling, results and photos | F28: Schedule and conduct inspections of work zones/traffic accommodations; record date, time, inspector, outcome, photos and files; NM asks for field inspectors to update records on mobile devices. | G28: Functional | H28: =IF(COUNTIF(M28:V28,"M")>0,"Must Have",IF(COUNTIF(M28:V28,"S")>0,"Should Have",IF(COUNTIF(M28:V28,"C")>0,"Could Have",IF(COUNTA(M28:V28)>0,"Stated – no priority","Aurigo-only (no RFP source)")))) -> Must Have | I28: =COUNTA(M28:V28) -> 4 | J28: =COUNTIF(M28:V28,"M") -> 2 | K28: =IF(I28=0,"Aurigo-only",IF(I28=1,"Single source",IF(I28=2,"Two sources",IF(I28<=4,"Common (3-4)","Broad (5+)")))) -> Common (3-4) | L28: =IF(J28>=3,"Tier 1: Must in 3+ sources",IF(J28=2,"Tier 2: Must in 2 sources",IF(J28=1,"Tier 3: Must in 1 source",IF(COUNTIF(M28:V28,"S")>0,"Tier 4: Should only",IF(COUNTIF(M28:V28,"C")>0,"Tier 5: Could only",IF(I28>0,"Tier 6: stated, no priority","Aurigo-only")))))) -> Tier 2: Must in 2 sources | O28: M | S28: E | T28: E | U28: M | W28: NMDOT RFP 06-0100: App. A §3.2.3 [SOW scope item / RFP purpose] City of Detroit RFP 185263: §2 Statement of Work [RFP – stated expectation (no priority given)] City of Calgary RFI 25-006: §2.4 Functional capabilities [RFI – expected capability (no priority given)] City of Regina RFI 25-00072: §4 Required features – Permit Management [RFI – 'Required software features']
A29: CTY-026 | B29: City / County | C29: Inspections & Compliance | D29: Inspections | E29: Inspection deficiency tracking, notification and escalation | F29: Create a deficiency record from a failed inspection (pre-filled), notify the applicant, log communications, set a fix deadline with automatic re-check, escalate overdue items; NM asks for automated notifications for upcoming, missed or failed inspections. | G29: Functional | H29: =IF(COUNTIF(M29:V29,"M")>0,"Must Have",IF(COUNTIF(M29:V29,"S")>0,"Should Have",IF(COUNTIF(M29:V29,"C")>0,"Could Have",IF(COUNTA(M29:V29)>0,"Stated – no priority","Aurigo-only (no RFP source)")))) -> Must Have | I29: =COUNTA(M29:V29) -> 2 | J29: =COUNTIF(M29:V29,"M") -> 2 | K29: =IF(I29=0,"Aurigo-only",IF(I29=1,"Single source",IF(I29=2,"Two sources",IF(I29<=4,"Common (3-4)","Broad (5+)")))) -> Two sources | L29: =IF(J29>=3,"Tier 1: Must in 3+ sources",IF(J29=2,"Tier 2: Must in 2 sources",IF(J29=1,"Tier 3: Must in 1 source",IF(COUNTIF(M29:V29,"S")>0,"Tier 4: Should only",IF(COUNTIF(M29:V29,"C")>0,"Tier 5: Could only",IF(I29>0,"Tier 6: stated, no priority","Aurigo-only")))))) -> Tier 2: Must in 2 sources | O29: M | U29: M | W29: NMDOT RFP 06-0100: App. A §3.2.3 [SOW scope item / RFP purpose] City of Regina RFI 25-00072: §4 Required features – Permit Management [RFI – 'Required software features'] ×5
A30: CTY-027 | B30: City / County | C30: Inspections & Compliance | D30: Compliance | E30: Compliance monitoring, violations and enforcement | F30: Monitor and enforce regulatory compliance, record violations and drive enforcement through workflows; escalation mechanisms. | G30: Functional | H30: =IF(COUNTIF(M30:V30,"M")>0,"Must Have",IF(COUNTIF(M30:V30,"S")>0,"Should Have",IF(COUNTIF(M30:V30,"C")>0,"Could Have",IF(COUNTA(M30:V30)>0,"Stated – no priority","Aurigo-only (no RFP source)")))) -> Must Have | I30: =COUNTA(M30:V30) -> 2 | J30: =COUNTIF(M30:V30,"M") -> 1 | K30: =IF(I30=0,"Aurigo-only",IF(I30=1,"Single source",IF(I30=2,"Two sources",IF(I30<=4,"Common (3-4)","Broad (5+)")))) -> Two sources | L30: =IF(J30>=3,"Tier 1: Must in 3+ sources",IF(J30=2,"Tier 2: Must in 2 sources",IF(J30=1,"Tier 3: Must in 1 source",IF(COUNTIF(M30:V30,"S")>0,"Tier 4: Should only",IF(COUNTIF(M30:V30,"C")>0,"Tier 5: Could only",IF(I30>0,"Tier 6: stated, no priority","Aurigo-only")))))) -> Tier 3: Must in 1 source | O30: M | T30: E | W30: NMDOT RFP 06-0100: App. A §3.2.3 [SOW scope item / RFP purpose] City of Calgary RFI 25-006: §2.4 Functional capabilities [RFI – expected capability (no priority given)] ×2
A31: CTY-028 | B31: City / County | C31: Inspections & Compliance | D31: Compliance | E31: Insurance and indemnification verification | F31: Workflow to authenticate with the City's indemnification/insurance solution, notify and validate insurance. | G31: Integration | H31: =IF(COUNTIF(M31:V31,"M")>0,"Must Have",IF(COUNTIF(M31:V31,"S")>0,"Should Have",IF(COUNTIF(M31:V31,"C")>0,"Could Have",IF(COUNTA(M31:V31)>0,"Stated – no priority","Aurigo-only (no RFP source)")))) -> Stated – no priority | I31: =COUNTA(M31:V31) -> 1 | J31: =COUNTIF(M31:V31,"M") -> 0 | K31: =IF(I31=0,"Aurigo-only",IF(I31=1,"Single source",IF(I31=2,"Two sources",IF(I31<=4,"Common (3-4)","Broad (5+)")))) -> Single source | L31: =IF(J31>=3,"Tier 1: Must in 3+ sources",IF(J31=2,"Tier 2: Must in 2 sources",IF(J31=1,"Tier 3: Must in 1 source",IF(COUNTIF(M31:V31,"S")>0,"Tier 4: Should only",IF(COUNTIF(M31:V31,"C")>0,"Tier 5: Could only",IF(I31>0,"Tier 6: stated, no priority","Aurigo-only")))))) -> Tier 6: stated, no priority | T31: E | W31: City of Calgary RFI 25-006: §2.4 Functional capabilities [RFI – expected capability (no priority given)]
A32: CTY-029 | B32: City / County | C32: Fees, Payments & Billing | D32: Billing | E32: Permit fees, invoicing, payments and billing integration | F32: Show cost, produce invoice, track what is paid or due, ideally receive payment before issuing the permit, warn staff of unpaid permits after X days, accept card payments (optional), block new requests until outstanding amounts are paid (optional), and interface with the corporate eCommerce/financial platform. | G32: Functional | H32: =IF(COUNTIF(M32:V32,"M")>0,"Must Have",IF(COUNTIF(M32:V32,"S")>0,"Should Have",IF(COUNTIF(M32:V32,"C")>0,"Could Have",IF(COUNTA(M32:V32)>0,"Stated – no priority","Aurigo-only (no RFP source)")))) -> Must Have | I32: =COUNTA(M32:V32) -> 2 | J32: =COUNTIF(M32:V32,"M") -> 1 | K32: =IF(I32=0,"Aurigo-only",IF(I32=1,"Single source",IF(I32=2,"Two sources",IF(I32<=4,"Common (3-4)","Broad (5+)")))) -> Two sources | L32: =IF(J32>=3,"Tier 1: Must in 3+ sources",IF(J32=2,"Tier 2: Must in 2 sources",IF(J32=1,"Tier 3: Must in 1 source",IF(COUNTIF(M32:V32,"S")>0,"Tier 4: Should only",IF(COUNTIF(M32:V32,"C")>0,"Tier 5: Could only",IF(I32>0,"Tier 6: stated, no priority","Aurigo-only")))))) -> Tier 3: Must in 1 source | T32: E | U32: M | W32: City of Calgary RFI 25-006: §2.4 Functional capabilities [RFI – expected capability (no priority given)] ×2 City of Regina RFI 25-00072: §4 Required features – Financials [RFI – 'Required software features'] ×3; §4 Optional features – Financials [RFI – 'Optional software features'] ×2; §4 Required features – General [RFI – 'Required software features'] ×2 | X32: Calgary: corporate eCommerce platform
A33: CTY-030 | B33: City / County | C33: Fees, Payments & Billing | D33: Billing | E33: Fee disclaimers, cancellation fees and staff-performed work billing | F33: Disclaimers about cancellation fees and additional accommodation-setup costs, with estimated cost where possible; summarize costs of city-performed work and create an invoice when direct billing is not possible. | G33: Functional | H33: =IF(COUNTIF(M33:V33,"M")>0,"Must Have",IF(COUNTIF(M33:V33,"S")>0,"Should Have",IF(COUNTIF(M33:V33,"C")>0,"Could Have",IF(COUNTA(M33:V33)>0,"Stated – no priority","Aurigo-only (no RFP source)")))) -> Could Have | I33: =COUNTA(M33:V33) -> 1 | J33: =COUNTIF(M33:V33,"M") -> 0 | K33: =IF(I33=0,"Aurigo-only",IF(I33=1,"Single source",IF(I33=2,"Two sources",IF(I33<=4,"Common (3-4)","Broad (5+)")))) -> Single source | L33: =IF(J33>=3,"Tier 1: Must in 3+ sources",IF(J33=2,"Tier 2: Must in 2 sources",IF(J33=1,"Tier 3: Must in 1 source",IF(COUNTIF(M33:V33,"S")>0,"Tier 4: Should only",IF(COUNTIF(M33:V33,"C")>0,"Tier 5: Could only",IF(I33>0,"Tier 6: stated, no priority","Aurigo-only")))))) -> Tier 5: Could only | U33: C | W33: City of Regina RFI 25-00072: §4 Optional features – Financials [RFI – 'Optional software features'] ×3; §4 Optional features – General [RFI – 'Optional software features'] ×2
A34: CTY-031 | B34: City / County | C34: Scheduling & Resources | D34: Scheduling | E34: Work scheduling and field-crew assignment | F34: Schedule tasks in 15-minute increments; share the affected area with and assign work to field workers via ArcGIS Workforce; work orders to assign resources and monitor work. | G34: Integration | H34: =IF(COUNTIF(M34:V34,"M")>0,"Must Have",IF(COUNTIF(M34:V34,"S")>0,"Should Have",IF(COUNTIF(M34:V34,"C")>0,"Could Have",IF(COUNTA(M34:V34)>0,"Stated – no priority","Aurigo-only (no RFP source)")))) -> Could Have | I34: =COUNTA(M34:V34) -> 2 | J34: =COUNTIF(M34:V34,"M") -> 0 | K34: =IF(I34=0,"Aurigo-only",IF(I34=1,"Single source",IF(I34=2,"Two sources",IF(I34<=4,"Common (3-4)","Broad (5+)")))) -> Two sources | L34: =IF(J34>=3,"Tier 1: Must in 3+ sources",IF(J34=2,"Tier 2: Must in 2 sources",IF(J34=1,"Tier 3: Must in 1 source",IF(COUNTIF(M34:V34,"S")>0,"Tier 4: Should only",IF(COUNTIF(M34:V34,"C")>0,"Tier 5: Could only",IF(I34>0,"Tier 6: stated, no priority","Aurigo-only")))))) -> Tier 5: Could only | T34: E | U34: C | W34: City of Calgary RFI 25-006: §2.4 Functional capabilities [RFI – expected capability (no priority given)] City of Regina RFI 25-00072: §4 Optional features – Permit Management [RFI – 'Optional software features'] ×3 | X34: ArcGIS Workforce; existing work order systems
